Workbook

Sheet TCS
A1: Price | B1: Close | C1: Daily Ret. | D1: CMP | E1: CAGR | F1: P/E | G1: P/B | H1: Mkt. Cap to Sales | I1: Sales Growth | J1: Working Capital | K1: Current Ratio | L1: D/E | M1: Int. Cov. Ratio | N1: Market_Cap | O1: Current_Price | P1: Stock_P/E | Q1: Book_Value | R1: Face_Value | S1: Eq_Shares_PY | T1: Debt | U1: Cash_End_PY | V1: Sales | W1: Net_profit | X1: EPS | Y1: EBIT | Z1: Current_Assets | AA1: Current_Liabilities | AB1: Interest_Expense | AC1: Shareholders_Equity
A2: 44291 | B2: 2847.2424 | C2: =(B3-B2)/B2 -> 0.007965578 | D2: =O2 -> 2451 | E2: =((B1237/B2)^(1/5)-1) -> -0.029550057 | F2: =D2/X2 -> 18.568182 | G2: =D2/Q2 -> 8.3367347 | H2: =N2/V2 -> 3.3998397 | I2: 0.0214 | J2: =Z2-AA2 -> 79215 | K2: =Z2/AA2 -> 2.4328739 | L2: =T2/AC2 -> 0.10269514 | M2: =Y2/AB2 -> 80.035176 | N2: 886685 | O2: 2451 | P2: 17.4 | Q2: 294 | R2: 1 | S2: 362 | T2: 10932 | U2: 13286 | V2: 260802 | W2: 47963 | X2: 132 | Y2: 63708 | Z2: 134499 | AA2: 55284 | AB2: 796 | AC2: 106451
A3: 44292 | B3: 2869.9224 | C3: =(B4-B3)/B3 -> 0.0020522829 | J3: Cr | N3: Cr | T3: Cr | V3: Cr | W3: Cr | Y3: Cr | Z3: Cr | AA3: Cr | AB3: Cr
A4: 44293 | B4: 2875.8123 | C4: =(B5-B4)/B4 -> 0.014046134
A5: 44294 | B5: 2916.2063 | C5: =(B6-B5)/B5 -> 0.0014768793
A6: 44295 | B6: 2920.5132 | C6: =(B7-B6)/B6 -> -0.02278552
A7: 44298 | B7: 2853.9678 | C7: =(B8-B7)/B7 -> -0.043893028
A8: 44299 | B8: 2728.6985 | C8: =(B9-B8)/B8 -> 0.037016399
A9: 44301 | B9: 2829.7051 | C9: =(B10-B9)/B9 -> -0.007393918
A10: 44302 | B10: 2808.7825 | C10: =(B11-B10)/B10 -> -0.010437668
A11: 44305 | B11: 2779.4653 | C11: =(B12-B11)/B11 -> -0.005455748
A12: 44306 | B12: 2764.3013 | C12: =(B13-B12)/B12 -> -0.0081885062
A13: 44308 | B13: 2741.6658 | C13: =(B14-B13)/B13 -> -0.0029822269
A14: 44309 | B14: 2733.4895 | C14: =(B15-B14)/B14 -> -0.0027978703
A15: 44312 | B15: 2725.8416 | C15: =(B16-B15)/B15 -> 0.010062206
... A1236: 46113 | B1236: 2408.2 | C1236: =(B1237-B1236)/B1236 -> 0.017648036
A1237: 46114 | B1237: 2450.7 | C1237: -

Sheet Max Healthcare
A1: Price | B1: Close | C1: Daily Ret. | D1: CMP | E1: CAGR | F1: P/E | G1: P/B | H1: Mkt. Cap to Sales | I1: Sales Growth | J1: Working Capital | K1: Current Ratio | L1: D/E | M1: Int. Cov. Ratio | N1: Market_Cap | O1: Current_Price | P1: Stock_P/E | Q1: Book_Value | R1: Face_Value | S1: Eq_Shares_PY | T1: Debt | U1: Cash_End_PY | V1: Sales | W1: Net_profit | X1: EPS | Y1: EBIT | Z1: Current_Assets | AA1: Current_Liabilities | AB1: Interest_Expense | AC1: Shareholders_Equity
A2: 44291 | B2: 227.61382 | C2: =(B3-B2)/B2 -> 0.0083095689 | D2: =O2 -> 945 | E2: =((B1237/B2)^(1/5)-1) -> 0.32925977 | F2: =D2/X2 -> 64.726027 | G2: =D2/Q2 -> 9.1747573 | H2: =N2/V2 -> 11.293366 | I2: 0.300036 | J2: =Z2-AA2 -> -439 | K2: =Z2/AA2 -> 0.79272899 | L2: =T2/AC2 -> 0.32580581 | M2: =Y2/AB2 -> 11.424242 | N2: 91928 | O2: 945 | P2: 63 | Q2: 103 | R2: 10 | S2: 97.2 | T2: 3275 | U2: 1099 | V2: 8140 | W2: 1419 | X2: 14.6 | Y2: 1885 | Z2: 1679 | AA2: 2118 | AB2: 165 | AC2: 10052
A3: 44292 | B3: 229.50519 | C3: =(B4-B3)/B3 -> -0.024940276 | J3: Cr | N3: Cr | T3: Cr | V3: Cr | W3: Cr | Y3: Cr | Z3: Cr | AA3: Cr | AB3: Cr
A4: 44293 | B4: 223.78127 | C4: =(B5-B4)/B4 -> -0.011120961
A5: 44294 | B5: 221.2926 | C5: =(B6-B5)/B5 -> -0.015294741
A6: 44295 | B6: 217.90799 | C6: =(B7-B6)/B6 -> 0.0089082432
A7: 44298 | B7: 219.84917 | C7: =(B8-B7)/B7 -> -0.0038488246
A8: 44299 | B8: 219.00301 | C8: =(B9-B8)/B8 -> -0.0002272762
A9: 44301 | B9: 218.95323 | C9: =(B10-B9)/B9 -> 0.0095476308
A10: 44302 | B10: 221.04372 | C10: =(B11-B10)/B10 -> 0.052015346
A11: 44305 | B11: 232.54138 | C11: =(B12-B11)/B11 -> 0.0087756873
A12: 44306 | B12: 234.58209 | C12: =(B13-B12)/B12 -> -0.042011512
A13: 44308 | B13: 224.72694 | C13: =(B14-B13)/B13 -> -0.0057586026
A14: 44309 | B14: 223.43283 | C14: =(B15-B14)/B14 -> 0.0013366893
A15: 44312 | B15: 223.73149 | C15: =(B16-B15)/B15 -> 0.012013258
... A1236: 46113 | B1236: 958.90002 | C1236: =(B1237-B1236)/B1236 -> -0.014912972
A1237: 46114 | B1237: 944.59998 | C1237: -

Sheet Tata Power
A1: Price | B1: Close | C1: Daily Ret. | D1: CMP | E1: CAGR | F1: P/E | G1: P/B | H1: Mkt. Cap to Sales | I1: Sales Growth | J1: Working Capital | K1: Current Ratio | L1: D/E | M1: Int. Cov. Ratio | N1: Market_Cap | O1: Current_Price | P1: Stock_P/E | Q1: Book_Value | R1: Face_Value | S1: Eq_Shares_PY | T1: Debt | U1: Cash_End_PY | V1: Sales | W1: Net_profit | X1: EPS | Y1: EBIT | Z1: Current_Assets | AA1: Current_Liabilities | AB1: Interest_Expense | AC1: Shareholders_Equity
A2: 44291 | B2: 99.286324 | C2: =(B3-B2)/B2 -> 0.013062508 | D2: =O2 -> 385 | E2: =((B1237/B2)^(1/5)-1) -> 0.31133683 | F2: =D2/X2 -> 32.352941 | G2: =D2/Q2 -> 3.2627119 | H2: =N2/V2 -> 1.9036426 | I2: 0.065 | J2: =Z2-AA2 -> -11314 | K2: =Z2/AA2 -> 0.72084875 | L2: =T2/AC2 -> 1.8594587 | M2: =Y2/AB2 -> 3.9001009 | N2: 123021 | O2: 385 | P2: 32.5 | Q2: 118 | R2: 1 | S2: 320 | T2: 70083 | U2: 9152 | V2: 64624 | W2: 5008 | X2: 11.9 | Y2: 11595 | Z2: 29216 | AA2: 40530 | AB2: 2973 | AC2: 37690
A3: 44292 | B3: 100.58325 | C3: =(B4-B3)/B3 -> -0.0023878065 | J3: Cr | N3: Cr | T3: Cr | V3: Cr | W3: Cr | Y3: Cr | Z3: Cr | AA3: Cr | AB3: Cr
A4: 44293 | B4: 100.34308 | C4: =(B5-B4)/B4 -> 0.0047870435
A5: 44294 | B5: 100.82343 | C5: =(B6-B5)/B5 -> -0.008099127
A6: 44295 | B6: 100.00684 | C6: =(B7-B6)/B6 -> -0.11431324
A7: 44298 | B7: 88.574738 | C7: =(B8-B7)/B7 -> 0.039587954
A8: 44299 | B8: 92.08123 | C8: =(B9-B8)/B8 -> -0.017735951
A9: 44301 | B9: 90.448082 | C9: =(B10-B9)/B9 -> 0.031863963
A10: 44302 | B10: 93.330116 | C10: =(B11-B10)/B10 -> -0.034482728
A11: 44305 | B11: 90.111839 | C11: =(B12-B11)/B11 -> -0.0021322245
A12: 44306 | B12: 89.919701 | C12: =(B13-B12)/B12 -> 0.0069443673
A13: 44308 | B13: 90.544136 | C13: =(B14-B13)/B13 -> 0.014854226
A14: 44309 | B14: 91.889099 | C14: =(B15-B14)/B14 -> 0.0067955332
A15: 44312 | B15: 92.513535 | C15: =(B16-B15)/B15 -> 0.017653238
... A1236: 46113 | B1236: 380.20001 | C1236: =(B1237-B1236)/B1236 -> 0.012624902
A1237: 46114 | B1237: 385 | C1237: -

Sheet Hindustan Unilever
A1: Price | B1: Close | C1: Daily Ret. | D1: CMP | E1: CAGR | F1: P/E | G1: P/B | H1: Mkt. Cap to Sales | I1: Sales Growth | J1: Working Capital | K1: Current Ratio | L1: D/E | M1: Int. Cov. Ratio | N1: Market_Cap | O1: Current_Price | P1: Stock_P/E | Q1: Book_Value | R1: Face_Value | S1: Eq_Shares_PY | T1: Debt | U1: Cash_End_PY | V1: Sales | W1: Net_profit | X1: EPS | Y1: EBIT | Z1: Current_Assets | AA1: Current_Liabilities | AB1: Interest_Expense | AC1: Shareholders_Equity
A2: 44291 | B2: 2182.4077 | C2: =(B3-B2)/B2 -> 0.014790234 | D2: =O2 -> 2065 | E2: =((B1237/B2)^(1/5)-1) -> -0.010970027 | F2: =D2/X2 -> 33.414239 | G2: =D2/Q2 -> 9.9758454 | H2: =N2/V2 -> 7.5182976 | I2: 0.0197 | J2: =Z2-AA2 -> 1669 | K2: =Z2/AA2 -> 1.0905687 | L2: =T2/AC2 -> 0.024119386 | M2: =Y2/AB2 -> 36.270886 | N2: 485261 | O2: 2065 | P2: 44.5 | Q2: 207 | R2: 1 | S2: 235 | T2: 1175 | U2: 7559 | V2: 64544 | W2: 14540 | X2: 61.8 | Y2: 14327 | Z2: 20097 | AA2: 18428 | AB2: 395 | AC2: 48716
A3: 44292 | B3: 2214.686 | C3: =(B4-B3)/B3 -> -0.0012665143 | J3: Cr | N3: Cr | T3: Cr | V3: Cr | W3: Cr | Y3: Cr | Z3: Cr | AA3: Cr | AB3: Cr
A4: 44293 | B4: 2211.8811 | C4: =(B5-B4)/B4 -> 0.0019332518
A5: 44294 | B5: 2216.1572 | C5: =(B6-B5)/B5 -> 0.027428509
A6: 44295 | B6: 2276.9431 | C6: =(B7-B6)/B6 -> -0.0056544038
A7: 44298 | B7: 2264.0684 | C7: =(B8-B7)/B7 -> -0.0030870348
A8: 44299 | B8: 2257.0791 | C8: =(B9-B8)/B8 -> 0.0025465668
A9: 44301 | B9: 2262.8269 | C9: =(B10-B9)/B9 -> -0.00071111531
A10: 44302 | B10: 2261.2178 | C10: =(B11-B10)/B10 -> -0.0090488524
A11: 44305 | B11: 2240.7563 | C11: =(B12-B11)/B11 -> -0.016087577
A12: 44306 | B12: 2204.708 | C12: =(B13-B12)/B12 -> -0.020042226
A13: 44308 | B13: 2160.5208 | C13: =(B14-B13)/B13 -> -0.017727795
A14: 44309 | B14: 2122.2195 | C14: =(B15-B14)/B14 -> 0.022922687
A15: 44312 | B15: 2170.8665 | C15: =(B16-B15)/B15 -> 0.0081334981
... A1236: 46113 | B1236: 2064.7 | C1236: =(B1237-B1236)/B1236 -> 0.00029064642
A1237: 46114 | B1237: 2065.3 | C1237: -

Sheet State Bank of India
A1: Price | B1: Close | C1: Daily Ret. | D1: CMP | E1: CAGR | F1: P/E | G1: P/B | H1: Mkt. Cap to Sales | I1: Sales Growth | J1: Working Capital | K1: Current Ratio | L1: D/E | M1: Int. Cov. Ratio | N1: Market_Cap | O1: Current_Price | P1: Stock_P/E | Q1: Book_Value | R1: Face_Value | S1: Eq_Shares_PY | T1: Debt | U1: Cash_End_PY | V1: Sales | W1: Net_profit | X1: EPS | Y1: EBIT | Z1: Current_Assets | AA1: Current_Liabilities | AB1: Interest_Expense | AC1: Shareholders_Equity
A2: 44291 | B2: 326.22644 | C2: =(B3-B2)/B2 -> -0.0084853881 | D2: =O2 -> 1018 | E2: =((B1237/B2)^(1/5)-1) -> 0.25568252 | F2: =D2/X2 -> 11.101418 | G2: =D2/Q2 -> 1.5881435 | H2: =N2/V2 -> 1.8383396 | I2: 0.1178 | J2: =Z2-AA2 -> -33161 | K2: =Z2/AA2 -> 0.95942561 | L2: =T2/AC2 -> 11.333957 | M2: =Y2/AB2 -> 1.4384652 | N2: 940046 | O2: 1018 | P2: 11.6 | Q2: 641 | R2: 1 | S2: 892 | T2: 6452558 | U2: 206767 | V2: 511356 | W2: 86537 | X2: 91.7 | Y2: 425101 | Z2: 784128 | AA2: 817289 | AB2: 295524 | AC2: 569312
A3: 44292 | B3: 323.45828 | C3: =(B4-B3)/B3 -> 0.022821413 | J3: Cr | N3: Cr | T3: Cr | V3: Cr | W3: Cr | Y3: Cr | Z3: Cr | AA3: Cr | AB3: Cr
A4: 44293 | B4: 330.84006 | C4: =(B5-B4)/B4 -> -0.0082275871
A5: 44294 | B5: 328.11804 | C5: =(B6-B5)/B5 -> -0.007311632
A6: 44295 | B6: 325.71896 | C6: =(B7-B6)/B6 -> -0.068413485
A7: 44298 | B7: 303.43539 | C7: =(B8-B7)/B7 -> 0.036946804
A8: 44299 | B8: 314.64636 | C8: =(B9-B8)/B8 -> 0.0049853875
A9: 44301 | B9: 316.215 | C9: =(B10-B9)/B9 -> -0.0081704479
A10: 44302 | B10: 313.63138 | C10: =(B11-B10)/B10 -> -0.025742836
A11: 44305 | B11: 305.55762 | C11: =(B12-B11)/B11 -> -0.0049827656
A12: 44306 | B12: 304.0351 | C12: =(B13-B12)/B12 -> 0.021699609
A13: 44308 | B13: 310.63254 | C13: =(B14-B13)/B13 -> -0.00059397924
A14: 44309 | B14: 310.44803 | C14: =(B15-B14)/B14 -> 0.023331621
A15: 44312 | B15: 317.69128 | C15: =(B16-B15)/B15 -> 0.025413953
... A1236: 46113 | B1236: 1017.8 | C1236: =(B1237-B1236)/B1236 -> 0.00058954277
A1237: 46114 | B1237: 1018.4 | C1237: -

Sheet FUNDAMENTALS
C2: Name | D2: CMP | E2: CAGR | F2: P/E | G2: P/B | H2: Mkt. Cap to Sales | I2: Sales Growth | J2: Working Capital | K2: Current Ratio | L2: D/E | M2: Int. Cov. Ratio
C3: TCS | D3: =TCS!D2 -> 2451 | E3: =TCS!E2 -> -0.029550057 | F3: =TCS!F2 -> 18.568182 | G3: =TCS!G2 -> 8.3367347 | H3: =TCS!H2 -> 3.3998397 | I3: =TCS!I2 -> 0.0214 | J3: =TCS!J2 -> 79215 | K3: =TCS!K2 -> 2.4328739 | ... M3: =TCS!M2 -> 80.035176
C4: MAX | D4: ='Max Healthcare'!D2 -> 945 | E4: ='Max Healthcare'!E2 -> 0.32925977 | F4: ='Max Healthcare'!F2 -> 64.726027 | G4: ='Max Healthcare'!G2 -> 9.1747573 | H4: ='Max Healthcare'!H2 -> 11.293366 | I4: ='Max Healthcare'!I2 -> 0.300036 | J4: ='Max Healthcare'!J2 -> -439 | K4: ='Max Healthcare'!K2 -> 0.79272899 | ... M4: ='Max Healthcare'!M2 -> 11.424242
C5: Tata Power | D5: ='Tata Power'!D2 -> 385 | E5: ='Tata Power'!E2 -> 0.31133683 | F5: ='Tata Power'!F2 -> 32.352941 | G5: ='Tata Power'!G2 -> 3.2627119 | H5: ='Tata Power'!H2 -> 1.9036426 | I5: ='Tata Power'!I2 -> 0.065 | J5: ='Tata Power'!J2 -> -11314 | K5: ='Tata Power'!K2 -> 0.72084875 | ... M5: ='Tata Power'!M2 -> 3.9001009
C6: HUL | D6: ='Hindustan Unilever'!D2 -> 2065 | E6: ='Hindustan Unilever'!E2 -> -0.010970027 | F6: ='Hindustan Unilever'!F2 -> 33.414239 | G6: ='Hindustan Unilever'!G2 -> 9.9758454 | H6: ='Hindustan Unilever'!H2 -> 7.5182976 | I6: ='Hindustan Unilever'!I2 -> 0.0197 | J6: ='Hindustan Unilever'!J2 -> 1669 | K6: ='Hindustan Unilever'!K2 -> 1.0905687 | ... M6: ='Hindustan Unilever'!M2 -> 36.270886
C7: SBI | D7: ='State Bank of India'!D2 -> 1018 | E7: ='State Bank of India'!E2 -> 0.25568252 | F7: ='State Bank of India'!F2 -> 11.101418 | G7: ='State Bank of India'!G2 -> 1.5881435 | H7: ='State Bank of India'!H2 -> 1.8383396 | I7: ='State Bank of India'!I2 -> 0.1178 | J7: ='State Bank of India'!J2 -> -33161 | K7: ='State Bank of India'!K2 -> 0.95942561 | ... M7: ='State Bank of India'!M2 -> 1.4384652

Sheet Financials
