Workbook
Name UPDATE: 'Data Sheet'!$E$1

Sheet TITAN DCF
B2: TITAN Company Ltd.
B4: Ticker | C4: TITAN
B6: INR | C6: 4184
B9: Period | C9: 2023 | D9: =C9+1 -> 2024 | E9: =D9+1 -> 2025 | F9: =E9+1 -> 2026 | G9: =F9+1 -> 2027 | H9: =G9+1 -> 2028 | I9: =H9+1 -> 2029 | J9: =I9+1 -> 2030 | K9: =J9+1 -> 2031 | L9: =K9+1 -> 2032
B10: Year | G10: 1 | H10: =G10+1 -> 2 | I10: =H10+1 -> 3 | J10: =I10+1 -> 4 | K10: =J10+1 -> 5 | L10: =K10+1 -> 6
B11: Growth | D11: =D12/C12-1 -> 0.25900185 | E11: =E12/D12-1 -> 0.18346253 | F11: =F12/E12-1 -> 0.44872304 | G11: =30% -> 0.3 | H11: =G11*(1-0.1) -> 0.27 | I11: =H11*(1-0.1) -> 0.243 | J11: =I11*(1-0.1) -> 0.2187 | K11: =J11*(1-0.1) -> 0.19683 | L11: =K11*(1-0.1) -> 0.177147
B12: Revenue | C12: ='Data Sheet'!H17 -> 40575 | D12: ='Data Sheet'!I17 -> 51084 | E12: ='Data Sheet'!J17 -> 60456 | F12: ='Data Sheet'!K17 -> 87584 | G12: =F12*(1+G11) -> 113859.2 | H12: =G12*(1+H11) -> 144601.18 | I12: =H12*(1+I11) -> 179739.27 | J12: =I12*(1+J11) -> 219048.25 | K12: =J12*(1+K11) -> 262163.52 | L12: =K12*(1+L11) -> 308605
B13: EBITDA | C13: ='Data Sheet'!T19+'Data Sheet'!T21 -> 5323 | D13: ='Data Sheet'!U19+'Data Sheet'!U21 -> 5876 | E13: ='Data Sheet'!V19+'Data Sheet'!V21 -> 6387 | F13: ='Data Sheet'!W19+'Data Sheet'!W21 -> 9181 | G13: =G12*10.5% -> 11955.216 | H13: =H12*10.5% -> 15183.124 | I13: =I12*10.5% -> 18872.624 | J13: =J12*10.5% -> 23000.066 | K13: =K12*10.5% -> 27527.169 | L13: =L12*10.5% -> 32403.525
B14: Less: Depreciation & Ammortisation | C14: ='Data Sheet'!T21 -> 441 | D14: ='Data Sheet'!U21 -> 584 | E14: ='Data Sheet'!V21 -> 693 | F14: ='Data Sheet'!W21 -> 826 | G14: =G12*1% -> 1138.592 | H14: =H12*1% -> 1446.0118 | I14: =I12*1% -> 1797.3927 | J14: =J12*1% -> 2190.4825 | K14: =K12*1% -> 2621.6352 | L14: =L12*1% -> 3086.05
B15: EBIT | C15: =C13-C14 -> 4882 | D15: =D13-D14 -> 5292 | E15: =E13-E14 -> 5694 | F15: =F13-F14 -> 8355 | G15: =G12*9.95% -> 11328.99 | H15: =H12*9.95% -> 14387.818 | I15: =I12*9.95% -> 17884.058 | J15: =J12*9.95% -> 21795.301 | K15: =K12*9.95% -> 26085.27 | L15: =L12*9.95% -> 30706.197
B16: Less: Tax | C16: ='Data Sheet'!T24 -> 1173 | D16: ='Data Sheet'!U24 -> 1127 | E16: ='Data Sheet'!V24 -> 1198 | F16: ='Data Sheet'!W24 -> 1728 | G16: =G15*21.01% -> 2380.2209 | H16: =H15*21.01% -> 3022.8805 | I16: =I15*21.01% -> 3757.4405 | J16: =J15*21.01% -> 4579.1927 | K16: =K15*21.01% -> 5480.5152 | L16: =L15*21.01% -> 6451.3721
B17: EBIT(1-Tax) | C17: =C15-C16 -> 3709 | D17: =D15-D16 -> 4165 | E17: =E15-E16 -> 4496 | F17: =F15-F16 -> 6627 | G17: =G15-G16 -> 8948.7695 | H17: =H15-H16 -> 11364.937 | I17: =I15-I16 -> 14126.617 | J17: =J15-J16 -> 17216.108 | ... L17: =L15-L16 -> 24254.825
B18: Add: Depreciation & Ammortisation | C18: =C14 -> 441 | D18: =D14 -> 584 | E18: =E14 -> 693 | F18: =F14 -> 826 | G18: =G14 -> 1138.592 | H18: =H14 -> 1446.0118 | I18: =I14 -> 1797.3927 | J18: =J14 -> 2190.4825 | ... L18: =L14 -> 3086.05
B19: NOPAT | C19: =C17+C18 -> 4150 | D19: =D17+D18 -> 4749 | E19: =E17+E18 -> 5189 | F19: =F17+F18 -> 7453 | G19: =G17+G18 -> 10087.362 | H19: =H17+H18 -> 12810.949 | I19: =I17+I18 -> 15924.01 | J19: =J17+J18 -> 19406.591 | ... L19: =L17+L18 -> 27340.875
B20: Less: Capex | C20: =-'Data Sheet'!V93 -> 432 | D20: =-'Data Sheet'!W93 -> 691 | E20: =-'Data Sheet'!X93 -> 494 | F20: =-'Data Sheet'!Y93 -> 902 | G20: =G12*1.05% -> 1195.5216 | H20: =H12*1.05% -> 1518.3124 | I20: =I12*1.05% -> 1887.2624 | J20: =J12*1.05% -> 2300.0066 | K20: =K12*1.05% -> 2752.7169 | L20: =L12*1.05% -> 3240.3525
B21: Less: Net Change in Working Capital | C21: =C51 -> 3164 | D21: =D51 -> 2615 | E21: =E51 -> 8630 | F21: =F51 -> 13506 | G21: =G51 -> 7877.1016 | H21: =H51 -> 13141.467 | I21: =I51 -> 15020.697 | J21: =J51 -> 16803.654 | ... L21: =L51 -> 19852.629
B22: Free Cash Flow to the Firm | C22: =C19-C20-C21 -> 554 | D22: =D19-D20-D21 -> 1443 | E22: =E19-E20-E21 -> -3935 | F22: =F19-F20-F21 -> -6955 | G22: =G19-G20-G21 -> 1014.7383 | H22: =H19-H20-H21 -> -1848.8307 | I22: =I19-I20-I21 -> -983.94987 | J22: =J19-J20-J21 -> 302.93002 | ... L22: =L19-L20-L21 -> 4247.8937
B23: Discount Rate (r)
B24: PV of Free Cash Flows | G24: =G22/(1+$D$43)^G10 -> 903.14918 | H24: =H22/(1+$D$43)^H10 -> -1464.563 | I24: =I22/(1+$D$43)^I10 -> -693.72814 | J24: =J22/(1+$D$43)^J10 -> 190.09211 | K24: =K22/(1+$D$43)^K10 -> 1140.9821 | L24: =L22/(1+$D$43)^L10 -> 2111.574
B26: WACC | F26: Sum of PV of FCFF | G26: =SUM(G24:L24) -> 2187.5063 | I26: Market Cap. In Cr.
B27: WACC = (% Equity x Cost of Equity) + (% Debt x Cost of Debt x (1 -Tax rate)) | I27: =D37 -> 372376
B28: Cost of Equity = Risk Free Rate + (Beta x (Expected Market Return - Risk Free Rate)) | F28: Terminal Value
F29: Terminal Growth Rate | G29: 0.07 | I29: Intrinsic Value DCF
B30: Cost of Debt | F30: Terminal Value | G30: =L22*(1+$G$29)/(D43-$G$29) -> 84869.733 | I30: =G40 -> 35247.174
B31: Debt | D31: ='Data Sheet'!Y59 -> 14551 | F31: PV of Terminal Value | G31: =G30/(1+D43)^L10 -> 42187.668
B32: % Debt | D32: =D31/(D31+D37) -> 0.037606577 | I32: Current Market Price
B33: Cost of Debt | D33: ='Data Sheet'!AA22 -> 0.081094083 | F33: Enterprise Value 1 + 2 | I33: =C6 -> 4184
B34: Tax Rate | D34: 0.2115 | F34: Enterprise Value | G34: =G31+G26 -> 44375.174
F35: Add: Cash | G35: ='Data Sheet'!K69 -> 1917 | I35: Implied Share Price
B36: Cost of Equity | D36: =D39+D40*(D41-D39) -> 0.125885 | F36: Add: Other Non Operating Assets | G36: ='Data Sheet'!Y68 -> 3506 | I36: =G42 -> 396.03566
B37: Equity | D37: =(C6*'Data Sheet'!J70)/10000000 -> 372376 | F37: Less: Debt | G37: =D31 -> 14551
B38: % Equity | D38: =D37/(D31+D37) -> 0.96239342 | F38: Less: Minority Interest | G38: 0 | J38: WACC
B39: Risk Free Rate | D39: 0.0731 | I39: =G42 -> 396.03566 | J39: =K39-0.5% -> 0.10855556 | K39: =L39-0.5% -> 0.11355556 | L39: =M39-0.5% -> 0.11855556 | M39: 0.12355556 | N39: =M39+0.5% -> 0.12855556 | O39: =N39+0.5% -> 0.13355556 | P39: =O39+0.5% -> 0.13855556
B40: Beta | D40: 1.15 | F40: Equity Value (DCF) | G40: =G34+G35+G36-G37 -> 35247.174 | I40: =I41-0.5% -> 0.06 | J40: 485.8299 | K40: 419.0362 | L40: 363.92041 | M40: 317.71926 | N40: 278.47586 | O40: 244.76559 | P40: 215.52671
B41: Market Return | D41: 0.119 | F41: No of shares | G41: ='Data Sheet'!Y57 -> 89 | I41: =I42-0.5% -> 0.065 | J41: 553.2336 | K41: 472.63445 | L41: 407.38074 | M41: 353.53378 | N41: 308.39456 | O41: 270.05166 | P41: 237.11359
F42: Value Per Share | G42: =G40/G41 -> 396.03566 | H42: TGR | I42: 0.07 | J42: 638.11952 | K42: 538.53842 | L42: 459.79172 | M42: 396.03566 | N42: 343.42271 | O42: 299.31631 | P42: 261.8493
B43: WACC | D43: =(D36*D38)+(D33*D32)*(1-D34) -> 0.12355556 | F43: CMP | G43: =C6 -> 4184 | I43: =I42+0.5% -> 0.075 | J43: 748.30256 | K43: 621.53564 | L43: 524.23583 | M43: 447.29079 | N43: 384.99138 | O43: 333.57872 | P43: 290.47698
F44: OV/UV By | G44: =G42/G43-1 -> -0.90534521 | I44: 0.117336 | J44: -3348.3149 | K44: -7475.1036 | L44: 22249.162 | M44: 4184.2808 | N44: 2221.9453 | O44: 1470.3475 | P44: 1073.6042
B46: Change in Working Capital Calculation | C46: 2023 | D46: =C46+1 -> 2024 | E46: =D46+1 -> 2025 | F46: =E46+1 -> 2026 | G46: =F46+1 -> 2027 | H46: =G46+1 -> 2028 | I46: =H46+1 -> 2029 | J46: =I46+1 -> 2030 | K46: =J46+1 -> 2031 | L46: =K46+1 -> 2032
B47: Debtors/Receivables | C47: ='Data Sheet'!V71 -> 674 | D47: ='Data Sheet'!W71 -> 1018 | E47: ='Data Sheet'!X71 -> 1068 | F47: ='Data Sheet'!Y71 -> 916 | G47: - | H47: - | I47: - | J47: - | K47: - | L47: -
B48: Payables | C48: ='Data Sheet'!V62 -> 1214 | D48: ='Data Sheet'!W62 -> 1410 | E48: ='Data Sheet'!X62 -> 1963 | F48: ='Data Sheet'!Y62 -> 2864 | G48: - | H48: - | I48: - | J48: - | K48: - | L48: -
B49: (Others) + | C49: ='Data Sheet'!V70 -> 16584 | D49: ='Data Sheet'!W70 -> 19051 | E49: ='Data Sheet'!X70 -> 28184 | F49: ='Data Sheet'!Y70 -> 42743 | G49: - | H49: - | I49: - | J49: - | K49: - | L49: -
B50: Working Capital | C50: =C47+C49-C48 -> 16044 | D50: =D47+D49-D48 -> 18659 | E50: =E47+E49-E48 -> 27289 | F50: =F47+F49-F48 -> 40795 | G50: =G12*G52 -> 48672.102 | H50: =H12*H52 -> 61813.569 | I50: =I12*I52 -> 76834.266 | J50: =J12*J52 -> 93637.92 | K50: =K12*K52 -> 112068.67 | L50: =L12*L52 -> 131921.3
B51: Change in Working Capital | C51: =C50-'Data Sheet'!K73 -> 3164 | D51: =D50-C50 -> 2615 | E51: =E50-D50 -> 8630 | F51: =F50-E50 -> 13506 | G51: =G50-F50 -> 7877.1016 | H51: =H50-G50 -> 13141.467 | I51: =I50-H50 -> 15020.697 | J51: =J50-I50 -> 16803.654 | K51: =K50-J50 -> 18430.752 | L51: =L50-K50 -> 19852.629
B52: Working Capital % Sales | C52: =C50/C12 -> 0.3954159 | D52: =D50/D12 -> 0.36526114 | E52: =E50/E12 -> 0.45138613 | F52: =F50/F12 -> 0.46578142 | G52: =AVERAGE($D$52:$F$52) -> 0.42747623 | H52: =G52 -> 0.42747623 | I52: =H52 -> 0.42747623 | J52: =I52 -> 0.42747623 | K52: =J52 -> 0.42747623 | L52: =K52 -> 0.42747623
B54: Working Capital = Debtors + Inventories - payables

Sheet Data Sheet
A1: COMPANY NAME | B1: TITAN COMPANY LTD | E1: =IF(B2<>B3, "A NEW VERSION OF THE WORKSHEET IS AVAILABLE", "")
A2: LATEST VERSION | B2: 2.1 | E2: PLEASE DO NOT MAKE ANY CHANGES TO THIS SHEET
A3: CURRENT VERSION | B3: 2.1
A5: META
A6: Number of shares | B6: =IF(B9>0, B9/B8, 0) -> 88.778616
A7: Face Value | B7: 1
A8: Current Price | B8: 4184
A9: Market Capitalization | B9: 371449.73
A15: PROFIT & LOSS
A16: Report Date | B16: 42825 | C16: 43190 | D16: 43555 | E16: 43921 | F16: 44286 | G16: 44651 | H16: 45016 | I16: 45382 | J16: 45747 | K16: 46112 | M16: Narration | N16: 42825 | O16: 43190 | P16: 43555 | Q16: 43921 | R16: 44286 | S16: 44651 | T16: 45016 | U16: 45382 | V16: 45747 | W16: 46112 | X16: Trailing | Y16: Best Case | Z16: Worst Case
A17: Sales | B17: 13260.83 | C17: 16119.77 | D17: 19778.52 | E17: 21052 | F17: 21644 | G17: 28799 | H17: 40575 | I17: 51084 | J17: 60456 | K17: 87584 | M17: Sales | N17: 13260.83 | O17: 16119.77 | P17: 19778.52 | Q17: 21052 | R17: 21644 | S17: 28799 | T17: 40575 | U17: 51084 | V17: 60456 | W17: 87584 | X17: 87584 | Y17: 126884.96 | Z17: 108023.86
A18: Raw Material Cost | B18: 9821.14 | C18: 12664.83 | D18: 15170.66 | E18: 16033 | F18: 16292 | G18: 26436 | H18: 32589 | I18: 42103 | J18: 55271 | K18: 80243 | M18: Expenses | N18: 12096.93 | O18: 14475.57 | P18: 17784.73 | Q18: 18589 | R18: 19919 | S18: 25455 | T18: 35693 | U18: 45792 | V18: 54762 | W18: 79229 | X18: 79228 | Y18: 114560.57 | Z18: 97717.779
A19: Change in Inventory | B19: 313.71 | C19: 978.61 | D19: 776.41 | E19: 878 | F19: -122 | G19: 4795 | H19: 2234 | I19: 2671 | J19: 7815 | K19: 9936 | M19: Operating Profit | N19: 1163.9 | O19: 1644.2 | P19: 1993.79 | Q19: 2463 | R19: 1725 | S19: 3344 | T19: 4882 | U19: 5292 | V19: 5694 | W19: 8355 | X19: 8356 | Y19: 12324.391 | Z19: 10306.076
A20: Power and Fuel | B20: 43.84 | C20: 45.32 | D20: 48.51 | E20: 52 | F20: 37 | G20: 45 | H20: 59 | I20: 71 | J20: 78 | M20: Other Income | N20: -42.38 | O20: 69.93 | P20: 178.48 | Q20: 153 | R20: 180 | S20: 177 | T20: 306 | U20: 534 | V20: 487 | W20: 452 | X20: 452 | Y20: 0 | Z20: 0
A21: Other Mfr. Exp | B21: 160.42 | C21: 124.83 | D21: 193.28 | E21: 215 | F21: 141 | G21: 183 | H21: 225 | I21: 286 | J21: 326 | M21: Depreciation | N21: 110.53 | O21: 131.43 | P21: 162.84 | Q21: 348 | R21: 375 | S21: 399 | T21: 441 | U21: 584 | V21: 693 | W21: 826 | X21: 826 | Y21: 826 | Z21: 826
A22: Employee Cost | B22: 894.32 | C22: 906.26 | D22: 1024.44 | E22: 1204 | F22: 1069 | G22: 1356 | H22: 1656 | I22: 1875 | J22: 2164 | K22: 2681 | M22: Interest | N22: 37.74 | O22: 52.92 | P22: 52.54 | Q22: 166 | R22: 203 | S22: 218 | T22: 300 | U22: 619 | V22: 953 | W22: 1180 | X22: 1180 | Y22: 1180 | Z22: 1180 | AA22: =W22/Y59 -> 0.081094083 | AB22: =T22/T19 -> 0.061450225 | AC22: =U22/U19 -> 0.11696901 | AD22: =V22/V19 -> 0.16736916 | AE22: =W22/W19 -> 0.14123279 | AF22: =X22/X19 -> 0.14121589 | AG22: =Y22/Y19 -> 0.095745098 | AH22: =Z22/Z19 -> 0.11449557 | AJ22: =MEDIAN(AB22:AH22) -> 0.11696901
A23: Selling and admin | B23: 1211.16 | C23: 1277.81 | D23: 1454.32 | E23: 1470 | F23: 1029 | G23: 1697 | H23: 2715 | I23: 3249 | J23: 3488 | K23: 1535 | M23: Profit before tax | N23: 973.25 | O23: 1529.78 | P23: 1956.89 | Q23: 2102 | R23: 1327 | S23: 2904 | T23: 4447 | U23: 4623 | V23: 4535 | W23: 6801 | X23: 6802 | Y23: 10318.391 | Z23: 8300.0757
A24: Other Expenses | B24: 279.76 | C24: 435.13 | D24: 669.93 | E24: 493 | F24: 1229 | G24: 533 | H24: 683 | I24: 879 | J24: 1250 | K24: 4706 | M24: Tax | N24: 275.97 | O24: 427.87 | P24: 568.24 | Q24: 609 | R24: 353 | S24: 706 | T24: 1173 | U24: 1127 | V24: 1198 | W24: 1728 | X24: 1728 | Y24: 0.25404293 | Z24: 0.25404293
A25: Other Income | B25: -42.38 | C25: 69.93 | D25: 178.48 | E25: 153 | F25: 180 | G25: 177 | H25: 306 | I25: 534 | J25: 487 | K25: 452 | M25: Net profit | N25: 711.47 | O25: 1130.09 | P25: 1404.15 | Q25: 1501 | R25: 973 | S25: 2173 | T25: 3250 | U25: 3496 | V25: 3337 | W25: 5073 | X25: 5074 | Y25: 7697.0765 | Z25: 6191.5002
A26: Depreciation | B26: 110.53 | C26: 131.43 | D26: 162.84 | E26: 348 | F26: 375 | G26: 399 | H26: 441 | I26: 584 | J26: 693 | K26: 826 | M26: EPS | N26: 8.0138545 | O26: 12.729106 | P26: 15.816062 | Q26: 16.906961 | R26: 10.959676 | S26: 24.476233 | T26: 36.607344 | U26: 39.378238 | V26: 37.587294 | W26: 57.141248 | X26: 57.153403 | Y26: 86.699668 | Z26: 69.740895
A27: Interest | B27: 37.74 | C27: 52.92 | D27: 52.54 | E27: 166 | F27: 203 | G27: 218 | H27: 300 | I27: 619 | J27: 953 | K27: 1180 | M27: Price to earning | N27: 57.743749 | O27: 74.027196 | P27: 72.195594 | Q27: 55.225773 | R27: 142.16205 | S27: 103.61684 | T27: 68.69933 | U27: 96.545711 | V27: 81.499614 | W27: 69.151447 | X27: 73.20649 | Y27: 80.100816 | Z27: 73.20649
A28: Profit before tax | B28: 973.25 | C28: 1529.78 | D28: 1956.89 | E28: 2102 | F28: 1327 | G28: 2904 | H28: 4447 | I28: 4623 | J28: 4535 | K28: 6801 | M28: Price | N28: 462.75 | O28: 942.3 | P28: 1141.85 | Q28: 933.7 | R28: 1558.05 | S28: 2536.15 | T28: 2514.9 | U28: 3801.8 | V28: 3063.35 | W28: 3951.4 | X28: 4184 | Y28: 6944.7141 | Z28: 5105.4861
A29: Tax | B29: 275.97 | C29: 427.87 | D29: 568.24 | E29: 609 | F29: 353 | G29: 706 | H29: 1173 | I29: 1127 | J29: 1198 | K29: 1728
A30: Net profit | B30: 711.47 | C30: 1130.09 | D30: 1404.15 | E30: 1501 | F30: 973 | G30: 2173 | H30: 3250 | I30: 3496 | J30: 3337 | K30: 5073
A31: Dividend Amount | B31: 230.83 | C31: 332.92 | D31: 443.9 | E31: 356 | F31: 356 | G31: 667.5 | H31: 890 | I31: 979 | J31: 979 | K31: 1335
A40: Quarters
A41: Report Date | B41: 45291 | C41: 45382 | D41: 45473 | E41: 45565 | F41: 45657 | G41: 45747 | H41: 45838 | I41: 45930 | J41: 46022 | K41: 46112
A42: Sales | B42: 14164 | C42: 12494 | D42: 13266 | E42: 14534 | F42: 17740 | G42: 14916 | H42: 16523 | I42: 18725 | J42: 25416 | K42: 26920
A43: Expenses | B43: 12599 | C43: 11303 | D43: 12019 | E43: 13298 | F43: 16066 | G43: 13379 | H43: 14693 | I43: 16850 | J43: 22703 | K43: 24982
A44: Other Income | B44: 136 | C44: 159 | D44: 120 | E44: 123 | F44: 128 | G44: 116 | H44: 105 | I44: 113 | J44: -1 | K44: 235
A45: Depreciation | B45: 154 | C45: 158 | D45: 164 | E45: 171 | F45: 175 | G45: 183 | H45: 184 | I45: 189 | J45: 207 | K45: 246
A46: Interest | B46: 169 | C46: 201 | D46: 230 | E46: 240 | F46: 231 | G46: 252 | H46: 271 | I46: 277 | J46: 282 | K46: 350
A47: Profit before tax | B47: 1378 | C47: 991 | D47: 973 | E47: 948 | F47: 1396 | G47: 1218 | H47: 1480 | I47: 1522 | J47: 2223 | K47: 1577
A48: Tax | B48: 325 | C48: 220 | D48: 258 | E48: 244 | F48: 349 | G48: 347 | H48: 389 | I48: 402 | J48: 539 | K48: 398
A49: Net profit | B49: 1053 | C49: 771 | D49: 715 | E49: 704 | F49: 1047 | G49: 871 | H49: 1091 | I49: 1120 | J49: 1684 | K49: 1179
A50: Operating Profit | B50: 1565 | C50: 1191 | D50: 1247 | E50: 1236 | F50: 1674 | G50: 1537 | H50: 1830 | I50: 1875 | J50: 2713 | K50: 1938
A55: BALANCE SHEET
A56: Report Date | B56: 42825 | C56: 43190 | D56: 43555 | E56: 43921 | F56: 44286 | G56: 44651 | H56: 45016 | I56: 45382 | J56: 45747 | K56: 46112 | N56: 42064 | O56: 42430 | P56: 42795 | Q56: 43160 | R56: 43525 | S56: 43891 | T56: 44256 | U56: 44621 | V56: 44986 | W56: 45352 | X56: 45717 | Y56: 46082
A57: Equity Share Capital | B57: 88.78 | C57: 88.78 | D57: 88.78 | E57: 89 | F57: 89 | G57: 89 | H57: 89 | I57: 89 | J57: 89 | K57: 89 | M57: Equity Capital | N57: 89 | O57: 89 | P57: 89 | Q57: 89 | R57: 89 | S57: 89 | T57: 89 | U57: 89 | V57: 89 | W57: 89 | X57: 89 | Y57: 89
A58: Reserves | B58: 4143.6 | C58: 5001.1 | D58: 5981.37 | E58: 6580 | F58: 7408 | G58: 9214 | H58: 11762 | I58: 9304 | J58: 11535 | K58: 15614 | M58: Reserves | N58: 2995 | O58: 3418 | P58: 4144 | Q58: 5001 | R58: 5981 | S58: 6580 | T58: 7408 | U58: 9214 | V58: 11762 | W58: 9304 | X58: 11535 | Y58: 15614
A59: Borrowings | B59: 1882.43 | C59: 1691.01 | D59: 2392.98 | E59: 3562 | F59: 5638 | G59: 7275 | H59: 9367 | I59: 15528 | J59: 20777 | K59: 14551 | M59: Borrowings + | N59: 100 | O59: 113 | P59: 1882 | Q59: 1691 | R59: 2393 | S59: 3562 | T59: 5638 | U59: 7275 | V59: 9367 | W59: 15528 | X59: 20777 | Y59: 14551
A60: Other Liabilities | B60: 2292.76 | C60: 2740.15 | D60: 3246.71 | E60: 3313 | F60: 3309 | G60: 4610 | H60: 5802 | I60: 6626 | J60: 8244 | K60: 30307 | M60: Other Liabilities - | N60: 2684 | O60: 2723 | P60: 2293 | Q60: 2740 | R60: 3247 | S60: 3313 | T60: 3309 | U60: 4610 | V60: 5802 | W60: 6626 | X60: 8244 | Y60: 30307
A61: Total | B61: 8407.57 | C61: 9521.04 | D61: 11709.84 | E61: 13544 | F61: 16444 | G61: 21188 | H61: 27020 | I61: 31547 | J61: 40645 | K61: 60561 | M61: Non controlling int | N61: 0 | O61: 0 | P61: 26 | Q61: -2 | R61: 14 | S61: 4 | T61: 5 | U61: 30 | V61: 53 | W61: 0 | X61: 0 | Y61: 0
A62: Net Block | B62: 1188.72 | C62: 1473.81 | D62: 1566.63 | E62: 2633 | F62: 2523 | G62: 2544 | H62: 2998 | I62: 3709 | J62: 4062 | K62: 6906 | M62: Trade Payables | N62: 1940 | O62: 1655 | P62: 783 | Q62: 878 | R62: 906 | S62: 596 | T62: 789 | U62: 1294 | V62: 1214 | W62: 1410 | X62: 1963 | Y62: 2864
A63: Capital Work in Progress | B63: 152.07 | C63: 43.37 | D63: 31.77 | E63: 18 | F63: 32 | G63: 85 | H63: 144 | I63: 97 | J63: 105 | K63: 135 | M63: Advance from Customers | N63: 160 | O63: 710 | P63: 943 | Q63: 233 | R63: 290 | S63: 386 | T63: 479 | U63: 532 | V63: 718 | W63: 1085 | X63: 2140
A64: Investments | B64: 430.73 | C64: 35.99 | D64: 108.42 | E64: 158 | F64: 2824 | G64: 294 | H64: 2515 | I64: 2345 | J64: 1988 | K64: 3506 | M64: Other liability items | N64: 585 | O64: 358 | P64: 541 | Q64: 1631 | R64: 2037 | S64: 2327 | T64: 2036 | U64: 2754 | V64: 3817 | W64: 4131 | X64: 4141 | Y64: 27443
A65: Other Assets | B65: 6636.05 | C65: 7967.87 | D65: 10003.02 | E65: 10735 | F65: 11065 | G65: 18265 | H65: 21363 | I65: 25396 | J65: 34490 | K65: 50014 | M65: Total Liabilities | N65: 5868 | O65: 6342 | P65: 8408 | Q65: 9521 | R65: 11710 | S65: 13544 | T65: 16444 | U65: 21188 | V65: 27020 | W65: 31547 | X65: 40645 | Y65: 60561
A66: Total | B66: 8407.57 | C66: 9521.04 | D66: 11709.84 | E66: 13544 | F66: 16444 | G66: 21188 | H66: 27020 | I66: 31547 | J66: 40645 | K66: 60561 | M66: Fixed Assets + | N66: 699 | O66: 771 | P66: 1189 | Q66: 1474 | R66: 1567 | S66: 2633 | T66: 2523 | U66: 2544 | V66: 2998 | W66: 3709 | X66: 4062 | Y66: 6906
A67: Receivables | B67: 207.6 | C67: 295.69 | D67: 420.45 | E67: 312 | F67: 366 | G67: 565 | H67: 674 | I67: 1018 | J67: 1068 | K67: 916 | M67: CWIP | N67: 55 | O67: 107 | P67: 152 | Q67: 43 | R67: 32 | S67: 18 | T67: 32 | U67: 85 | V67: 144 | W67: 97 | X67: 105 | Y67: 135
A68: Inventory | B68: 4925.74 | C68: 5924.84 | D68: 7038.82 | E68: 8103 | F68: 8408 | G68: 13609 | H68: 16584 | I68: 19051 | J68: 28184 | K68: 42743 | M68: Investments | N68: 3 | O68: 30 | P68: 431 | Q68: 36 | R68: 108 | S68: 158 | T68: 2824 | U68: 294 | V68: 2515 | W68: 2345 | X68: 1988 | Y68: 3506
A69: Cash & Bank | B69: 778.93 | C69: 617.91 | D69: 1066.48 | E69: 381 | F69: 560 | G69: 1573 | H69: 1343 | I69: 1526 | J69: 1584 | K69: 1917 | M69: Other Assets - | N69: 5111 | O69: 5434 | P69: 6636 | Q69: 7968 | R69: 10003 | S69: 10735 | T69: 11065 | U69: 18265 | V69: 21363 | W69: 25396 | X69: 34490 | Y69: 50014
A70: No. of Equity Shares | B70: 887786160 | C70: 887786160 | D70: 887786160 | E70: 887786160 | F70: 887786160 | G70: 887786160 | H70: 890000000 | I70: 890000000 | J70: 890000000 | M70: Inventories | N70: 4049 | O70: 4447 | P70: 4926 | Q70: 5925 | R70: 7039 | S70: 8103 | T70: 8408 | U70: 13609 | V70: 16584 | W70: 19051 | X70: 28184 | Y70: 42743
A71: New Bonus Shares | M71: Trade receivables + | N71: 190 | O71: 192 | P71: 208 | Q71: 296 | R71: 420 | S71: 312 | T71: 366 | U71: 565 | V71: 674 | W71: 1018 | X71: 1068 | Y71: 916
A72: Face value | B72: 1 | C72: 1 | D72: 1 | E72: 1 | F72: 1 | G72: 1 | H72: 1 | I72: 1 | J72: 1 | K72: 1 | M72: Cash Equivalents | N72: 214 | O72: 116 | P72: 779 | Q72: 618 | R72: 1066 | S72: 381 | T72: 560 | U72: 1573 | V72: 1343 | W72: 1526 | X72: 1584 | Y72: 1917
K73: =U71+U70-U62 -> 12880 | M73: Loans n Advances | N73: 47 | O73: 87 | P73: 122 | Q73: 141 | R73: 25 | S73: 142 | T73: 109 | U73: 29 | V73: 167 | W73: 151 | X73: 324 | Y73: 1099
M74: Other asset items | N74: 611 | O74: 591 | P74: 602 | Q74: 988 | R74: 1452 | S74: 1797 | T74: 1622 | U74: 2489 | V74: 2595 | W74: 3650 | X74: 3330 | Y74: 3339
M75: Total Assets | N75: 5868 | O75: 6342 | P75: 8408 | Q75: 9521 | R75: 11710 | S75: 13544 | T75: 16444 | U75: 21188 | V75: 27020 | W75: 31547 | X75: 40645 | Y75: 60561
A80: CASH FLOW:
A81: Report Date | B81: 42825 | C81: 43190 | D81: 43555 | E81: 43921 | F81: 44286 | G81: 44651 | H81: 45016 | I81: 45382 | J81: 45747 | K81: 46112 | N81: 42064 | O81: 42430 | P81: 42795 | Q81: 43160 | R81: 43525 | S81: 43891 | T81: 44256 | U81: 44621 | V81: 44986 | W81: 45352 | X81: 45717 | Y81: 46082
A82: Cash from Operating Activity | B82: 1712.3 | C82: -51.12 | D82: 1242.92 | E82: -348 | F82: 4139 | G82: -724 | H82: 1370 | I82: 1695 | J82: -541 | K82: 5590 | M82: Cash from Operating Activity - | N82: 503 | O82: 576 | P82: 1712 | Q82: -51 | R82: 1243 | S82: -348 | T82: 4139 | U82: -724 | V82: 1370 | W82: 1695 | X82: -541 | Y82: 5590
A83: Cash from Investing Activity | B83: -953.15 | C83: 97.62 | D83: -796.61 | E83: 235 | F83: -2799 | G83: 1165 | H83: -1814 | I83: -189 | J83: 546 | K83: -2934 | M83: Profit from operations | N83: 1163 | O83: 942 | P83: 1073 | Q83: 1642 | R83: 2183 | S83: 2481 | T83: 1789 | U83: 3298 | V83: 4937 | W83: 5404 | X83: 5774 | Y83: 8447
A84: Cash from Financing Activity | B84: -165.6 | C84: -252.45 | D84: -488.83 | E84: -242 | F84: -1234 | G84: -403 | H84: 457 | I84: -1329 | J84: -7 | K84: -2159 | M84: Receivables | N84: -39 | O84: 0 | P84: -12 | Q84: -90 | R84: -139 | S84: 109 | T84: -59 | U84: -207 | V84: -112 | W84: -348 | X84: -95 | Y84: 210
A85: Net Cash Flow | B85: 593.55 | C85: -205.95 | D85: -42.52 | E85: -355 | F85: 106 | G85: 38 | H85: 13 | I85: 177 | J85: -2 | K85: 497 | M85: Inventory | N85: -180 | O85: -398 | P85: -448 | Q85: -996 | R85: -1120 | S85: -1057 | T85: -316 | U85: -5199 | V85: -2977 | W85: -2462 | X85: -9072 | Y85: -11592
M86: Payables | N86: 1079 | O86: -245 | P86: 238 | Q86: 95 | R86: 32 | S86: -310 | T86: 195 | U86: 504 | V86: -89 | W86: 196 | X86: 564 | Y86: 472
M87: Loans Advances | N87: -71 | O87: -66 | P87: 0 | Q87: 3 | R87: -24 | S87: -20 | T87: -8 | U87: -3 | V87: -18 | W87: -21 | X87: 4 | Y87: 7296
M88: Operating borrowings | N88: 0 | O88: 0 | P88: 763 | Q88: -270 | R88: 741 | S88: -768 | T88: 2625 | U88: 1188 | V88: -99 | W88: 42 | X88: 2468 | Y88: 0
M89: Other WC items | N89: -1204 | O89: 545 | P89: 375 | Q89: 22 | R89: 206 | S89: -226 | T89: 184 | U89: 497 | V89: 882 | W89: 57 | X89: 905 | Y89: 2494
A90: PRICE: | B90: 462.75 | C90: 942.3 | D90: 1141.85 | E90: 933.7 | F90: 1558.05 | G90: 2536.15 | H90: 2514.9 | I90: 3801.8 | J90: 3063.35 | K90: 3951.4 | M90: Working capital changes | N90: -415 | O90: -163 | P90: 916 | Q90: -1237 | R90: -304 | S90: -2272 | T90: 2621 | U90: -3220 | V90: -2413 | W90: -2536 | X90: -5226 | Y90: -1120
M91: Direct taxes | N91: -245 | O91: -202 | P91: -277 | Q91: -456 | R91: -636 | S91: -557 | T91: -271 | U91: -802 | V91: -1154 | W91: -1173 | X91: -1089 | Y91: -1737
A92: DERIVED: | M92: Cash from Investing Activity - | N92: -118 | O92: -159 | P92: -953 | Q92: 98 | R92: -797 | S92: 235 | T92: -2799 | U92: 1165 | V92: -1814 | W92: -189 | X92: 546 | Y92: -2934
A93: Adjusted Equity Shares in Cr | B93: 88.78 | C93: 88.78 | D93: 88.78 | E93: 88.78 | F93: 88.78 | G93: 88.78 | H93: 88.78 | I93: 88.78 | J93: 88.78 | K93: 88.78 | M93: Fixed assets purchased | N93: -209 | O93: -254 | P93: -256 | Q93: -305 | R93: -265 | S93: -355 | T93: -146 | U93: -224 | V93: -432 | W93: -691 | X93: -494 | Y93: -902
M94: Fixed assets sold | N94: 2 | O94: 2 | P94: 5 | Q94: 6 | R94: 1 | S94: 10 | T94: 7 | U94: 8 | V94: 12 | W94: 20 | X94: 24 | Y94: 25
M95: Investments purchased | N95: -135 | O95: -1078 | P95: -325 | Q95: 0 | R95: -36 | S95: -13 | T95: -2656 | U95: -253 | V95: -2104 | W95: -21893 | X95: -15342 | Y95: -21936
M96: Investments sold | N96: 135 | O96: 1083 | P96: 0 | Q96: 412 | R96: 18 | S96: 0 | T96: 43 | U96: 2870 | V96: 0 | W96: 22213 | X96: 15747 | Y96: 20797
M97: Interest received | N97: 77 | O97: 58 | P97: 41 | Q97: 64 | R97: 85 | S97: 73 | T97: 49 | U97: 56 | V97: 143 | W97: 249 | X97: 288 | Y97: 227
M98: Invest in subsidiaries | N98: 0 | O98: 0 | P98: 0 | Q98: 0 | R98: 0 | S98: -39 | T98: 0 | U98: 0 | V98: 0 | W98: 0 | X98: 0 | Y98: 0
M99: Investment in group cos | N99: 0 | O99: -18 | P99: 0 | Q99: 0 | R99: 0 | S99: 0 | T99: 0 | U99: 0 | V99: 0 | W99: 0 | X99: 0 | Y99: 0
M100: Acquisition of companies | N100: 0 | O100: 0 | P100: -385 | Q100: 0 | R100: 0 | S100: 0 | T100: 0 | U100: 0 | V100: 0 | W100: 0 | X100: 0 | Y100: 0
M101: Inter corporate deposits | N101: -48 | O101: 38 | P101: 5 | Q101: -35 | R101: -115 | S101: 200 | T101: -50 | U101: -344 | V101: 294 | W101: -143 | X101: 243 | Y101: 0
M102: Other investing items | N102: 60 | O102: 10 | P102: -38 | Q102: -43 | R102: -485 | S102: 359 | T102: -46 | U102: -948 | V102: 273 | W102: 56 | X102: 80 | Y102: -1145
M103: Cash from Financing Activity - | N103: -1005 | O103: -505 | P103: -166 | Q103: -252 | R103: -489 | S103: -242 | T103: -1234 | U103: -403 | V103: 457 | W103: -1329 | X103: -7 | Y103: -2159
M104: Proceeds from borrowings | N104: 0 | O104: 0 | P104: 0 | Q104: 0 | R104: 0 | S104: 693 | T104: 0 | U104: 349 | V104: 1684 | W104: 5629 | X104: 2599 | Y104: 3314
M105: Repayment of borrowings | N105: 0 | O105: 0 | P105: 0 | Q105: 0 | R105: -39 | S105: 0 | T105: -562 | U105: -7 | V105: -7 | W105: 0 | X105: -378 | Y105: -2632
... M112: CFO/OP | N112: 0.65 | O112: 0.83 | P112: 1.71 | Q112: 0.25 | R112: 0.94 | S112: 0.08 | T112: 2.56 | U112: 0.02 | V112: 0.52 | W112: 0.54 | X112: 0.1 | Y112: 0.88
