Workbook
Name UPDATE: #REF!
Name UPDATE: #REF!
Name UPDATE: #REF!
Name UPDATE: #REF!
Name UPDATE: 'Data Sheet'!$E$1

Sheet Profile
B11: INR (Crs)
B12: Key Financial Metrics | C12: Mar-22 | D12: Mar-23 | E12: Mar-24 | F12: Mar-25 | G12: Mar-26 | I12: Share Price
B13: Total Sales | C13: ='H2'!E9 -> 973.76 | D13: ='H2'!F9 -> 1173.57 | E13: ='H2'!G9 -> 1296.9 | F13: ='H2'!H9 -> 1515.87 | G13: ='H2'!I9 -> 1703.08
B14: Sales Growth (y-o-y) | C14: ='H2'!E10 -> 0.49797708 | D14: ='H2'!F10 -> 0.2051943 | E14: ='H2'!G10 -> 0.1050896 | F14: ='H2'!H10 -> 0.16884108 | G14: ='H2'!I10 -> 0.12350004
B15: Gross Profit Margins (%) | C15: ='H2'!E21 -> 0.71539188 | D15: ='H2'!F21 -> 0.77303442 | E15: ='H2'!G21 -> 0.77823271 | F15: ='H2'!H21 -> 0.77705212 | G15: ='H2'!I21 -> 0.77550086
B16: EBITDA Margins (%) | C16: ='H2'!E29 -> 0.31622782 | D16: ='H2'!F29 -> 0.34047394 | E16: ='H2'!G29 -> 0.33338731 | F16: ='H2'!H29 -> 0.32604379 | G16: ='H2'!I29 -> 0.32202833
B17: EBIT Margins (%) | C17: ='H2'!E33 -> 0.2307242 | D17: ='H2'!F33 -> 0.26355479 | E17: ='H2'!G33 -> 0.24696584 | F17: ='H2'!H33 -> 0.2347167 | G17: ='H2'!I33 -> 0.23361792
B18: Net Profit Margins (%) | C18: ='H2'!E42 -> 0.14241702 | D18: ='H2'!F42 -> 0.18096918 | E18: ='H2'!G42 -> 0.16831676 | F18: ='H2'!H42 -> 0.1611088 | G18: ='H2'!I42 -> 0.16531226
B19: Earnings Per Share (In Rs) | C19: ='H2'!E46 -> 14.737513 | D19: ='H2'!F46 -> 20.924138 | E19: ='H2'!G46 -> 21.506404 | F19: ='H2'!H46 -> 24.037402 | G19: ='H2'!I46 -> 27.71063
B20: EPS Growth (y-o-y) | C20: ='H2'!E47 -> 0.6203163 | D20: ='H2'!F47 -> 0.41978755 | E20: ='H2'!G47 -> 0.027827479 | F20: ='H2'!H47 -> 0.11768577 | G20: ='H2'!I47 -> 0.15281304
B21: Dividend Per Share (In Rs) | C21: ='H2'!E49 -> 1.9989373 | D21: ='H2'!F49 -> 3 | E21: ='H2'!G49 -> 3 | F21: ='H2'!H49 -> 2.9980315 | G21: ='H2'!I49 -> 3.4990157
B23: Key Financial Ratios | C23: Mar-22 | D23: Mar-23 | E23: Mar-24 | F23: Mar-25 | G23: Mar-26 | I23: Volume (Thousands)
B24: Return on Equity | C24: ='F3'!D27 -> 0.864364 | D24: ='F3'!E27 -> 0.85662492 | E24: ='F3'!F27 -> 0.86050667 | F24: ='F3'!G27 -> 0.87527639 | G24: ='F3'!H27 -> 0.8737302
B25: Return on Capital Employed | C25: ='F3'!D26 -> 0.18975507 | D25: ='F3'!E26 -> 0.1897546 | E25: ='F3'!F26 -> 0.15824605 | F25: ='F3'!G26 -> 0.15933721 | G25: ='F3'!H26 -> 0.15664173
B26: CFO to NP | C26: ='Cash Flow'!U4/'H2'!E41 -> 1.6152293 | D26: ='Cash Flow'!V4/'H2'!F41 -> 1.5491101 | E26: ='Cash Flow'!W4/'H2'!G41 -> 1.4705209 | F26: ='Cash Flow'!X4/'H2'!H41 -> 1.6214888 | G26: ='Cash Flow'!Y4/'H2'!I41 -> 1.4917951
B27: Debt to Profit | C27: ='Balance Sheet'!U6/'H2'!E41 -> 4.2688203 | D27: ='Balance Sheet'!V6/'H2'!F41 -> 2.6838685 | E27: ='Balance Sheet'!W6/'H2'!G41 -> 3.5045123 | F27: ='Balance Sheet'!X6/'H2'!H41 -> 3.1283269 | G27: ='Balance Sheet'!Y6/'H2'!I41 -> 3.1647368
B28: Debt to Equity | C28: ='F3'!D31 -> 0.045608108 | D28: ='F3'!E31 -> 0 | E28: ='F3'!F31 -> 0 | F28: ='F3'!G31 -> 0 | G28: ='F3'!H31 -> 0
B30: Shareholding | C30: No. Shares (In Crs) | E30: % Holding | F30: Institutional Inv> > 1% Holding | I30: Shareholding Pattern
B31: Promoter & Promoter Grp | C31: 5.06 | E31: 0.4984 | F31: ICICI Bank | G31: 0.052
B32: MF/AIF | C32: 1.94 | E32: 0.1916 | F32: DSP Mutual Fund | G32: 0.043
B33: Financial Inst./Banks/Insurance Comp. | C33: 0.2 | E33: 0.0197 | F33: Franklin Templeton | G33: 0.029
B34: FPI & FII & Foreign Nationals | C34: 1.75 | E34: 0.1724 | F34: Abu Dhabi Inv | G34: 0.021
B35: Resident Individuals (Trusts & HUF) | C35: 1.11 | E35: 0.1095 | F35: Vanguard Fund | G35: 0.018
B36: Corporates | C36: 0.058 | E36: 0.0057 | F36: Ashoka Whiteoak | G36: 0.017
B37: NRI | C37: 0.027 | E37: 0.0027 | F37: Tata MF | G37: 0.017
B38: Clearing Members | C38: 0.00027 | E38: 0 | F38: HDFC Life | G38: 0.015
B42: Company Snapshot | E42: Returns Abs. | G42: CAGR | I42: Capital Structure
B43: CMP | C43: 1439.8 | E43: 1 | F43: -0.0525 | G43: -0.05 | I43: Share price as on 25-Aug-26 | J43: =C43 -> 1439.8
B44: Market Cap | C44: =J45 -> 14628.368 | E44: 3 | F44: 0.3793 | G44: 0.11 | I44: Number of Shares o/s | J44: ='Data Sheet'!K93 -> 10.16
B45: 52 Wk High/Low | C45: 1,439.1/1,610 | E45: 5 | F45: - | G45: - | I45: Market Capitalization | J45: =J44*J43 -> 14628.368
B46: Div Yield | C46: ='H2'!I49/Profile!C43 -> 0.0024302096 | E46: Max | F46: 9.837 | G46: 0.2819 | I46: Less : Cash & Equivalents | J46: ='Balance Sheet'!Y35 -> 34
B47: P/E | C47: =Profile!C43/'H2'!I46 -> 51.9584 | I47: Add : Total Debt | J47: ='Balance Sheet'!Y6 -> 891
B48: Industry P/E | C48: 49.28 | I48: Enterprise Value | J48: =J45+J46-J47 -> 13771.368
B50: Recent Updates
B56: Source : Screener.in & Capitalmarket.com
B57: Made by Shivansh Chandra

Sheet Business
B3: B | C3: usiness
B6: Business Description | H6: Revenue Model
B19: Industry Overview | H19: Positioning

Sheet B2
B3: B | C3: usiness
B6: Growth Strategies | H6: Capex Plans
B17: Recent Developments | H17: Corporate History

Sheet B3
B3: B | C3: usiness
B6: Strength | H6: Weakness
B17: Opportunities | H17: Threats

Sheet Management
B3: M | C3: anagement
B6: Management Analysis
D8: Name | F8: Education | J8: Insights
C12: DR. Ramesh Kancharla
C19: Dr. Dinesh Kumar Chirla
C26: Abrarali Dalal

Sheet M2
B3: M | C3: anagement
B6: Management Analysis
B8: Name | F8: Education | J8: Insights
C12: Vikas Maheshwari
C19: Dr. Adarsh Kancharla
C26: Ms. Shreya Mitra

Sheet Financials
B3: F | C3: inancials
B6: Quarterly Performance
D8: FY25 | H8: FY26
D9: Q1 | E9: Q2 | F9: Q3 | G9: Q4 | H9: Q1 | I9: Q2 | J9: Q3 | K9: Q4
D10: 45444 | E10: 45536 | F10: 45627 | G10: 45717 | H10: 45809 | I10: 45901 | J10: 45992 | K10: 46082
B11: Sales | D11: 1543 | E11: 1707 | F11: 1868 | G11: 1910 | H11: 2028 | I11: 2135 | J11: 2068 | K11: 2143
B12: Growth % | D12: - | E12: =E11/D11-1 -> 0.10628645 | F12: =F11/E11-1 -> 0.094317516 | G12: =G11/F11-1 -> 0.02248394 | H12: =H11/G11-1 -> 0.061780105 | I12: =I11/H11-1 -> 0.052761341 | J12: =J11/I11-1 -> -0.031381733 | K12: =K11/J11-1 -> 0.036266925
B13: Expenses | D13: 1156 | E13: 1257 | F13: 1369 | G13: 1398 | H13: 1505 | I13: 1560 | J13: 1529 | K13: 1536
B14: EBITDA | D14: 387 | E14: 451 | F14: 499 | G14: 512 | H14: 523 | I14: 575 | J14: 538 | K14: 606
B15: EBITDA Margin | D15: =D14/D11 -> 0.25081011 | E15: =E14/E11 -> 0.26420621 | F15: =F14/F11 -> 0.26713062 | G15: =G14/G11 -> 0.26806283 | H15: =H14/H11 -> 0.25788955 | I15: =I14/I11 -> 0.26932084 | J15: =J14/J11 -> 0.26015474 | K15: =K14/K11 -> 0.28278115
B16: Other Income | D16: 35 | E16: 41 | F16: -40 | G16: 47 | H16: 37 | I16: 33 | J16: -3 | K16: 48
B17: Depreciation | D17: 77 | E17: 84 | F17: 98 | G17: 101 | H17: 104 | I17: 108 | J17: 111 | K17: 123
B18: EBIT | D18: =(D14+D16)-D17 -> 345 | E18: =(E14+E16)-E17 -> 408 | F18: =(F14+F16)-F17 -> 361 | G18: =(G14+G16)-G17 -> 458 | H18: =(H14+H16)-H17 -> 456 | I18: =(I14+I16)-I17 -> 500 | J18: =(J14+J16)-J17 -> 424 | K18: =(K14+K16)-K17 -> 531
B19: Interest | D19: 24 | E19: 34 | F19: 52 | G19: 55 | H19: 55 | I19: 54 | J19: 60 | K19: 67
B20: EBT | D20: =D18-D19 -> 321 | E20: =E18-E19 -> 374 | F20: =F18-F19 -> 309 | G20: =G18-G19 -> 403 | H20: =H18-H19 -> 401 | I20: =I18-I19 -> 446 | J20: =J18-J19 -> 364 | K20: =K18-K19 -> 464
B21: Tax | D21: =D20*D22 -> 83.46 | E21: =E20*E22 -> 93.5 | F21: =F20*F22 -> 71.07 | G21: =G20*G22 -> 84.63 | H21: =H20*H22 -> 92.23 | I21: =I20*I22 -> -44.6 | J21: =J20*J22 -> 61.88 | K21: =K20*K22 -> 120.64
B22: Tax % | D22: 0.26 | E22: 0.25 | F22: 0.23 | G22: 0.21 | H22: 0.23 | I22: -0.1 | J22: 0.17 | K22: 0.26
B23: Net Profit | D23: =D20-D21 -> 237.54 | E23: =E20-E21 -> 280.5 | F23: =F20-F21 -> 237.93 | G23: =G20-G21 -> 318.37 | H23: =H20-H21 -> 308.77 | I23: =I20-I21 -> 490.6 | J23: =J20-J21 -> 302.12 | K23: =K20-K21 -> 343.36
B25: Interpretation

Sheet H2
B3: F | C3: inancials
B6: P/L Statement
B8: Income Statement (₹ Cr) | E8: 2022 | F8: =E8+1 -> 2023 | G8: =F8+1 -> 2024 | H8: =G8+1 -> 2025 | I8: =H8+1 -> 2026 | J8: =I8+1 -> 2027 | K8: =J8+1 -> 2028 | L8: =K8+1 -> 2029
B9: Sales | E9: ='Data Sheet'!G17 -> 973.76 | F9: ='Data Sheet'!H17 -> 1173.57 | G9: ='Data Sheet'!I17 -> 1296.9 | H9: ='Data Sheet'!J17 -> 1515.87 | I9: ='Data Sheet'!K17 -> 1703.08 | J9: =I9*(1+J10) -> 1928.6988 | K9: =J9*(1+K10) -> 2184.2068 | L9: =K9*(1+L10) -> 2473.5638
B10: Sales Growth% | E10: ='Data Sheet'!G17/'Data Sheet'!F17-1 -> 0.49797708 | F10: ='Data Sheet'!H17/'Data Sheet'!G17-1 -> 0.2051943 | G10: ='Data Sheet'!I17/'Data Sheet'!H17-1 -> 0.1050896 | H10: ='Data Sheet'!J17/'Data Sheet'!I17-1 -> 0.16884108 | I10: ='Data Sheet'!K17/'Data Sheet'!J17-1 -> 0.12350004 | J10: =AVERAGE($G$10:$I$10) -> 0.13247691 | K10: =AVERAGE($G$10:$I$10) -> 0.13247691 | L10: =AVERAGE($G$10:$I$10) -> 0.13247691
B11: COGS
B12: Raw Material Cost | E12: ='Data Sheet'!G18 -> 194.73 | F12: ='Data Sheet'!H18 -> 158.28 | G12: ='Data Sheet'!I18 -> 165.28 | H12: ='Data Sheet'!J18 -> 194.92 | I12: ='Data Sheet'!K18 -> 227.03
B13: Change in Inventory | E13: ='Data Sheet'!G19 -> 0 | F13: ='Data Sheet'!H19 -> 0 | G13: ='Data Sheet'!I19 -> 0 | H13: ='Data Sheet'!J19 -> 0 | I13: ='Data Sheet'!K19 -> 0
B14: Power and Fuel | E14: ='Data Sheet'!G20 -> 16.81 | F14: ='Data Sheet'!H20 -> 21.23 | G14: ='Data Sheet'!I20 -> 26.61 | H14: ='Data Sheet'!J20 -> 27.72 | I14: ='Data Sheet'!K20 -> 28.85
B15: Other Mfr. Exp | E15: ='Data Sheet'!G21 -> 65.6 | F15: ='Data Sheet'!H21 -> 86.85 | G15: ='Data Sheet'!I21 -> 95.72 | H15: ='Data Sheet'!J21 -> 115.32 | I15: ='Data Sheet'!K21 -> 126.46
B17: Total COGS | E17: =IF(E13<0,SUM(E12:E15),SUM(E15,E14,E12)-E13) -> 277.14 | F17: =SUM(F14:F15,F12)-F13 -> 266.36 | G17: =IF(G13<0,SUM(G12:G15),SUM(G15,G14,G12)-G13) -> 287.61 | H17: =IF(H13<0,SUM(H12:H15),SUM(H15,H14,H12)-H13) -> 337.96 | I17: =IF(I13<0,SUM(I12:I15),SUM(I15,I14,I12)-I13) -> 382.34 | J17: =J9*J18 -> 430.23761 | K17: =K9*K18 -> 487.23415 | L17: =L9*L18 -> 551.78143
B18: COGS % of Sales | E18: =E17/E9 -> 0.28460812 | F18: =F17/F9 -> 0.22696558 | G18: =G17/G9 -> 0.22176729 | H18: =H17/H9 -> 0.22294788 | I18: =I17/I9 -> 0.22449914 | J18: =AVERAGE($G$18:$I$18) -> 0.22307144 | K18: =AVERAGE($G$18:$I$18) -> 0.22307144 | L18: =AVERAGE($G$18:$I$18) -> 0.22307144
B20: Gross Profit | E20: =E9-E17 -> 696.62 | F20: =F9-F17 -> 907.21 | G20: =G9-G17 -> 1009.29 | H20: =H9-H17 -> 1177.91 | I20: =I9-I17 -> 1320.74 | J20: =J9-J17 -> 1498.4612 | K20: =K9-K17 -> 1696.9727 | L20: =L9-L17 -> 1921.7823
B21: Gross Margin % Sales | E21: =E20/E9 -> 0.71539188 | F21: =F20/F9 -> 0.77303442 | G21: =G20/G9 -> 0.77823271 | H21: =H20/H9 -> 0.77705212 | I21: =I20/I9 -> 0.77550086 | J21: =J20/J9 -> 0.77692856 | K21: =K20/K9 -> 0.77692856 | L21: =L20/L9 -> 0.77692856
B22: SG&A
B23: Employee Cost | E23: ='Data Sheet'!G22 -> 116.37 | F23: ='Data Sheet'!H22 -> 144.56 | G23: ='Data Sheet'!I22 -> 176.71 | H23: ='Data Sheet'!J22 -> 206.82 | I23: ='Data Sheet'!K22 -> 234.11
B24: Selling and admin | E24: ='Data Sheet'!G23 -> 266.44 | F24: ='Data Sheet'!H23 -> 350.18 | G24: ='Data Sheet'!I23 -> 395.45 | H24: ='Data Sheet'!J23 -> 469.57 | I24: ='Data Sheet'!K23 -> 525.36
B25: Other Expenses | E25: ='Data Sheet'!G24 -> 5.88 | F25: ='Data Sheet'!H24 -> 12.9 | G25: ='Data Sheet'!I24 -> 4.76 | H25: ='Data Sheet'!J24 -> 7.28 | I25: ='Data Sheet'!K24 -> 12.83
B26: Total OpEx | E26: =SUM(E23:E25) -> 388.69 | F26: =SUM(F23:F25) -> 507.64 | G26: =SUM(G23:G25) -> 576.92 | H26: =SUM(H23:H25) -> 683.67 | I26: =SUM(I23:I25) -> 772.3 | J26: =J9*J27 -> 867.4813 | K26: =K9*K27 -> 982.40254 | L26: =L9*L27 -> 1112.5482
B27: OpEx % Sales | E27: =E26/E9 -> 0.39916407 | F27: =F26/F9 -> 0.43256048 | G27: =G26/G9 -> 0.4448454 | H27: =H26/H9 -> 0.45100833 | I27: =I26/I9 -> 0.45347253 | J27: =AVERAGE($G$27:$I$27) -> 0.44977542 | K27: =AVERAGE($G$27:$I$27) -> 0.44977542 | L27: =AVERAGE($G$27:$I$27) -> 0.44977542
B28: EBITDA | E28: =E20-E26 -> 307.93 | F28: =F20-F26 -> 399.57 | G28: =G20-G26 -> 432.37 | H28: =H20-H26 -> 494.24 | I28: =I20-I26 -> 548.44 | J28: =J9*J29 -> 630.97986 | K28: =K9*K29 -> 714.57012 | L28: =L9*L29 -> 809.23416
B29: EBITDA Margin % Sales | E29: =E28/E9 -> 0.31622782 | F29: =F28/F9 -> 0.34047394 | G29: =G28/G9 -> 0.33338731 | H29: =H28/H9 -> 0.32604379 | I29: =I28/I9 -> 0.32202833 | J29: =AVERAGE($G$29:$I$29) -> 0.32715314 | K29: =AVERAGE($G$29:$I$29) -> 0.32715314 | L29: =AVERAGE($G$29:$I$29) -> 0.32715314
B30: D&A | E30: ='Data Sheet'!G26 -> 83.26 | F30: ='Data Sheet'!H26 -> 90.27 | G30: ='Data Sheet'!I26 -> 112.08 | H30: ='Data Sheet'!J26 -> 138.44 | I30: ='Data Sheet'!K26 -> 150.57 | J30: =J9*J31 -> 171.11349 | K30: =K9*K31 -> 193.78208 | L30: =L9*L31 -> 219.45373
B31: D&A as % Sales | E31: =E30/E9 -> 0.085503615 | F31: =F30/F9 -> 0.076919144 | G31: =G30/G9 -> 0.086421467 | H31: =H30/H9 -> 0.091327093 | I31: =I30/I9 -> 0.088410409 | J31: =AVERAGE($G$31:$I$31) -> 0.088719656 | K31: =AVERAGE($G$31:$I$31) -> 0.088719656 | L31: =AVERAGE($G$31:$I$31) -> 0.088719656
B32: EBIT | E32: =E28-E30 -> 224.67 | F32: =F28-F30 -> 309.3 | G32: =G28-G30 -> 320.29 | H32: =H28-H30 -> 355.8 | I32: =I28-I30 -> 397.87 | J32: =J28-J30 -> 459.86637 | K32: =K28-K30 -> 520.78804 | L32: =L28-L30 -> 589.78043
B33: EBIT Margin % Sales | E33: =E32/E9 -> 0.2307242 | F33: =F32/F9 -> 0.26355479 | G33: =G32/G9 -> 0.24696584 | H33: =H32/H9 -> 0.2347167 | I33: =I32/I9 -> 0.23361792 | J33: =AVERAGE($G$33:$I$33) -> 0.23843348 | K33: =AVERAGE($G$33:$I$33) -> 0.23843348 | L33: =AVERAGE($G$33:$I$33) -> 0.23843348
B34: Interest | E34: ='Data Sheet'!G27 -> 56.17 | F34: ='Data Sheet'!H27 -> 58.39 | G34: ='Data Sheet'!I27 -> 62.53 | H34: ='Data Sheet'!J27 -> 76.81 | I34: ='Data Sheet'!K27 -> 81.89 | J34: =J9*J35 -> 94.486322 | K34: =K9*K35 -> 107.00358 | L34: =L9*L35 -> 121.17908
B35: Interest % Sales | E35: =E34/E9 -> 0.057683618 | F35: =F34/F9 -> 0.049754169 | G35: =G34/G9 -> 0.048214974 | H35: =H34/H9 -> 0.050670572 | I35: =I34/I9 -> 0.048083472 | J35: =AVERAGE($G$35:$I$35) -> 0.048989673 | K35: =AVERAGE($G$35:$I$35) -> 0.048989673 | L35: =AVERAGE($G$35:$I$35) -> 0.048989673
B36: EBT | E36: =(E32-E34)+E40 -> 187.35 | F36: =(F32-F34)+F40 -> 281.78 | G36: =(G32-G34)+G40 -> 294.82 | H36: =(H32-H34)+H40 -> 330 | I36: =(I32-I34)+I40 -> 358.23 | J36: =J32-J34 -> 365.38005 | K36: =K32-K34 -> 413.78447 | L36: =L32-L34 -> 468.60135
B37: EBT % Sales | E37: =E36/E9 -> 0.19239854 | F37: =F36/F9 -> 0.24010498 | G37: =G36/G9 -> 0.2273267 | H37: =H36/H9 -> 0.21769677 | I37: =I36/I9 -> 0.21034244 | J37: =AVERAGE($G$37:$I$37) -> 0.2184553 | K37: =AVERAGE($G$37:$I$37) -> 0.2184553 | L37: =AVERAGE($G$37:$I$37) -> 0.2184553
B38: Tax | E38: ='Data Sheet'!G29 -> 48.67 | F38: ='Data Sheet'!H29 -> 69.4 | G38: ='Data Sheet'!I29 -> 76.53 | H38: ='Data Sheet'!J29 -> 85.78 | I38: ='Data Sheet'!K29 -> 76.69 | J38: =J36*J39 -> 89.347826 | K38: =K36*K39 -> 101.18435 | L38: =L36*L39 -> 114.58894
B39: Tax % EBT | E39: =E38/E36 -> 0.25978116 | F39: =F38/F36 -> 0.24629143 | G39: =G38/G36 -> 0.25958212 | H39: =H38/H36 -> 0.25993939 | I39: =I38/I36 -> 0.21408034 | J39: =AVERAGE($G$39:$I$39) -> 0.24453395 | K39: =AVERAGE($G$39:$I$39) -> 0.24453395 | L39: =AVERAGE($G$39:$I$39) -> 0.24453395
B40: Other Income | E40: ='Data Sheet'!G25 -> 18.85 | F40: ='Data Sheet'!H25 -> 30.87 | G40: ='Data Sheet'!I25 -> 37.06 | H40: ='Data Sheet'!J25 -> 51.01 | I40: ='Data Sheet'!K25 -> 42.25 | J40: =I40*(1+0.046) -> 44.1935 | K40: =J40*(1+0.046) -> 46.226401 | L40: =K40*(1+0.046) -> 48.352815
B41: Net Profit | E41: =(E36-E38) -> 138.68 | F41: =(F36-F38) -> 212.38 | G41: =(G36-G38) -> 218.29 | H41: =(H36-H38) -> 244.22 | I41: =(I36-I38) -> 281.54 | J41: =(J36-J38) -> 276.03222 | K41: =(K36-K38) -> 312.60012 | L41: =(L36-L38) -> 354.01241
B42: Net Profit Margin % | E42: =E41/E9 -> 0.14241702 | F42: =F41/F9 -> 0.18096918 | G42: =G41/G9 -> 0.16831676 | H42: =H41/H9 -> 0.1611088 | I42: =I41/I9 -> 0.16531226 | J42: =AVERAGE(G42:I42) -> 0.16491261 | K42: =AVERAGE(H42:J42) -> 0.16377789 | L42: =AVERAGE(I42:K42) -> 0.16466758
B44: No. of Equity Shares | E44: ='Data Sheet'!G93 -> 9.41 | F44: ='Data Sheet'!H93 -> 10.15 | G44: ='Data Sheet'!I93 -> 10.15 | H44: ='Data Sheet'!J93 -> 10.16 | I44: ='Data Sheet'!K93 -> 10.16 | J44: =I44 -> 10.16 | K44: =J44 -> 10.16 | L44: =K44 -> 10.16
B46: Earnings Per Share | E46: =E41/E44 -> 14.737513 | F46: =F41/F44 -> 20.924138 | G46: =G41/G44 -> 21.506404 | H46: =H41/H44 -> 24.037402 | I46: =I41/I44 -> 27.71063 | J46: =J41/J44 -> 27.168526 | K46: =K41/K44 -> 30.767728 | L46: =L41/L44 -> 34.843741
B47: EPS Growth % | E47: =E46/'Profit & Loss'!F13-1 -> 0.6203163 | F47: =F46/E46-1 -> 0.41978755 | G47: =G46/F46-1 -> 0.027827479 | H47: =H46/G46-1 -> 0.11768577 | I47: =I46/H46-1 -> 0.15281304 | J47: =J46/I46-1 -> -0.019563043 | K47: =K46/J46-1 -> 0.13247691 | L47: =L46/K46-1 -> 0.13247691
B49: Dividend Per Share | E49: ='Data Sheet'!G31/'H2'!E44 -> 1.9989373 | F49: ='Data Sheet'!H31/'H2'!F44 -> 3 | G49: ='Data Sheet'!I31/'H2'!G44 -> 3 | H49: ='Data Sheet'!J31/'H2'!H44 -> 2.9980315 | I49: ='Data Sheet'!K31/'H2'!I44 -> 3.4990157 | J49: =(J50*J41)/J44 -> 3.5363164 | K49: =(K50*K41)/K44 -> 3.9090979 | L49: =(L50*L41)/L44 -> 4.454005
B50: Dividend Payout Ratio | E50: ='Data Sheet'!G31/'H2'!E41 -> 0.135636 | F50: ='Data Sheet'!H31/'H2'!F41 -> 0.14337508 | G50: ='Data Sheet'!I31/'H2'!G41 -> 0.13949333 | H50: ='Data Sheet'!J31/'H2'!H41 -> 0.12472361 | I50: ='Data Sheet'!K31/'H2'!I41 -> 0.1262698 | J50: =AVERAGE(G50:I50) -> 0.13016225 | K50: =AVERAGE(H50:J50) -> 0.12705189 | L50: =AVERAGE(I50:K50) -> 0.12782798
B52: Retained Earnings | E52: =1-E50 -> 0.864364 | F52: =1-F50 -> 0.85662492 | G52: =1-G50 -> 0.86050667 | H52: =1-H50 -> 0.87527639 | I52: =1-I50 -> 0.8737302 | J52: =1-J50 -> 0.86983775 | K52: =1-K50 -> 0.87294811 | L52: =1-L50 -> 0.87217202
B54: Interpretation

Sheet F3
B3: F | C3: inancials
B6: Ratios Analysis Rainbow Hospitals
B8: Years | D8: 44651 | E8: 45016 | F8: 45382 | G8: 45747 | H8: 46112 | I8: Trend | J8: Mean | K8: Median
B10: Sales Growth | D10: ='Data Sheet'!G17/'Data Sheet'!F17-1 -> 0.49797708 | E10: ='Data Sheet'!H17/'Data Sheet'!G17-1 -> 0.2051943 | F10: ='Data Sheet'!I17/'Data Sheet'!H17-1 -> 0.1050896 | G10: ='Data Sheet'!J17/'Data Sheet'!I17-1 -> 0.16884108 | H10: ='Data Sheet'!K17/'Data Sheet'!J17-1 -> 0.12350004 | J10: =IFERROR(AVERAGE(D10:H10),0) -> 0.22012042 | K10: =IFERROR(MEDIAN(D10:H10),0) -> 0.16884108
B11: EBITDA Growth | D11: ='Profit & Loss'!G6/'Profit & Loss'!F6-1 -> 0.86466029 | E11: ='H2'!F28/'H2'!E28-1 -> 0.2976001 | F11: ='H2'!G28/'H2'!F28-1 -> 0.082088245 | G11: ='H2'!H28/'H2'!G28-1 -> 0.14309503 | H11: ='H2'!I28/'H2'!H28-1 -> 0.10966332 | J11: =IFERROR(AVERAGE(D11:H11),0) -> 0.2994214 | K11: =IFERROR(MEDIAN(D11:H11),0) -> 0.14309503
B12: EBIT Growth | D12: =('Profit & Loss'!G6-'Profit & Loss'!G8)/('Profit & Loss'!F6-'Profit & Loss'!F8)-1 -> 1.4473856 | E12: ='H2'!F36/'H2'!E36-1 -> 0.50402989 | F12: ='H2'!G36/'H2'!F36-1 -> 0.046277238 | G12: ='H2'!H36/'H2'!G36-1 -> 0.11932705 | H12: ='H2'!I36/'H2'!H36-1 -> 0.085545455 | J12: =IFERROR(AVERAGE(D12:H12),0) -> 0.44051305 | K12: =IFERROR(MEDIAN(D12:H12),0) -> 0.11932705
B13: Net Profit Growth | D13: ='H2'!E42 -> 0.14241702 | E13: ='H2'!F42 -> 0.18096918 | F13: ='H2'!G42 -> 0.16831676 | G13: ='H2'!H42 -> 0.1611088 | H13: ='H2'!I42 -> 0.16531226 | J13: =IFERROR(AVERAGE(D13:H13),0) -> 0.1636248 | K13: =IFERROR(MEDIAN(D13:H13),0) -> 0.16531226
B14: Dividend Growth | D14: ='H2'!E50 -> 0.135636 | E14: ='H2'!F50 -> 0.14337508 | F14: ='H2'!G50 -> 0.13949333 | G14: ='H2'!H50 -> 0.12472361 | H14: ='H2'!I50 -> 0.1262698 | J14: =IFERROR(AVERAGE(D14:H14),0) -> 0.13389957 | K14: =IFERROR(MEDIAN(D14:H14),0) -> 0.135636
B16: Gross Margin | D16: ='H2'!E21 -> 0.71539188 | E16: ='H2'!F21 -> 0.77303442 | F16: ='H2'!G21 -> 0.77823271 | G16: ='H2'!H21 -> 0.77705212 | H16: ='H2'!I21 -> 0.77550086 | J16: =IFERROR(AVERAGE(D16:H16),0) -> 0.7638424 | K16: =IFERROR(MEDIAN(D16:H16),0) -> 0.77550086
B17: EBITDA Margin | D17: ='H2'!E29 -> 0.31622782 | E17: ='H2'!F29 -> 0.34047394 | F17: ='H2'!G29 -> 0.33338731 | G17: ='H2'!H29 -> 0.32604379 | H17: ='H2'!I29 -> 0.32202833 | J17: =IFERROR(AVERAGE(D17:H17),0) -> 0.32763224 | K17: =IFERROR(MEDIAN(D17:H17),0) -> 0.32604379
B18: EBIT Margin | D18: ='H2'!E33 -> 0.2307242 | E18: ='H2'!F33 -> 0.26355479 | F18: ='H2'!G33 -> 0.24696584 | G18: ='H2'!H33 -> 0.2347167 | H18: ='H2'!I33 -> 0.23361792 | J18: =IFERROR(AVERAGE(D18:H18),0) -> 0.24191589 | K18: =IFERROR(MEDIAN(D18:H18),0) -> 0.2347167
B19: EBT Margin | D19: ='H2'!E37 -> 0.19239854 | E19: ='H2'!F37 -> 0.24010498 | F19: ='H2'!G37 -> 0.2273267 | G19: ='H2'!H37 -> 0.21769677 | H19: ='H2'!I37 -> 0.21034244 | J19: =IFERROR(AVERAGE(D19:H19),0) -> 0.21757389 | K19: =IFERROR(MEDIAN(D19:H19),0) -> 0.21769677
B20: Net Profit Margin | D20: ='H2'!E42 -> 0.14241702 | E20: ='H2'!F42 -> 0.18096918 | F20: ='H2'!G42 -> 0.16831676 | G20: ='H2'!H42 -> 0.1611088 | H20: ='H2'!I42 -> 0.16531226 | J20: =IFERROR(AVERAGE(D20:H20),0) -> 0.1636248 | K20: =IFERROR(MEDIAN(D20:H20),0) -> 0.16531226
B22: SalesExpenses%Sales | D22: ='H2'!E18 -> 0.28460812 | E22: ='H2'!F18 -> 0.22696558 | F22: ='H2'!G18 -> 0.22176729 | G22: ='H2'!H18 -> 0.22294788 | H22: ='H2'!I18 -> 0.22449914 | J22: =IFERROR(AVERAGE(D22:H22),0) -> 0.2361576 | K22: =IFERROR(MEDIAN(D22:H22),0) -> 0.22449914
B23: Depreciation%Sales | D23: ='H2'!E31 -> 0.085503615 | E23: ='H2'!F31 -> 0.076919144 | F23: ='H2'!G31 -> 0.086421467 | G23: ='H2'!H31 -> 0.091327093 | H23: ='H2'!I31 -> 0.088410409 | J23: =IFERROR(AVERAGE(D23:H23),0) -> 0.085716346 | K23: =IFERROR(MEDIAN(D23:H23),0) -> 0.086421467
B24: OperatingIncome%Sales | D24: ='H2'!E33 -> 0.2307242 | E24: ='H2'!F33 -> 0.26355479 | F24: ='H2'!G33 -> 0.24696584 | G24: ='H2'!H33 -> 0.2347167 | H24: ='H2'!I33 -> 0.23361792 | J24: =IFERROR(AVERAGE(D24:H24),0) -> 0.24191589 | K24: =IFERROR(MEDIAN(D24:H24),0) -> 0.2347167
B26: Return on Capital Employed | D26: ='H2'!E32/SUM('Balance Sheet'!U4:U6) -> 0.18975507 | E26: ='H2'!F32/SUM('Balance Sheet'!V4:V6) -> 0.1897546 | F26: ='H2'!G32/SUM('Balance Sheet'!W4:W6) -> 0.15824605 | G26: ='H2'!H32/SUM('Balance Sheet'!X4:X6) -> 0.15933721 | H26: ='H2'!I32/SUM('Balance Sheet'!Y4:Y6) -> 0.15664173 | J26: =IFERROR(AVERAGE(D26:H26),0) -> 0.17074693 | K26: =IFERROR(MEDIAN(D26:H26),0) -> 0.15933721
B27: Retained Earnings% | D27: ='H2'!E52 -> 0.864364 | E27: ='H2'!F52 -> 0.85662492 | F27: ='H2'!G52 -> 0.86050667 | G27: ='H2'!H52 -> 0.87527639 | H27: ='H2'!I52 -> 0.8737302 | J27: =IFERROR(AVERAGE(D27:H27),0) -> 0.86610043 | K27: =IFERROR(MEDIAN(D27:H27),0) -> 0.864364
B28: Return on Equity% | D28: ='H2'!E41/SUM('Balance Sheet'!U4:U5) -> 0.23425676 | E28: ='H2'!F41/SUM('Balance Sheet'!V4:V5) -> 0.20035849 | F28: ='H2'!G41/SUM('Balance Sheet'!W4:W5) -> 0.17338364 | G28: ='H2'!H41/SUM('Balance Sheet'!X4:X5) -> 0.16624915 | H28: ='H2'!I41/SUM('Balance Sheet'!Y4:Y5) -> 0.17073378 | J28: =IFERROR(AVERAGE(D28:H28),0) -> 0.18899636 | K28: =IFERROR(MEDIAN(D28:H28),0) -> 0.17338364
B29: Self Sustained Growth Rate | D29: =IFERROR(D27*D28,0) -> 0.20248311 | E29: =IFERROR(E27*E28,0) -> 0.17163208 | F29: =IFERROR(F27*F28,0) -> 0.14919778 | G29: =IFERROR(G27*G28,0) -> 0.14551396 | H29: =IFERROR(H27*H28,0) -> 0.14917526 | J29: =IFERROR(AVERAGE(D29:H29),0) -> 0.16360043 | K29: =IFERROR(MEDIAN(D29:H29),0) -> 0.14919778
B30: Debt servicing ratio | D30: ='H2'!E28/'H2'!E34 -> 5.4821079 | E30: ='H2'!F28/'H2'!F34 -> 6.8431238 | F30: ='H2'!G28/'H2'!G34 -> 6.914601 | G30: ='H2'!H28/'H2'!H34 -> 6.4345788 | H30: ='H2'!I28/'H2'!I34 -> 6.6972768 | J30: =IFERROR(AVERAGE(D30:H30),0) -> 6.4743377 | K30: =IFERROR(MEDIAN(D30:H30),0) -> 6.6972768
B31: Debt/Equity Ratio | D31: ='Balance Sheet'!U7/SUM('Balance Sheet'!U4:U5) -> 0.045608108 | E31: ='Balance Sheet'!V7/SUM('Balance Sheet'!V4:V5) -> 0 | F31: ='Balance Sheet'!W7/SUM('Balance Sheet'!W4:W5) -> 0 | G31: ='Balance Sheet'!X7/SUM('Balance Sheet'!X4:X5) -> 0 | H31: ='Balance Sheet'!Y7/SUM('Balance Sheet'!Y4:Y5) -> 0 | J31: =IFERROR(AVERAGE(D31:H31),0) -> 0.0091216216 | K31: =IFERROR(MEDIAN(D31:H31),0) -> 0
B32: Interest Coverage Ratio | D32: ='H2'!E32/'H2'!E34 -> 3.999822 | E32: ='H2'!F32/'H2'!F34 -> 5.2971399 | F32: ='H2'!G32/'H2'!G34 -> 5.1221814 | G32: ='H2'!H32/'H2'!H34 -> 4.6322093 | H32: ='H2'!I32/'H2'!I34 -> 4.8585908 | J32: =IFERROR(AVERAGE(D32:H32),0) -> 4.7819887 | K32: =IFERROR(MEDIAN(D32:H32),0) -> 4.8585908
B34: Debtor Turnover Ratio | D34: ='H2'!E12/'Balance Sheet'!U34 -> 4.86825 | E34: ='H2'!F12/'Balance Sheet'!V34 -> 3.1035294 | F34: ='H2'!G12/'Balance Sheet'!W34 -> 2.3611429 | G34: ='H2'!H12/'Balance Sheet'!X34 -> 2.5314286 | H34: ='H2'!I12/'Balance Sheet'!Y34 -> 2.2041748 | J34: =IFERROR(AVERAGE(D34:H34),0) -> 3.0137051 | K34: =IFERROR(MEDIAN(D34:H34),0) -> 2.5314286
B35: Creditor Turnover Ratio | D35: ='H2'!E9/'Balance Sheet'!U14 -> 15.215 | E35: ='H2'!F9/'Balance Sheet'!V14 -> 14.855316 | F35: ='H2'!G9/'Balance Sheet'!W14 -> 15.815854 | G35: ='H2'!H9/'Balance Sheet'!X14 -> 16.657912 | H35: ='H2'!I9/'Balance Sheet'!Y14 -> 16.862178 | J35: =IFERROR(AVERAGE(D35:H35),0) -> 15.881252 | K35: =IFERROR(MEDIAN(D35:H35),0) -> 15.815854
B36: Inventory Turnover | D36: ='H2'!E9/'Balance Sheet'!U33 -> 64.917333 | E36: ='H2'!F9/'Balance Sheet'!V33 -> 61.766842 | F36: ='H2'!G9/'Balance Sheet'!W33 -> 54.0375 | G36: ='H2'!H9/'Balance Sheet'!X33 -> 54.138214 | H36: ='H2'!I9/'Balance Sheet'!Y33 -> 40.549524 | J36: =IFERROR(AVERAGE(D36:H36),0) -> 55.081883 | K36: =IFERROR(MEDIAN(D36:H36),0) -> 54.138214
B37: Fixed Asset Turnover | D37: ='H2'!E9/'Balance Sheet'!U18 -> 1.1349184 | E37: ='H2'!F9/'Balance Sheet'!V18 -> 1.2605478 | F37: ='H2'!G9/'Balance Sheet'!W18 -> 1.0350359 | G37: ='H2'!H9/'Balance Sheet'!X18 -> 1.0843133 | H37: ='H2'!I9/'Balance Sheet'!Y18 -> 0.96986333 | J37: =IFERROR(AVERAGE(D37:H37),0) -> 1.0969358 | K37: =IFERROR(MEDIAN(D37:H37),0) -> 1.0843133
B38: Current Ratio | D38: =SUM('Balance Sheet'!U33:U37)/SUM('Balance Sheet'!U13:U16) -> 3.6846847 | E38: =SUM('Balance Sheet'!V33:V37)/SUM('Balance Sheet'!V13:V16) -> 5.3758865 | F38: =SUM('Balance Sheet'!W33:W37)/SUM('Balance Sheet'!W13:W16) -> 4.0068027 | G38: =SUM('Balance Sheet'!X33:X37)/SUM('Balance Sheet'!X13:X16) -> 2.6206897 | H38: =SUM('Balance Sheet'!Y33:Y37)/SUM('Balance Sheet'!Y13:Y16) -> 2.2616034 | J38: =IFERROR(AVERAGE(D38:H38),0) -> 3.5899334 | K38: =IFERROR(MEDIAN(D38:H38),0) -> 3.6846847
B39: Acid Test Ratio | D39: {=SUM('Balance Sheet'!U34:U37/SUM('Balance Sheet'!U13:U16))} -> 3.5495495 | E39: {=SUM('Balance Sheet'!V34:V37/SUM('Balance Sheet'!V13:V16))} -> 5.2411348 | F39: {=SUM('Balance Sheet'!W34:W37/SUM('Balance Sheet'!W13:W16))} -> 3.8435374 | G39: {=SUM('Balance Sheet'!X34:X37/SUM('Balance Sheet'!X13:X16))} -> 2.4275862 | H39: {=SUM('Balance Sheet'!Y34:Y37/SUM('Balance Sheet'!Y13:Y16))} -> 2.0843882 | J39: =IFERROR(AVERAGE(D39:H39),0) -> 3.4292392 | K39: =IFERROR(MEDIAN(D39:H39),0) -> 3.5495495
B40: Equity Capital Turnover Ratio | D40: ='H2'!E9/SUM('Balance Sheet'!U4:U5) -> 1.6448649 | E40: ='H2'!F9/SUM('Balance Sheet'!V4:V5) -> 1.1071415 | F40: ='H2'!G9/SUM('Balance Sheet'!W4:W5) -> 1.0301033 | G40: ='H2'!H9/SUM('Balance Sheet'!X4:X5) -> 1.0319061 | H40: ='H2'!I9/SUM('Balance Sheet'!Y4:Y5) -> 1.0327956 | J40: =IFERROR(AVERAGE(D40:H40),0) -> 1.1693623 | K40: =IFERROR(MEDIAN(D40:H40),0) -> 1.0327956
B42: Debtor Days | D42: =365/D34 -> 74.975607 | E42: =365/E34 -> 117.60804 | F42: =365/F34 -> 154.58616 | G42: =365/G34 -> 144.18736 | H42: =365/H34 -> 165.59486 | J42: =IFERROR(AVERAGE(D42:H42),0) -> 131.3904 | K42: =IFERROR(MEDIAN(D42:H42),0) -> 144.18736
B43: Payable Days | D43: =365/D35 -> 23.989484 | E43: =365/E35 -> 24.570328 | F43: =365/F35 -> 23.078109 | G43: =365/G35 -> 21.91151 | H43: =365/H35 -> 21.646077 | J43: =IFERROR(AVERAGE(D43:H43),0) -> 23.039102 | K43: =IFERROR(MEDIAN(D43:H43),0) -> 23.078109
B44: Inventory Days | D44: =365/D36 -> 5.6225353 | E44: =365/E36 -> 5.9093194 | F44: =365/F36 -> 6.7545686 | G44: =365/G36 -> 6.7420029 | H44: =365/H36 -> 9.0013388 | J44: =IFERROR(AVERAGE(D44:H44),0) -> 6.805953 | K44: =IFERROR(MEDIAN(D44:H44),0) -> 6.7420029
B45: Cash Conversion Cycle (in days) | D45: =(D42+D44)-D43 -> 56.608659 | E45: =(E42+E44)-E43 -> 98.947028 | F45: =(F42+F44)-F43 -> 138.26262 | G45: =(G42+G44)-G43 -> 129.01785 | H45: =(H42+H44)-H43 -> 152.95012 | J45: =IFERROR(AVERAGE(D45:H45),0) -> 115.15725 | K45: =IFERROR(MEDIAN(D45:H45),0) -> 129.01785
B47: CFO/Sales | D47: ='Cash Flow'!U4/'H2'!E9 -> 0.23003615 | E47: ='Cash Flow'!V4/'H2'!F9 -> 0.28034118 | F47: ='Cash Flow'!W4/'H2'!G9 -> 0.2475133 | G47: ='Cash Flow'!X4/'H2'!H9 -> 0.26123612 | H47: ='Cash Flow'!Y4/'H2'!I9 -> 0.24661202 | J47: =IFERROR(AVERAGE(D47:H47),0) -> 0.25314775 | K47: =IFERROR(MEDIAN(D47:H47),0) -> 0.2475133
B48: CFO/Total Assets | D48: ='Cash Flow'!U4/'Balance Sheet'!U38 -> 0.17283951 | E48: ='Cash Flow'!V4/'Balance Sheet'!V38 -> 0.18577075 | F48: ='Cash Flow'!W4/'Balance Sheet'!W38 -> 0.14792627 | G48: ='Cash Flow'!X4/'Balance Sheet'!X38 -> 0.16659655 | H48: ='Cash Flow'!Y4/'Balance Sheet'!Y38 -> 0.15135135 | J48: =IFERROR(AVERAGE(D48:H48),0) -> 0.16489689 | K48: =IFERROR(MEDIAN(D48:H48),0) -> 0.16659655
B49: CFO/Total Debt | D49: ='Cash Flow'!U4/'Balance Sheet'!U6 -> 0.37837838 | E49: ='Cash Flow'!V4/'Balance Sheet'!V6 -> 0.57719298 | F49: ='Cash Flow'!W4/'Balance Sheet'!W6 -> 0.41960784 | G49: ='Cash Flow'!X4/'Balance Sheet'!X6 -> 0.51832461 | H49: ='Cash Flow'!Y4/'Balance Sheet'!Y6 -> 0.47138047 | J49: =IFERROR(AVERAGE(D49:H49),0) -> 0.47297686 | K49: =IFERROR(MEDIAN(D49:H49),0) -> 0.47138047
B51: Interpretation

Sheet Valuations
B3: V | C3: aluations
B6: Company Comparables
L7: EV/Revenue | M7: EV/EBITDA | N7: P/E
L8: ='V3'!O30/'V3'!O31 -> 1368.3104 | M8: ='V3'!P30/'V3'!P31 -> 2010.1961 | N8: ='V3'!Q30/'V3'!Q31 -> 1849.3867
L9: =IF('V3'!E13<L8,"Undervalued","Overvalued") -> Overvalued | M9: =IF($D$7<M8,"Undervalued","Overvalued") -> Undervalued | N9: =IF($D$7<N8,"Undervalued","Overvalued") -> Undervalued
B20: DCF
L21: Equity Value (DCF) | M21: ='V2'!G41 -> 10996.379
L22: No of shares | M22: ='V2'!G42 -> 10.155916
L23: Value Per Share | M23: ='V2'!G43 -> 1082.756
L24: CMP | M24: ='V2'!G44 -> 1439.8
L25: OV/UV By | M25: ='V2'!G45 -> -0.24798163

Sheet V2
B3: V | C3: aluations
B6: Period | C6: 2023 | G6: =C6+1 -> 2024 | H6: =G6+1 -> 2025 | I6: =H6+1 -> 2026 | J6: =I6+1 -> 2027 | K6: =J6+1 -> 2028 | L6: =K6+1 -> 2029 | M6: =L6+1 -> 2030 | N6: =M6+1 -> 2031
B7: Year | J7: 1 | K7: =J7+1 -> 2 | L7: =K7+1 -> 3 | M7: =L7+1 -> 4 | N7: =M7+1 -> 5
B8: Growth | G8: ='Data Sheet'!I17/'Data Sheet'!H17-1 -> 0.1050896 | H8: ='Data Sheet'!J17/'Data Sheet'!I17-1 -> 0.16884108 | I8: ='Data Sheet'!K17/'Data Sheet'!J17-1 -> 0.12350004 | J8: =AVERAGE($G$8:$I$8) -> 0.13247691 | K8: =AVERAGE($G$8:$I$8) -> 0.13247691 | L8: =AVERAGE($G$8:$I$8) -> 0.13247691 | M8: =AVERAGE($G$8:$I$8) -> 0.13247691 | N8: =AVERAGE($G$8:$I$8) -> 0.13247691
B9: Revenue | G9: ='H2'!G9 -> 1296.9 | H9: ='H2'!H9 -> 1515.87 | I9: ='H2'!I9 -> 1703.08 | J9: =I9*(1+J8) -> 1928.6988 | K9: =J9*(1+K8) -> 2184.2068 | L9: =K9*(1+L8) -> 2473.5638 | M9: =L9*(1+M8) -> 2801.2538 | N9: =M9*(1+N8) -> 3172.3553
B10: EBITDA | G10: ='H2'!G28 -> 432.37 | H10: ='H2'!H28 -> 494.24 | I10: ='H2'!I28 -> 548.44 | J10: =J9*J11 -> 630.97986 | K10: =K9*K11 -> 714.57012 | L10: =L9*L11 -> 809.23416 | M10: =M9*M11 -> 916.439 | N10: =N9*N11 -> 1037.846
B11: EBITDA Margin% | G11: =G10/G9 -> 0.33338731 | H11: =H10/H9 -> 0.32604379 | I11: =I10/I9 -> 0.32202833 | J11: =AVERAGE($G$11:$I$11) -> 0.32715314 | K11: =AVERAGE($G$11:$I$11) -> 0.32715314 | L11: =AVERAGE($G$11:$I$11) -> 0.32715314 | M11: =AVERAGE($G$11:$I$11) -> 0.32715314 | N11: =AVERAGE($G$11:$I$11) -> 0.32715314
B12: Less: Depreciation & Ammortisation | G12: ='H2'!G30 -> 112.08 | H12: ='H2'!H30 -> 138.44 | I12: ='H2'!I30 -> 150.57 | J12: =J9*J13 -> 171.11349 | K12: =K9*K13 -> 193.78208 | L12: =L9*L13 -> 219.45373 | M12: =M9*M13 -> 248.52628 | N12: =N9*N13 -> 281.45027
B13: Depreciation % Sales | G13: =G12/G9 -> 0.086421467 | H13: =H12/H9 -> 0.091327093 | I13: =I12/I9 -> 0.088410409 | J13: =AVERAGE($G$13:$I$13) -> 0.088719656 | K13: =AVERAGE($G$13:$I$13) -> 0.088719656 | L13: =AVERAGE($G$13:$I$13) -> 0.088719656 | M13: =AVERAGE($G$13:$I$13) -> 0.088719656 | N13: =AVERAGE($G$13:$I$13) -> 0.088719656
B14: EBIT | G14: =(G10-G12) -> 320.29 | H14: =(H10-H12) -> 355.8 | I14: =(I10-I12) -> 397.87 | J14: =(J10-J12) -> 459.86637 | K14: =(K10-K12) -> 520.78804 | L14: =(L10-L12) -> 589.78043 | M14: =(M10-M12) -> 667.91272 | N14: =(N10-N12) -> 756.39573
B15: Less: Tax | G15: ='H2'!G38 -> 76.53 | H15: ='H2'!H38 -> 85.78 | I15: ='H2'!I38 -> 76.69 | J15: =J14*J16 -> 112.45294 | K15: =K14*K16 -> 127.35036 | L15: =L14*L16 -> 144.22134 | M15: =M14*M16 -> 163.32734 | N15: =N14*N16 -> 184.96444
B16: Tax % EBT | G16: ='H2'!G39 -> 0.25958212 | H16: ='H2'!H39 -> 0.25993939 | I16: ='H2'!I39 -> 0.21408034 | J16: =AVERAGE($G$16:$I$16) -> 0.24453395 | K16: =AVERAGE($G$16:$I$16) -> 0.24453395 | L16: =AVERAGE($G$16:$I$16) -> 0.24453395 | M16: =AVERAGE($G$16:$I$16) -> 0.24453395 | N16: =AVERAGE($G$16:$I$16) -> 0.24453395
B17: EBIT(1-Tax) | G17: =G14-G15 -> 243.76 | H17: =H14-H15 -> 270.02 | I17: =I14-I15 -> 321.18 | J17: =J14-J15 -> 347.41343 | K17: =K14-K15 -> 393.43769 | L17: =L14-L15 -> 445.55909 | M17: =M14-M15 -> 504.58538 | N17: =N14-N15 -> 571.43129
B18: Add: Depreciation & Ammortisation | G18: ='H2'!G30 -> 112.08 | H18: ='H2'!H30 -> 138.44 | I18: ='H2'!I30 -> 150.57 | J18: =J12 -> 171.11349 | K18: =K12 -> 193.78208 | L18: =L12 -> 219.45373 | M18: =M12 -> 248.52628 | N18: =N12 -> 281.45027
B19: NOPAT | G19: =G17+G18 -> 355.84 | H19: =H17+H18 -> 408.46 | I19: =I17+I18 -> 471.75 | J19: =J17+J18 -> 518.52692 | K19: =K17+K18 -> 587.21976 | L19: =L17+L18 -> 665.01282 | M19: =M17+M18 -> 753.11166 | N19: =N17+N18 -> 852.88156
B20: Less: Capex | G20: =-'Cash Flow'!W15 -> 354 | H20: =-'Cash Flow'!X15 -> 146 | I20: =-'Cash Flow'!Y15 -> 216 | J20: =J9*12% -> 231.44385 | K20: =K9*12% -> 262.10482 | L20: =L9*12% -> 296.82765 | M20: =M9*12% -> 336.15046 | N20: =N9*12% -> 380.68263
B21: Add: Reinvestment | G21: ='Cash Flow'!W16 -> 0 | H21: ='Cash Flow'!X16 -> 0 | I21: ='Cash Flow'!Y16 -> 1 | J21: 0 | K21: 0 | L21: 0 | M21: 0 | N21: 0
B22: Less: Net Change in Working Capital | G22: =G52 -> 21 | H22: =H52 -> 2 | I22: =I52 -> 30 | J22: =J52 -> -12.769624 | K22: =K52 -> 4.1373035 | L22: =L52 -> 4.6854007 | M22: =M52 -> 5.3061081 | N22: =N52 -> 6.0090449
B23: Free Cash Flow to the Firm | G23: =(G19-G20-G22)+G21 -> -19.16 | H23: =(H19-H20-H22)+H21 -> 260.46 | I23: =(I19-I20-I22)+I21 -> 226.75 | J23: =(J19-J20-J22)+J21 -> 299.85269 | K23: =(K19-K20-K22)+K21 -> 320.97764 | L23: =(L19-L20-L22)+L21 -> 363.49977 | M23: =(M19-M20-M22)+M21 -> 411.65509 | N23: =(N19-N20-N22)+N21 -> 466.18988
B24: Discount Rate (r)
B25: PV of Free Cash Flows | J25: =J23/(1+$D$41)^J7 -> 278.29567 | K25: =K23/(1+$D$41)^K7 -> 276.48512 | L25: =L23/(1+$D$41)^L7 -> 290.60268 | M25: =M23/(1+$D$41)^M7 -> 305.44109 | N25: =N23/(1+$D$41)^N7 -> 321.03716
B27: WACC | F27: Sum of PV of FCFF | G27: =SUM(J25:N25) -> 1471.8617 | I27: Market Cap. In Cr.
B28: Cost of Debt | I28: =D35 -> 14622.487
B29: Debt | D29: ='Balance Sheet'!Y6 -> 891 | F29: Terminal Value
B30: % Debt | D30: =D29/SUM((D29,D35)) -> 0.057433895 | F30: Terminal Growth Rate | G30: 0.042 | I30: Intrinsic Value DCF
B31: Cost of Debt | D31: ='H2'!I34/'Balance Sheet'!Y6 -> 0.091907969 | F31: Terminal Value | G31: =(N23*(1+G30))/(D41-G30) -> 13698.758 | I31: =G41 -> 10996.379
B32: Tax Rate | D32: 0.245 | F32: PV of TV | G32: =G31/((1+D41)^N7) -> 9433.5173
I33: Current Market Price
B34: Cost of Equity | D34: =D37+D38*(D39-D37) -> 0.077952625 | F34: Enterprise Value 1 + 2 | I34: =G44 -> 1439.8
B35: Equity | D35: =Profile!C43*('Data Sheet'!K70/10000000) -> 14622.487 | F35: Enterprise Value | G35: =G32+G27 -> 10905.379
B36: % Equity | D36: =D35/SUM(D35,D29) -> 0.9425661 | F36: Add: Cash | G36: 594 | I36: Implied Share Price
B37: Risk Free Rate | D37: 0.0687 | F37: Add: Other Non Operating Assets | G37: ='Balance Sheet'!Y31 -> 404 | I37: =G43 -> 1082.756
B38: Beta | D38: =Closing!Y3 -> 0.81881635 | F38: Less: Debt | G38: ='Balance Sheet'!Y6 -> 891
B39: Market Return | D39: 0.08 | F39: Less: Minority Interest | G39: ='Balance Sheet'!Y13 -> 16
I40: =G43 -> 1082.756 | J40: =K40-1% -> 0.057461865 | K40: =L40-1% -> 0.067461865 | L40: 0.077461865 | M40: =L40+1% -> 0.087461865 | N40: =M40+0.5% -> 0.092461865
B41: WACC | D41: =((D34*D36))+((D31*D30)*(1-D32)) -> 0.07746087 | F41: Equity Value (DCF) | G41: =(G35+G36+G37)-(G38+G39) -> 10996.379 | I41: =I42-1% -> 0.022 | J41: 1163.0264 | K41: 902.65463 | L41: 736.37933 | M41: 621.06933 | N41: 575.74303
F42: No of shares | G42: =('Data Sheet'!K70/10000000) -> 10.155916 | I42: =I43-1% -> 0.032 | J42: 1569.5943 | K42: 1121.948 | L42: 871.46038 | M42: 711.4769 | N42: 651.3885
F43: Value Per Share | G43: =G41/G42 -> 1082.756 | I43: 0.042 | J43: 2502.0598 | K43: 1513.4937 | L43: 1082.7253 | M43: 841.65738 | N43: 757.01522
F44: CMP | G44: =Profile!C43 -> 1439.8 | I44: =I43+1% -> 0.052 | J44: 6848.9835 | K44: 2411.5058 | L44: 1459.9362 | M44: 1045.2579 | N44: 914.85244
F45: OV/UV By | G45: =(G43/G44)-1 -> -0.24798163 | I45: =I44+1% -> 0.062 | J45: -7961.408 | K45: 6597.8159 | L45: 2325.0715 | M45: 1408.7841 | N45: 1176.319
B47: Change in Working Capital Calculation | F47: 2023 | G47: 2024 | H47: =G47+1 -> 2025 | I47: =H47+1 -> 2026 | J47: =I47+1 -> 2027 | K47: =J47+1 -> 2028 | L47: =K47+1 -> 2029 | M47: =L47+1 -> 2030 | N47: =M47+1 -> 2031
B48: Debtors/Receivables | F48: ='Balance Sheet'!V34 -> 51 | G48: ='Balance Sheet'!W34 -> 70 | H48: ='Balance Sheet'!X34 -> 77 | I48: ='Balance Sheet'!Y34 -> 103
B49: Payables | F49: ='Balance Sheet'!V14 -> 79 | G49: ='Balance Sheet'!W14 -> 82 | H49: ='Balance Sheet'!X14 -> 91 | I49: ='Balance Sheet'!Y14 -> 101
B50: (Others) + | F50: ='Balance Sheet'!V33 -> 19 | G50: ='Balance Sheet'!W33 -> 24 | H50: ='Balance Sheet'!X33 -> 28 | I50: ='Balance Sheet'!Y33 -> 42
B51: Working Capital | F51: =(F48+F50)-F49 -> -9 | G51: =(G48+G50)-G49 -> 12 | H51: =(H48+H50)-H49 -> 14 | I51: =(I48+I50)-I49 -> 44 | J51: =J9*J53 -> 31.230376 | K51: =K9*K53 -> 35.367679 | L51: =L9*L53 -> 40.05308 | M51: =M9*M53 -> 45.359188 | N51: =N9*N53 -> 51.368233
B52: Net Change in Working Capital | G52: =G51-(F51) -> 21 | H52: =H51-(G51) -> 2 | I52: =I51-(H51) -> 30 | J52: =J51-I51 -> -12.769624 | K52: =K51-J51 -> 4.1373035 | L52: =L51-K51 -> 4.6854007 | M52: =M51-L51 -> 5.3061081 | N52: =N51-M51 -> 6.0090449
B53: Working Capital % Sales | G53: =G52/G9 -> 0.016192459 | H53: =H52/H9 -> 0.0013193744 | I53: =I52/I9 -> 0.017615144 | J53: =MEDIAN(G53:I53) -> 0.016192459 | K53: =MEDIAN(H53:J53) -> 0.016192459 | L53: =MEDIAN(I53:K53) -> 0.016192459 | M53: =MEDIAN(J53:L53) -> 0.016192459 | N53: =MEDIAN(K53:M53) -> 0.016192459
B55: Working Capital = Debtors + Inventories - payables

Sheet V3
B3: V | C3: aluations
B6: Relative Valuation
B8: Relative Valuation method 22/08/26 Healthcare
E10: Market Data | K10: Financials | O10: Valuation
B11: Company | D11: Ticker | E11: Share Price | F11: Shares Outstanding | G11: Equity Value | H11: Net Debt | I11: Enterprise Value | K11: Revenue | L11: EBITDA | M11: Net Income | O11: EV/Revenue | P11: EV/EBITDA | Q11: P/E
A13: x | B13: Rainbow Hosp. | D13: RAINBOW | E13: =Profile!C43 -> 1439.8 | F13: ='Data Sheet'!K70/10000000 -> 10.155916 | G13: =E13*F13 -> 14622.487 | H13: =891-20.3 -> 870.7 | I13: =G13+H13 -> 15493.187 | K13: 1820 | L13: ='H2'!I28 -> 548.44 | M13: ='H2'!I41 -> 281.54 | O13: =I13/K13 -> 8.5127403 | P13: =I13/L13 -> 28.249557 | Q13: =G13/M13 -> 51.937513
B14: Max | D14: MAXHEALTH | E14: 1000 | F14: 97.2 | G14: =E14*F14 -> 97200 | H14: =3478-682 -> 2796 | I14: =G14+H14 -> 99996 | K14: 8712 | L14: 2318 | M14: 1457 | O14: =I14/K14 -> 11.477961 | P14: =I14/L14 -> 43.138913 | Q14: =G14/M14 -> 66.712423
B15: Apollo | D15: APOLLOHOSP | E15: 8693 | F15: 14.4 | G15: =E15*F15 -> 125179.2 | H15: =8493-1360 -> 7133 | I15: =G15+H15 -> 132312.2 | K15: 26430 | L15: 4010 | M15: 2172 | O15: =I15/K15 -> 5.006137 | P15: =I15/L15 -> 32.995561 | Q15: =G15/M15 -> 57.633149
B16: Fortis | D16: FORTIS | E16: 907 | F16: 75.5 | G16: =E16*F16 -> 68478.5 | H16: =3473-508 -> 2965 | I16: =G16+H16 -> 71443.5 | K16: 9506 | L16: 2131 | M16: 1070 | O16: =I16/K16 -> 7.5156217 | P16: =I16/L16 -> 33.525809 | Q16: =G16/M16 -> 63.998598
B17: Aster DM | D17: ASTERDM | E17: 762 | F17: 87.17 | G17: =E17*F17 -> 66423.54 | H17: =2220-1380 -> 840 | I17: =G17+H17 -> 67263.54 | K17: 4876 | L17: 918 | M17: 363 | O17: =I17/K17 -> 13.79482 | P17: =I17/L17 -> 73.27183 | Q17: =G17/M17 -> 182.98496
B18: Medanta | D18: MEDANTA | E18: 1410 | F18: 26.9 | G18: =E18*F18 -> 37929 | H18: =1190-1122 -> 68 | I18: =G18+H18 -> 37997 | K18: 4683 | L18: 979 | M18: 552 | O18: =I18/K18 -> 8.1138159 | P18: =I18/L18 -> 38.812053 | Q18: =G18/M18 -> 68.711957
A20: x | B20: High | O20: =MAX(O14:O18) -> 13.79482 | P20: =MAX(P14:P18) -> 73.27183 | Q20: =MAX(Q14:Q18) -> 182.98496
B21: 75th Percentile | O21: =QUARTILE(O14:O18,3) -> 11.477961 | P21: =QUARTILE(P14:P18,3) -> 43.138913 | Q21: =QUARTILE(Q14:Q18,3) -> 68.711957
B22: Average | O22: =AVERAGE(O14:O18) -> 9.1816711 | P22: =AVERAGE(P14:P18) -> 44.348833 | Q22: =AVERAGE(Q14:Q18) -> 88.008217
B23: Median | O23: =MEDIAN(O14:O18) -> 8.1138159 | P23: =MEDIAN(P14:P18) -> 38.812053 | Q23: =MEDIAN(Q14:Q18) -> 66.712423
B24: 25th Percentile | O24: =QUARTILE(O14:O18,1) -> 7.5156217 | P24: =QUARTILE(P14:P18,1) -> 33.525809 | Q24: =QUARTILE(Q14:Q18,1) -> 63.998598
B25: Low | O25: =MIN(O14:O18) -> 5.006137 | P25: =MIN(P14:P18) -> 32.995561 | Q25: =MIN(Q14:Q18) -> 57.633149
A27: x | B27: Max Health | O27: EV/Revenue | P27: EV/EBITDA | Q27: P/E
B28: Implied Enterprise Value | O28: =K13*O23 -> 14767.145 | P28: =L13*P23 -> 21286.082 | Q28: =Q30-Q29 -> 17911.516
B29: Net Debt | O29: =H13 -> 870.7 | P29: =O29 -> 870.7 | Q29: =H13 -> 870.7
B30: Implied Market Value | O30: =O28-O29 -> 13896.445 | P30: =P28-P29 -> 20415.382 | Q30: =M13*Q23 -> 18782.216
B31: Shares Outstanding | O31: =F13 -> 10.155916 | P31: =O31 -> 10.155916 | Q31: =P31 -> 10.155916
A32: x | B32: Implied Value Per Share | O32: =O30/O31 -> 1368.3104 | P32: =P30/P31 -> 2010.1961 | Q32: =Q30/Q31 -> 1849.3867
O33: =IF(E13<O32,"Undervalued","Overvalued") -> Overvalued | P33: =IF($D$7<P32,"Undervalued","Overvalued") -> Undervalued | Q33: =IF($D$7<Q32,"Undervalued","Overvalued") -> Undervalued
B35: Interpretation

Sheet Risks
B4: R | C4: isks

Sheet Dupont
B4: R | C4: isks
B7: Return on Equity (ROE)
E8: 44651 | F8: 45016 | G8: 45382 | H8: 45747 | I8: 46112
B9: Net Profit | E9: ='H2'!E41 -> 138.68 | F9: ='H2'!F41 -> 212.38 | G9: ='H2'!G41 -> 218.29 | H9: ='H2'!H41 -> 244.22 | I9: ='H2'!I41 -> 281.54
B10: Average Shareholder Equity | E10: =SUM('Balance Sheet'!U4:U5) -> 592 | F10: =SUM('Balance Sheet'!V4:V5) -> 1060 | G10: =SUM('Balance Sheet'!W4:W5) -> 1259 | H10: =SUM('Balance Sheet'!X4:X5) -> 1469 | I10: =SUM('Balance Sheet'!Y4:Y5) -> 1649
B11: Return on Equity | E11: =E9/E10 -> 0.23425676 | F11: =F9/F10 -> 0.20035849 | G11: =G9/G10 -> 0.17338364 | H11: =H9/H10 -> 0.16624915 | I11: =I9/I10 -> 0.17073378
B13: ROE - Dupont Equation
E14: =E8 -> 44651 | F14: =F8 -> 45016 | G14: =G8 -> 45382 | H14: =H8 -> 45747 | I14: =I8 -> 46112
B15: =B9 -> Net Profit | E15: =E9 -> 138.68 | F15: =F9 -> 212.38 | G15: =G9 -> 218.29 | H15: =H9 -> 244.22 | I15: =I9 -> 281.54
B16: Revenue | E16: ='H2'!E9 -> 973.76 | F16: ='H2'!F9 -> 1173.57 | G16: ='H2'!G9 -> 1296.9 | H16: ='H2'!H9 -> 1515.87 | I16: ='H2'!I9 -> 1703.08
B17: Net Profit Margin | E17: =E15/E16 -> 0.14241702 | F17: =F15/F16 -> 0.18096918 | G17: =G15/G16 -> 0.16831676 | H17: =H15/H16 -> 0.1611088 | I17: =I15/I16 -> 0.16531226
B19: Revenue | E19: =E16 -> 973.76 | F19: =F16 -> 1173.57 | G19: =G16 -> 1296.9 | H19: =H16 -> 1515.87 | I19: =I16 -> 1703.08
B20: Average Total Asset | E20: {=SUM('Balance Sheet'!T38:U380/2)} -> 1188.5 | F20: {=SUM('Balance Sheet'!U38:V380/2)} -> 1533.5 | G20: {=SUM('Balance Sheet'!V38:W380/2)} -> 1970.5 | H20: {=SUM('Balance Sheet'!W38:X380/2)} -> 2273.5 | I20: {=SUM('Balance Sheet'!X38:Y380/2)} -> 2576
B21: Asset Turnover Ratio | E21: =E19/E20 -> 0.81931847 | F21: =F19/F20 -> 0.76528856 | G21: =G19/G20 -> 0.65815783 | H21: =H19/H20 -> 0.6667561 | I21: =I19/I20 -> 0.66113354
B23: =B20 -> Average Total Asset | E23: =E20 -> 1188.5 | F23: =F20 -> 1533.5 | G23: =G20 -> 1970.5 | H23: =H20 -> 2273.5 | I23: =I20 -> 2576
B24: =B10 -> Average Shareholder Equity | E24: =E10 -> 592 | F24: =F10 -> 1060 | G24: =G10 -> 1259 | H24: =H10 -> 1469 | I24: =I10 -> 1649
B25: Equity Multiplier (C) | E25: =E23/E24 -> 2.0076014 | F25: =F23/F24 -> 1.4466981 | G25: =G23/G24 -> 1.5651311 | H25: =H23/H24 -> 1.5476515 | I25: =I23/I24 -> 1.5621589
B27: Return on Equity (A*B*C) | E27: =E25*E21*E17 -> 0.23425676 | F27: =F25*F21*F17 -> 0.20035849 | G27: =G25*G21*G17 -> 0.17338364 | H27: =H25*H21*H17 -> 0.16624915 | I27: =I25*I21*I17 -> 0.17073378
B29: Return on Asset
E30: =E14 -> 44651 | F30: =F14 -> 45016 | G30: =G14 -> 45382 | H30: =H14 -> 45747 | I30: =I14 -> 46112
B31: Net Profit | E31: =E15 -> 138.68 | F31: =F15 -> 212.38 | G31: =G15 -> 218.29 | H31: =H15 -> 244.22 | I31: =I15 -> 281.54
B32: =B23 -> Average Total Asset | E32: =E20 -> 1188.5 | F32: =F20 -> 1533.5 | G32: =G20 -> 1970.5 | H32: =H20 -> 2273.5 | I32: =I20 -> 2576
B33: Return on Asset | E33: =E31/E32 -> 0.1166849 | F33: =F31/F32 -> 0.13849364 | G33: =G31/G32 -> 0.11077899 | H33: =H31/H32 -> 0.10742028 | I33: =I31/I32 -> 0.10929348
B35: ROA - Dupont Equation
E36: =E30 -> 44651 | F36: =F30 -> 45016 | G36: =G30 -> 45382 | H36: =H30 -> 45747 | I36: =I30 -> 46112
B37: =B31 -> Net Profit | E37: =E31 -> 138.68 | F37: =F31 -> 212.38 | G37: =G31 -> 218.29 | H37: =H31 -> 244.22 | I37: =I31 -> 281.54
B38: Revenue | E38: =E19 -> 973.76 | F38: =F19 -> 1173.57 | G38: =G19 -> 1296.9 | H38: =H19 -> 1515.87 | I38: =I19 -> 1703.08
B39: Net Profit Margin (A) | E39: =E37/E38 -> 0.14241702 | F39: =F37/F38 -> 0.18096918 | G39: =G37/G38 -> 0.16831676 | H39: =H37/H38 -> 0.1611088 | I39: =I37/I38 -> 0.16531226
B41: Revenue | E41: =E38 -> 973.76 | F41: =F38 -> 1173.57 | G41: =G38 -> 1296.9 | H41: =H38 -> 1515.87 | I41: =I38 -> 1703.08
B42: Average Total Asset | E42: =E32 -> 1188.5 | F42: =F32 -> 1533.5 | G42: =G32 -> 1970.5 | H42: =H32 -> 2273.5 | I42: =I32 -> 2576
B43: Asset Turnover Ratio (B) | E43: =E41/E42 -> 0.81931847 | F43: =F41/F42 -> 0.76528856 | G43: =G41/G42 -> 0.65815783 | H43: =H41/H42 -> 0.6667561 | I43: =I41/I42 -> 0.66113354
B45: Return on Asset (A*B) | E45: =E43*E39 -> 0.1166849 | F45: =F43*F39 -> 0.13849364 | G45: =G43*G39 -> 0.11077899 | H45: =H43*H39 -> 0.10742028 | I45: =I43*I39 -> 0.10929348
B47: Interpretation

Sheet Altman Z
B4: R | C4: isks
B7: Working Capital / Total Assets
E8: 44651 | F8: 45016 | G8: 45382 | H8: 45747 | I8: 46112
B9: Working Capital | E9: ='Data Sheet'!G65-'Data Sheet'!G60 -> 297.41 | F9: =SUM('Balance Sheet'!V32-'Balance Sheet'!V12) -> 619 | G9: =SUM('Balance Sheet'!W32-'Balance Sheet'!W12) -> 444 | H9: =SUM('Balance Sheet'!X32-'Balance Sheet'!X12) -> 235 | I9: =SUM('Balance Sheet'!Y32-'Balance Sheet'!Y12) -> 299
B10: Total Assets | E10: ='Balance Sheet'!U38 -> 1296 | F10: ='Balance Sheet'!V38 -> 1771 | G10: ='Balance Sheet'!W38 -> 2170 | H10: ='Balance Sheet'!X38 -> 2377 | I10: ='Balance Sheet'!Y38 -> 2775
B11: Working Capital / Total Assets (A) | E11: =E9/E10 -> 0.22948302 | F11: =F9/F10 -> 0.34952005 | G11: =G9/G10 -> 0.20460829 | H11: =H9/H10 -> 0.098864114 | I11: =I9/I10 -> 0.10774775
B13: Retained Earnings / Total Assets
E14: =E8 -> 44651 | F14: =F8 -> 45016 | G14: =G8 -> 45382 | H14: =H8 -> 45747 | I14: =I8 -> 46112
B15: Retained Earnings | E15: ='H2'!E52 -> 0.864364 | F15: ='H2'!F52 -> 0.85662492 | G15: ='H2'!G52 -> 0.86050667 | H15: ='H2'!H52 -> 0.87527639 | I15: ='H2'!I52 -> 0.8737302
B16: Total Assets | E16: =E10 -> 1296 | F16: =F10 -> 1771 | G16: =G10 -> 2170 | H16: =H10 -> 2377 | I16: =I10 -> 2775
B17: Retained Earnings / Total Assets (B) | E17: =E15/E16 -> 0.00066694753 | F17: =F15/F16 -> 0.00048369561 | G17: =G15/G16 -> 0.00039654685 | H17: =H15/H16 -> 0.00036822734 | I17: =I15/I16 -> 0.00031485773
B19: EBIT / Total Assets
B20: EBIT | E20: ='H2'!E32 -> 224.67 | F20: ='H2'!F32 -> 309.3 | G20: ='H2'!G32 -> 320.29 | H20: ='H2'!H32 -> 355.8 | I20: ='H2'!I32 -> 397.87
B21: Total Assets | E21: =E16 -> 1296 | F21: =F16 -> 1771 | G21: =G16 -> 2170 | H21: =H16 -> 2377 | I21: =I16 -> 2775
B22: EBIT/Total Assets (C) | E22: =E20/E21 -> 0.17335648 | F22: =F20/F21 -> 0.17464709 | G22: =G20/G21 -> 0.14759908 | H22: =H20/H21 -> 0.14968448 | I22: =I20/I21 -> 0.14337658
B24: Market Cap / Liabilities
B25: Market Cap | E25: =450.2*'Data Sheet'!G93 -> 4236.382 | F25: ='Data Sheet'!H90*'Data Sheet'!H93 -> 7414.575 | G25: ='Data Sheet'!I90*'Data Sheet'!I93 -> 13170.132 | H25: ='Data Sheet'!J90*'Data Sheet'!J93 -> 14241.272 | I25: =Profile!C43*('Data Sheet'!K70/10000000) -> 14622.487
B26: Long Term Liabilities | E26: ='Balance Sheet'!U6 -> 592 | F26: ='Balance Sheet'!V6 -> 570 | G26: ='Balance Sheet'!W6 -> 765 | H26: ='Balance Sheet'!X6 -> 764 | I26: ='Balance Sheet'!Y6 -> 891
B27: Market Cap / Liabilities (D) | E27: =E25/E26 -> 7.1560507 | F27: =IFERROR(F25/F26,0) -> 13.008026 | G27: =G25/G26 -> 17.215859 | H27: =H25/H26 -> 18.640408 | I27: =I25/I26 -> 16.411321
B29: Sales / Total Assets
E30: =E14 -> 44651 | F30: =F14 -> 45016 | G30: =G14 -> 45382 | H30: =H14 -> 45747 | I30: =I14 -> 46112
B31: Total Sales | E31: ='H2'!E9 -> 973.76 | F31: ='H2'!F9 -> 1173.57 | G31: ='H2'!G9 -> 1296.9 | H31: ='H2'!H9 -> 1515.87 | I31: ='H2'!I9 -> 1703.08
B32: Total Assets | E32: =E10 -> 1296 | F32: =F10 -> 1771 | G32: =G10 -> 2170 | H32: =H10 -> 2377 | I32: =I10 -> 2775
B33: Return on Asset (E) | E33: =E31/E32 -> 0.75135802 | F33: =F31/F32 -> 0.66265951 | G33: =G31/G32 -> 0.59764977 | H33: =H31/H32 -> 0.63772402 | I33: =I31/I32 -> 0.61372252
B35: Altman's Z Score
E36: =E30 -> 44651 | F36: =F30 -> 45016 | G36: =G30 -> 45382 | H36: =H30 -> 45747 | I36: =I30 -> 46112
B37: Final Score | E37: =(E11*1.2)+(E17*1.4)+(E22*3.3)+(E27*0.6)+(E33*1) -> 5.8933782 | F37: =(F11*1.2)+(F17*1.4)+(F22*3.3)+(F27*0.6)+(F33*1) -> 9.4639119 | G37: =(G11*1.2)+(G17*1.4)+(G22*3.3)+(G27*0.6)+(G33*1) -> 11.660328 | H37: =(H11*1.2)+(H17*1.4)+(H22*3.3)+(H27*0.6)+(H33*1) -> 12.43508 | I37: =(I11*1.2)+(I17*1.4)+(I22*3.3)+(I27*0.6)+(I33*1) -> 11.063396
B38: Financial Stability | E38: =IF(E37<1.81," Distressed",IF(E37>3,"Strong","Grey Zone")) -> Strong | F38: =IF(F37<1.81," Distressed",IF(F37>3,"Strong","Grey Zone")) -> Strong | G38: =IF(G37<1.81," Distressed",IF(G37>3,"Strong","Grey Zone")) -> Strong | H38: =IF(H37<1.81," Distressed",IF(H37>3,"Strong","Grey Zone")) -> Strong | I38: =IF(I37<1.81," Distressed",IF(I37>3,"Strong","Grey Zone")) -> Strong
B40: Interpretation

Sheet Monte Carlo
B4: R | C4: isks
B7: Date | C7: Price | D7: Return | E7: Sorted Return | G7: Replication | H7: Simulated Returns | J7: Calculation of Value at Risk - Apollo Tyres (Simulation)
B8: 44712 | C8: =Closing!Q2 -> 490.58237
B9: 44742 | C9: =Closing!Q3 -> 459.74826 | D9: =C9/C8-1 -> -0.062852048 | E9: 0.25014224 | G9: 1 | H9: =NORMINV(RAND(),N$10,N$11) -> 0.10881665 | J9: Historical Approach
B10: 44773 | C10: =Closing!Q4 -> 482.49149 | D10: =C10/C9-1 -> 0.049468866 | E10: 0.24887534 | G10: 2 | H10: =NORMINV(RAND(),N$10,N$11) -> -0.078434446 | J10: Mean | N10: =AVERAGE(E9:E59) -> 0.024543064
B11: 44804 | C11: =Closing!Q5 -> 602.57172 | D11: =C11/C10-1 -> 0.24887534 | E11: 0.15312364 | G11: 3 | H11: =NORMINV(RAND(),N$10,N$11) -> -0.014068853 | J11: Std Deviation | N11: =STDEV(E9:E59) -> 0.082906077
B12: 44834 | C12: =Closing!Q6 -> 624.55133 | D12: =C12/C11-1 -> 0.036476346 | E12: 0.14868374 | G12: 4 | H12: =NORMINV(RAND(),N$10,N$11) -> 0.10522255 | J12: Min | N12: =MIN(E9:E59) -> -0.13780305
B13: 44865 | C13: =Closing!Q7 -> 682.17029 | D13: =C13/C12-1 -> 0.09225656 | E13: 0.130768 | G13: 5 | H13: =NORMINV(RAND(),N$10,N$11) -> 0.038140484 | J13: Max | N13: =MAX(E9:E59) -> 0.25014224
B14: 44895 | C14: =Closing!Q8 -> 738.10614 | D14: =C14/C13-1 -> 0.081996905 | E14: 0.11594412 | G14: 6 | H14: =NORMINV(RAND(),N$10,N$11) -> -0.021834801 | J14: CMP | N14: =Profile!C43 -> 1439.8
B15: 44926 | C15: =Closing!Q9 -> 731.81952 | D15: =C15/C14-1 -> -0.0085172318 | E15: 0.11465184 | G15: 7 | H15: =NORMINV(RAND(),N$10,N$11) -> -0.053175723
B16: 44957 | C16: =Closing!Q10 -> 759.29254 | D16: =C16/C15-1 -> 0.037540707 | E16: 0.11157167 | G16: 8 | H16: =NORMINV(RAND(),N$10,N$11) -> 0.072727492 | J16: Monte Carlo Simulation
B17: 44985 | C17: =Closing!Q11 -> 733.15607 | D17: =C17/C16-1 -> -0.034422141 | E17: 0.10441806 | G17: 9 | H17: =NORMINV(RAND(),N$10,N$11) -> -0.04779308 | J17: Mean | N17: =AVERAGE(H9:H213) -> 0.031976675
B18: 45016 | C18: =Closing!Q12 -> 723.20642 | D18: =C18/C17-1 -> -0.01357098 | E18: 0.10221196 | G18: 10 | H18: =NORMINV(RAND(),N$10,N$11) -> 0.076266082 | J18: Std Deviation | N18: =STDEV(H9:H213) -> 0.079829111
B19: 45046 | C19: =Closing!Q13 -> 783.44879 | D19: =C19/C18-1 -> 0.083298999 | E19: 0.09225656 | G19: 11 | H19: =NORMINV(RAND(),N$10,N$11) -> -0.06635921 | J19: Min | N19: =MIN(H9:H213) -> -0.14279936
B20: 45077 | C20: =Closing!Q14 -> 979.42242 | D20: =C20/C19-1 -> 0.25014224 | E20: 0.083298999 | G20: 12 | H20: =NORMINV(RAND(),N$10,N$11) -> 0.11563032 | J20: Max | N20: =MAX(H9:H213) -> 0.23239674
B21: 45107 | C21: =Closing!Q15 -> 954.43396 | D21: =C21/C20-1 -> -0.02551347 | E21: 0.081996905 | G21: 13 | H21: =NORMINV(RAND(),N$10,N$11) -> 0.066149042 | J21: CMP | N21: =N14 -> 1439.8
B22: 45138 | C22: =Closing!Q16 -> 1096.3428 | D22: =C22/C21-1 -> 0.14868374 | E22: 0.081166874 | G22: 14 | H22: =NORMINV(RAND(),N$10,N$11) -> 0.15472472
B23: 45169 | C23: =Closing!Q17 -> 1052.1017 | D23: =C23/C22-1 -> -0.040353337 | E23: 0.076691647 | G23: 15 | H23: =NORMINV(RAND(),N$10,N$11) -> 0.034229683 | J23: Percentile | L23: VAR % | M23: Stock Price | N23: VAR (INR)
B24: 45199 | C24: =Closing!Q18 -> 1021.2175 | D24: =C24/C23-1 -> -0.029354725 | E24: 0.070026493 | G24: 16 | H24: =NORMINV(RAND(),N$10,N$11) -> 0.11576871 | J24: 0.05 | L24: =PERCENTILE($H$9:$H$50008,J24) -> -0.10261676 | M24: =L24*(1-$N$21) -> 147.64499 | N24: =$N$21-M24 -> 1292.155
B25: 45230 | C25: =Closing!Q19 -> 1055.7761 | D25: =C25/C24-1 -> 0.03384058 | E25: 0.059843464 | G25: 17 | H25: =NORMINV(RAND(),N$10,N$11) -> -0.0057811614 | J25: 0.01 | L25: =PERCENTILE($H$9:$H$50008,J25) -> -0.14024925 | M25: =L25*(1-$N$21) -> 201.79062 | N25: =$N$21-M25 -> 1238.0094
B26: 45260 | C26: =Closing!Q20 -> 1065.8558 | D26: =C26/C25-1 -> 0.0095472058 | E26: 0.049468866 | G26: 18 | H26: =NORMINV(RAND(),N$10,N$11) -> -0.083587351 | J26: 0.005 | L26: =PERCENTILE($H$9:$H$50008,J26) -> -0.15142393 | M26: =L26*(1-$N$21) -> 217.86875 | N26: =$N$21-M26 -> 1221.9312
B27: 45291 | C27: =Closing!Q21 -> 1184.7751 | D27: =C27/C26-1 -> 0.11157167 | E27: 0.045338747 | G27: 19 | H27: =NORMINV(RAND(),N$10,N$11) -> -0.027215075
B28: 45322 | C28: =Closing!Q22 -> 1209.1549 | D28: =C28/C27-1 -> 0.020577542 | E28: 0.037540707 | G28: 20 | H28: =NORMINV(RAND(),N$10,N$11) -> 0.18465263
B29: 45351 | C29: =Closing!Q23 -> 1347.7867 | D29: =C29/C28-1 -> 0.11465184 | E29: 0.036476346 | G29: 21 | H29: =NORMINV(RAND(),N$10,N$11) -> -0.077555706
B30: 45382 | C30: =Closing!Q24 -> 1288.5505 | D30: =C30/C29-1 -> -0.043950726 | E30: 0.03384058 | G30: 22 | H30: =NORMINV(RAND(),N$10,N$11) -> -0.063189085
B31: 45412 | C31: =Closing!Q25 -> 1365.6619 | D31: =C31/C30-1 -> 0.059843464 | E31: 0.024559747 | G31: 23 | H31: =NORMINV(RAND(),N$10,N$11) -> 0.11118776
B32: 45443 | C32: =Closing!Q26 -> 1291.6786 | D32: =C32/C31-1 -> -0.054173934 | E32: 0.020577542 | G32: 24 | H32: =NORMINV(RAND(),N$10,N$11) -> 0.11713608
B33: 45473 | C33: =Closing!Q27 -> 1237.2091 | D33: =C33/C32-1 -> -0.042169533 | E33: 0.015053919 | G33: 25 | H33: =NORMINV(RAND(),N$10,N$11) -> -0.051286228
B34: 45504 | C34: =Closing!Q28 -> 1179.4225 | D34: =C34/C33-1 -> -0.046707239 | E34: 0.0098819749 | G34: 26 | H34: =NORMINV(RAND(),N$10,N$11) -> 0.0034811798
B35: 45535 | C35: =Closing!Q29 -> 1262.0133 | D35: =C35/C34-1 -> 0.070026493 | E35: 0.0095472058 | G35: 27 | H35: =NORMINV(RAND(),N$10,N$11) -> 0.062572531
B36: 45565 | C36: =Closing!Q30 -> 1393.7903 | D36: =C36/C35-1 -> 0.10441806 | E36: -0.0085172318 | G36: 28 | H36: =NORMINV(RAND(),N$10,N$11) -> -0.029283679
B37: 45596 | C37: =Closing!Q31 -> 1607.2125 | D37: =C37/C36-1 -> 0.15312364 | E37: -0.013217428 | G37: 29 | H37: =NORMINV(RAND(),N$10,N$11) -> 0.021725812
B38: 45626 | C38: =Closing!Q32 -> 1582.5199 | D38: =C38/C37-1 -> -0.015363635 | E38: -0.01357098 | G38: 30 | H38: =NORMINV(RAND(),N$10,N$11) -> -0.092671454
... B59: 46265 | C59: =Closing!Q53 -> 1439.8 | D59: =C59/C58-1 -> -0.056116412 | E59: -0.13780305 | G59: 51 | H59: =NORMINV(RAND(),N$10,N$11) -> -0.027875322
B60: - | C60: - | D60: - | E60: - | F60: - | G60: 52 | H60: =NORMINV(RAND(),N$10,N$11) -> -0.023030346
G61: 53 | H61: =NORMINV(RAND(),N$10,N$11) -> 0.12076544
G62: 54 | H62: =NORMINV(RAND(),N$10,N$11) -> 0.13255204
G63: 55 | H63: =NORMINV(RAND(),N$10,N$11) -> 0.054015149
G64: 56 | H64: =NORMINV(RAND(),N$10,N$11) -> 0.07255848
G65: 57 | H65: =NORMINV(RAND(),N$10,N$11) -> -0.038546162
G66: 58 | H66: =NORMINV(RAND(),N$10,N$11) -> 0.047433275
G67: 59 | H67: =NORMINV(RAND(),N$10,N$11) -> 0.031503104
G68: 60 | H68: =NORMINV(RAND(),N$10,N$11) -> -0.1014828
G69: 61 | H69: =NORMINV(RAND(),N$10,N$11) -> 0.0099664708
G70: 62 | H70: =NORMINV(RAND(),N$10,N$11) -> -0.11517667
G71: 63 | H71: =NORMINV(RAND(),N$10,N$11) -> 0.065010668
G72: 64 | H72: =NORMINV(RAND(),N$10,N$11) -> 0.010399431
... G508: 500 | H508: =NORMINV(RAND(),N$10,N$11) -> 0.093130728
G509: - | H509: - | I509: -
I50009: - | J50009: - | K50009: -

Sheet Conclusion
B4: C | C4: onclusion
B7: RATING | D7: CMP | F7: TARGET | H7: UPSIDE/DOWNSIDE | J7: HORIZON
N8: Why Rainbow Childrens Medicare Ltd.
B12: Investment Rationale
N21: Key Risks
N32: SPECIAL THANKS TO
N33: Dr. Anju Virmani

Sheet Data Sheet
A1: COMPANY NAME | B1: RAINBOW CHILDRENS MEDICARE LTD | E1: =IF(B2<>B3, "A NEW VERSION OF THE WORKSHEET IS AVAILABLE", "")
A2: LATEST VERSION | B2: 2.1 | E2: PLEASE DO NOT MAKE ANY CHANGES TO THIS SHEET
A3: CURRENT VERSION | B3: 2.1
A5: META
A6: Number of shares | B6: =IF(B9>0, B9/B8, 0) -> 10.156663
A7: Face Value | B7: 10
A8: Current Price | B8: 1453.5
A9: Market Capitalization | B9: 14762.71
A15: PROFIT & LOSS
A16: Report Date | B16: 42825 | C16: 43190 | D16: 43555 | E16: 43921 | F16: 44286 | G16: 44651 | H16: 45016 | I16: 45382 | J16: 45747 | K16: 46112
A17: Sales | B17: 321.29 | C17: 401.83 | D17: 542.79 | E17: 719.39 | F17: 650.05 | G17: 973.76 | H17: 1173.57 | I17: 1296.9 | J17: 1515.87 | K17: 1703.08
A18: Raw Material Cost | B18: 51.62 | C18: 59.99 | D18: 80.21 | E18: 105.31 | F18: 103.26 | G18: 194.73 | H18: 158.28 | I18: 165.28 | J18: 194.92 | K18: 227.03
A19: Change in Inventory
A20: Power and Fuel | B20: 8.27 | C20: 9.33 | D20: 12.35 | E20: 14.86 | F20: 13.84 | G20: 16.81 | H20: 21.23 | I20: 26.61 | J20: 27.72 | K20: 28.85
A21: Other Mfr. Exp | B21: 10.95 | C21: 14.71 | D21: 45.83 | E21: 65.58 | F21: 56.7 | G21: 65.6 | H21: 86.85 | I21: 95.72 | J21: 115.32 | K21: 126.46
A22: Employee Cost | B22: 69.22 | C22: 88.24 | D22: 85.8 | E22: 109.01 | F22: 102.14 | G22: 116.37 | H22: 144.56 | I22: 176.71 | J22: 206.82 | K22: 234.11
A23: Selling and admin | B23: 35.55 | C23: 46.36 | D23: 163.36 | E23: 216.75 | F23: 202.75 | G23: 266.44 | H23: 350.18 | I23: 395.45 | J23: 469.57 | K23: 525.36
A24: Other Expenses | B24: 90.71 | C24: 113.79 | D24: 3.79 | E24: 7.2 | F24: 6.22 | G24: 5.88 | H24: 12.9 | I24: 4.76 | J24: 7.28 | K24: 12.83
A25: Other Income | B25: 11.07 | C25: 9.6 | D25: 8.35 | E25: 10.35 | F25: 10.26 | G25: 18.85 | H25: 30.87 | I25: 37.06 | J25: 51.01 | K25: 42.25
A26: Depreciation | B26: 21.89 | C26: 28.08 | D26: 60.32 | E26: 69.41 | F26: 73.34 | G26: 83.26 | H26: 90.27 | I26: 112.08 | J26: 138.44 | K26: 150.57
A27: Interest | B27: 2.9 | C27: 4.27 | D27: 41.96 | E27: 48.26 | F27: 46.37 | G27: 56.17 | H27: 58.39 | I27: 62.53 | J27: 76.81 | K27: 81.89
A28: Profit before tax | B28: 41.25 | C28: 46.66 | D28: 57.52 | E28: 93.36 | F28: 55.69 | G28: 187.35 | H28: 281.78 | I28: 294.82 | J28: 330 | K28: 358.23
A29: Tax | B29: 9.9 | C29: 10.39 | D29: 12.93 | E29: 38.02 | F29: 16.13 | G29: 48.67 | H29: 69.4 | I29: 76.53 | J29: 85.78 | K29: 76.69
A30: Net profit | B30: 31.35 | C30: 36.27 | D30: 44.59 | E30: 55.73 | F30: 40.02 | G30: 138.27 | H30: 210.83 | I30: 217 | J30: 243.42 | K30: 278.32
A31: Dividend Amount | B31: 2.32 | C31: 4.4 | D31: 4.4 | E31: 8.79 | G31: 18.81 | H31: 30.45 | I31: 30.45 | J31: 30.46 | K31: 35.55
A40: Quarters
A41: Report Date | B41: 45382 | C41: 45473 | D41: 45565 | E41: 45657 | F41: 45747 | G41: 45838 | H41: 45930 | I41: 46022 | J41: 46112 | K41: 46203
A42: Sales | B42: 341.1 | C42: 330.22 | D42: 417.46 | E42: 398.08 | F42: 370.11 | G42: 352.93 | H42: 444.8 | I42: 445.45 | J42: 459.9 | K42: 469.99
A43: Expenses | B43: 235.56 | C43: 236.49 | D43: 270.38 | E43: 263.72 | F43: 255.39 | G43: 249.31 | H43: 295.94 | I43: 298.47 | J43: 315.19 | K43: 335.34
A44: Other Income | B44: 12.78 | C44: 11.93 | D44: 11.27 | E44: 13.27 | F44: 14.53 | G44: 20.02 | H44: 8.2 | I44: 10.51 | J44: 3.52 | K44: 12.71
A45: Depreciation | B45: 32.3 | C45: 34.14 | D45: 34.9 | E45: 35.23 | F45: 34.16 | G45: 34.19 | H45: 35.84 | I45: 39.6 | J45: 40.94 | K45: 42.2
A46: Interest | B46: 16.85 | C46: 18.16 | D46: 18.1 | E46: 18.07 | F46: 18.12 | G46: 18.08 | H46: 18.85 | I46: 20.2 | J46: 20.5 | K46: 21.21
A47: Profit before tax | B47: 69.17 | C47: 53.36 | D47: 105.35 | E47: 94.33 | F47: 76.97 | G47: 71.37 | H47: 102.37 | I47: 97.69 | J47: 86.79 | K47: 83.95
A48: Tax | B48: 18.11 | C48: 13.62 | D48: 26.34 | E48: 25.39 | F48: 20.42 | G48: 17.57 | H48: 26.74 | I48: 23.8 | J48: 8.57 | K48: 21.41
A49: Net profit | B49: 50.97 | C49: 39.53 | D49: 78.87 | E49: 68.69 | F49: 56.34 | G49: 53.5 | H49: 75.25 | I49: 72.53 | J49: 77.04 | K49: 60.57
A50: Operating Profit | B50: 105.54 | C50: 93.73 | D50: 147.08 | E50: 134.36 | F50: 114.72 | G50: 103.62 | H50: 148.86 | I50: 146.98 | J50: 144.71 | K50: 134.65
A55: BALANCE SHEET
A56: Report Date | B56: 42825 | C56: 43190 | D56: 43555 | E56: 43921 | F56: 44286 | G56: 44651 | H56: 45016 | I56: 45382 | J56: 45747 | K56: 46112
A57: Equity Share Capital | B57: 9.28 | C57: 43.96 | D57: 43.96 | E57: 43.96 | F57: 43.96 | G57: 94.05 | H57: 101.5 | I57: 101.5 | J57: 101.55 | K57: 101.56
A58: Reserves | B58: 308.45 | C58: 306.96 | D58: 317.25 | E58: 350.5 | F58: 391.46 | G58: 497.81 | H58: 958.41 | I58: 1157.43 | J58: 1366.64 | K58: 1546.51
A59: Borrowings | B59: 26.37 | C59: 24.08 | D59: 476.24 | E59: 501.16 | F59: 529.41 | G59: 591.85 | H59: 570.32 | I59: 765.31 | J59: 763.58 | K59: 890.98
A60: Other Liabilities | B60: 54.64 | C60: 72.6 | D60: 88.94 | E60: 123.26 | F60: 116.44 | G60: 112.03 | H60: 140.49 | I60: 146.16 | J60: 145.22 | K60: 235.79
A61: Total | B61: 398.74 | C61: 447.6 | D61: 926.39 | E61: 1018.88 | F61: 1081.27 | G61: 1295.74 | H61: 1770.72 | I61: 2170.4 | J61: 2376.99 | K61: 2774.84
A62: Net Block | B62: 173.61 | C62: 295.74 | D62: 701.73 | E62: 701.53 | F62: 772.31 | G62: 858.44 | H62: 931.11 | I62: 1252.98 | J62: 1398.14 | K62: 1755.89
A63: Capital Work in Progress | B63: 7.34 | C63: 11.65 | D63: 22.63 | E63: 42.75 | F63: 28.77 | G63: 5.76 | H63: 22.79 | I63: 19.9 | J63: 28.46 | K63: 79.22
A64: Investments | B64: 5.51 | C64: 0.14 | D64: 3.19 | E64: 9.9 | F64: 18.27 | G64: 22.1 | H64: 58.14 | I64: 307.5 | J64: 570.73 | K64: 404.5
A65: Other Assets | B65: 212.28 | C65: 140.07 | D65: 198.84 | E65: 264.7 | F65: 261.92 | G65: 409.44 | H65: 758.68 | I65: 590.02 | J65: 379.66 | K65: 535.23
A66: Total | B66: 398.74 | C66: 447.6 | D66: 926.39 | E66: 1018.88 | F66: 1081.27 | G66: 1295.74 | H66: 1770.72 | I66: 2170.4 | J66: 2376.99 | K66: 2774.84
A67: Receivables | B67: 13.68 | C67: 15.39 | D67: 34.97 | E67: 43.96 | F67: 43.97 | G67: 40.41 | H67: 51.2 | I67: 70.44 | J67: 77.3 | K67: 103.18
... A70: No. of Equity Shares | B70: 9279671 | C70: 43958924 | D70: 43958924 | E70: 43958924 | F70: 43958924 | G70: 94053928 | H70: 101501687 | I70: 101501687 | J70: 101551673 | K70: 101559156
A71: New Bonus Shares
A72: Face value | B72: 10 | C72: 10 | D72: 10 | E72: 10 | F72: 10 | G72: 10 | H72: 10 | I72: 10 | J72: 10 | K72: 10
A80: CASH FLOW:
A81: Report Date | B81: 42825 | C81: 43190 | D81: 43555 | E81: 43921 | F81: 44286 | G81: 44651 | H81: 45016 | I81: 45382 | J81: 45747 | K81: 46112
A82: Cash from Operating Activity | B82: 35.53 | C82: 47.91 | D82: 127.24 | E82: 170.41 | F82: 142.71 | G82: 223.73 | H82: 328.78 | I82: 321.4 | J82: 395.66 | K82: 419.66
A83: Cash from Investing Activity | B83: -33.34 | C83: -42.36 | D83: -116.89 | E83: -117.03 | F83: -82.88 | G83: -175.35 | H83: -465.2 | I83: -226.47 | J83: -267.8 | K83: -258.65
A84: Cash from Financing Activity | B84: -1.11 | C84: -7.48 | D84: -8.69 | E84: -51.81 | F84: -60.87 | G84: -44.06 | H84: 143.41 | I84: -101.78 | J84: -117.72 | K84: -147.37
A85: Net Cash Flow | B85: 1.08 | C85: -1.93 | D85: 1.66 | E85: 1.56 | F85: -1.04 | G85: 4.32 | H85: 6.99 | I85: -6.85 | J85: 10.14 | K85: 13.64
A90: PRICE: | H90: 730.5 | I90: 1297.55 | J90: 1401.7 | K90: 1163.1
A92: DERIVED:
A93: Adjusted Equity Shares in Cr | B93: 0.93 | C93: 4.4 | D93: 4.4 | E93: 4.4 | F93: 4.4 | G93: 9.41 | H93: 10.15 | I93: 10.15 | J93: 10.16 | K93: 10.16

Sheet Quarters
A1: ='Profit & Loss'!A1 -> RAINBOW CHILDRENS MEDICARE LTD | J1: SCREENER.IN
A3: Narration | B3: 45382 | C3: 45473 | D3: 45565 | E3: 45657 | F3: 45747 | G3: 45838 | H3: 45930 | I3: 46022 | J3: 46112 | K3: 46203
A4: Sales | B4: 341.1 | C4: 330.22 | D4: 417.46 | E4: 398.08 | F4: 370.11 | G4: 352.93 | H4: 444.8 | I4: 445.45 | J4: 459.9 | K4: 469.99
A5: Expenses | B5: 235.56 | C5: 236.49 | D5: 270.38 | E5: 263.72 | F5: 255.39 | G5: 249.31 | H5: 295.94 | I5: 298.47 | J5: 315.19 | K5: 335.34
A6: Operating Profit | B6: 105.54 | C6: 93.73 | D6: 147.08 | E6: 134.36 | F6: 114.72 | G6: 103.62 | H6: 148.86 | I6: 146.98 | J6: 144.71 | K6: 134.65
A7: Other Income | B7: 12.78 | C7: 11.93 | D7: 11.27 | E7: 13.27 | F7: 14.53 | G7: 20.02 | H7: 8.2 | I7: 10.51 | J7: 3.52 | K7: 12.71
A8: Depreciation | B8: 32.3 | C8: 34.14 | D8: 34.9 | E8: 35.23 | F8: 34.16 | G8: 34.19 | H8: 35.84 | I8: 39.6 | J8: 40.94 | K8: 42.2
A9: Interest | B9: 16.85 | C9: 18.16 | D9: 18.1 | E9: 18.07 | F9: 18.12 | G9: 18.08 | H9: 18.85 | I9: 20.2 | J9: 20.5 | K9: 21.21
A10: Profit before tax | B10: 69.17 | C10: 53.36 | D10: 105.35 | E10: 94.33 | F10: 76.97 | G10: 71.37 | H10: 102.37 | I10: 97.69 | J10: 86.79 | K10: 83.95
A11: Tax | B11: 18.11 | C11: 13.62 | D11: 26.34 | E11: 25.39 | F11: 20.42 | G11: 17.57 | H11: 26.74 | I11: 23.8 | J11: 8.57 | K11: 21.41
A12: Net profit | B12: 50.97 | C12: 39.53 | D12: 78.87 | E12: 68.69 | F12: 56.34 | G12: 53.5 | H12: 75.25 | I12: 72.53 | J12: 77.04 | K12: 60.57
A14: OPM | B14: =IF(B4>0,B6/B4,"") -> 0.30941073 | C14: =IF(C4>0,C6/C4,"") -> 0.28384108 | D14: =IF(D4>0,D6/D4,"") -> 0.35232118 | E14: =IF(E4>0,E6/E4,"") -> 0.3375201 | F14: =IF(F4>0,F6/F4,"") -> 0.3099619 | G14: =IF(G4>0,G6/G4,"") -> 0.2935993 | H14: =IF(H4>0,H6/H4,"") -> 0.33466727 | I14: =IF(I4>0,I6/I4,"") -> 0.32995847 | ... K14: =IF(K4>0,K6/K4,"") -> 0.28649546

Sheet Profit & Loss
A1: RAINBOW CHILDRENS MEDICARE LTD | M1: SCREENER.IN
A3: Narration | B3: 42825 | C3: 43190 | D3: 43555 | E3: 43921 | F3: 44286 | G3: 44651 | H3: 45016 | I3: 45382 | J3: 45747 | K3: 46112 | L3: Trailing | M3: Best Case | N3: Worst Case
A4: Sales | B4: 321.29 | C4: 401.83 | D4: 542.79 | E4: 719.39 | F4: 650.05 | G4: 973.76 | H4: 1173.57 | I4: 1296.9 | J4: 1515.87 | K4: 1703.08 | L4: =SUM(Quarters!H4:K4) -> 1820.14 | M4: =$K4+M23*K4 -> 1928.1629 | N4: =$K4+N23*L4 -> 1927.8674
A5: Expenses | B5: 266.32 | C5: 332.42 | D5: 391.34 | E5: 518.71 | F5: 484.91 | G5: 665.83 | H5: 774 | I5: 864.53 | J5: 1021.63 | K5: 1154.64 | L5: =SUM(Quarters!H5:K5) -> 1244.94 | M5: =M4-M6 -> 1298.3509 | N5: =N4-N6 -> 1342.325
A6: Operating Profit | B6: =B4-B5 -> 54.97 | C6: =C4-C5 -> 69.41 | D6: =D4-D5 -> 151.45 | E6: =E4-E5 -> 200.68 | F6: =F4-F5 -> 165.14 | G6: =G4-G5 -> 307.93 | H6: =H4-H5 -> 399.57 | I6: =I4-I5 -> 432.37 | ... K6: =K4-K5 -> 548.44 | L6: =SUM(Quarters!H6:K6) -> 575.2 | M6: =M4*M24 -> 629.81205 | N6: =N4*N24 -> 585.54234
A7: Other Income | B7: 11.07 | C7: 9.6 | D7: 8.35 | E7: 10.35 | F7: 10.26 | G7: 18.85 | H7: 30.87 | I7: 37.06 | J7: 51.01 | K7: 42.25 | L7: =SUM(Quarters!H7:K7) -> 34.94 | M7: 0 | N7: 0
A8: Depreciation | B8: 21.89 | C8: 28.08 | D8: 60.32 | E8: 69.41 | F8: 73.34 | G8: 83.26 | H8: 90.27 | I8: 112.08 | J8: 138.44 | K8: 150.57 | L8: =SUM(Quarters!H8:K8) -> 158.58 | M8: =+$L8 -> 158.58 | N8: =+$L8 -> 158.58
A9: Interest | B9: 2.9 | C9: 4.27 | D9: 41.96 | E9: 48.26 | F9: 46.37 | G9: 56.17 | H9: 58.39 | I9: 62.53 | J9: 76.81 | K9: 81.89 | L9: =SUM(Quarters!H9:K9) -> 80.76 | M9: =+$L9 -> 80.76 | N9: =+$L9 -> 80.76
A10: Profit before tax | B10: 41.25 | C10: 46.66 | D10: 57.52 | E10: 93.36 | F10: 55.69 | G10: 187.35 | H10: 281.78 | I10: 294.82 | J10: 330 | K10: 358.23 | L10: =SUM(Quarters!H10:K10) -> 370.8 | M10: =M6+M7-SUM(M8:M9) -> 390.47205 | N10: =N6+N7-SUM(N8:N9) -> 346.20234
A11: Tax | B11: 9.9 | C11: 10.39 | D11: 12.93 | E11: 38.02 | F11: 16.13 | G11: 48.67 | H11: 69.4 | I11: 76.53 | J11: 85.78 | K11: 76.69 | L11: =SUM(Quarters!H11:K11) -> 80.52 | M11: =IF($L10>0,$L11/$L10,0) -> 0.2171521 | N11: =IF($L10>0,$L11/$L10,0) -> 0.2171521
A12: Net profit | B12: 31.35 | C12: 36.27 | D12: 44.59 | E12: 55.73 | F12: 40.02 | G12: 138.27 | H12: 210.83 | I12: 217 | J12: 243.42 | K12: 278.32 | L12: =SUM(Quarters!H12:K12) -> 285.39 | M12: =M10-M11*M10 -> 305.68022 | N12: =N10-N11*N10 -> 271.02377
A13: EPS | B13: 33.709677 | C13: 8.2431818 | D13: 10.134091 | E13: 12.665909 | F13: 9.0954545 | G13: 14.693943 | H13: 20.771429 | I13: 21.37931 | J13: 23.958661 | K13: 27.393701 | L13: 28.098795 | M13: 30.096521 | N13: 26.684332
A14: Price to earning | B14: =IF(B15>0,B15/B13,"") | C14: =IF(C15>0,C15/C13,"") | D14: =IF(D15>0,D15/D13,"") | E14: =IF(E15>0,E15/E13,"") | F14: =IF(F15>0,F15/F13,"") | G14: =IF(G15>0,G15/G13,"") | H14: =IF(H15>0,H15/H13,"") -> 35.168501 | I14: =IF(I15>0,I15/I13,"") -> 60.691855 | ... K14: =IF(K15>0,K15/K13,"") -> 42.458666 | L14: =IF(L13>0,L15/L13,0) -> 51.728197 | M14: =M25 -> 53.345914 | N14: =N25 -> 49.710431
A15: Price | B15: 0 | C15: 0 | D15: 0 | E15: 0 | F15: 0 | G15: 0 | H15: 730.5 | I15: 1297.55 | J15: 1401.7 | K15: 1163.1 | L15: 1453.5 | M15: =M13*M14 -> 1605.5264 | N15: =N13*N14 -> 1326.4896
A17: RATIOS:
A18: Dividend Payout | B18: 0.07400319 | C18: 0.12131238 | D18: 0.098676833 | E18: 0.15772474 | F18: 0 | G18: 0.13603819 | H18: 0.14442916 | I18: 0.14032258 | J18: 0.12513351 | K18: 0.12773067
A19: OPM | B19: =IF(B6>0,B6/B4,0) -> 0.17109154 | C19: =IF(C6>0,C6/C4,0) -> 0.17273474 | D19: =IF(D6>0,D6/D4,0) -> 0.27902135 | E19: =IF(E6>0,E6/E4,0) -> 0.27895856 | F19: =IF(F6>0,F6/F4,0) -> 0.254042 | G19: =IF(G6>0,G6/G4,0) -> 0.31622782 | H19: =IF(H6>0,H6/H4,0) -> 0.34047394 | I19: =IF(I6>0,I6/I4,0) -> 0.33338731 | ... L19: =IF(L6>0,L6/L4,0) -> 0.31601965
G22: TRENDS: | H22: 10 YEARS | I22: 7 YEARS | J22: 5 YEARS | K22: 3 YEARS | L22: RECENT | M22: BEST | N22: WORST
G23: Sales Growth | H23: =IF(B4=0,"",POWER($K4/B4,1/9)-1) -> 0.20359945 | I23: =IF(D4=0,"",POWER($K4/D4,1/7)-1) -> 0.17745228 | J23: =IF(F4=0,"",POWER($K4/F4,1/5)-1) -> 0.21243275 | K23: =IF(H4=0,"",POWER($K4/H4, 1/3)-1) -> 0.13216228 | L23: =IF(ISERROR(MAX(IF(J4=0,"",(K4-J4)/J4),IF(K4=0,"",(L4-K4)/K4))),"",MAX(IF(J4=0,"",(K4-J4)/J4),IF(K4=0,"",(L4-K4)/K4))) -> 0.12350004 | M23: =MAX(K23:L23) -> 0.13216228 | N23: =MIN(H23:L23) -> 0.12350004
G24: OPM | H24: =IF(SUM(B4:$K$4)=0,"",SUMPRODUCT(B19:$K$19,B4:$K$4)/SUM(B4:$K$4)) -> 0.30372543 | I24: =IF(SUM(E4:$K$4)=0,"",SUMPRODUCT(E19:$K$19,E4:$K$4)/SUM(E4:$K$4)) -> 0.31725265 | J24: =IF(SUM(G4:$K$4)=0,"",SUMPRODUCT(G19:$K$19,G4:$K$4)/SUM(G4:$K$4)) -> 0.32755381 | K24: =IF(SUM(I4:$K$4)=0, "", SUMPRODUCT(I19:$K$19,I4:$K$4)/SUM(I4:$K$4)) -> 0.3266384 | L24: =L19 -> 0.31601965 | M24: =MAX(K24:L24) -> 0.3266384 | N24: =MIN(H24:L24) -> 0.30372543
G25: Price to Earning | H25: =IF(ISERROR(AVERAGEIF(B14:$L14,">0")),"",AVERAGEIF(B14:$L14,">0")) -> 49.710431 | I25: =IF(ISERROR(AVERAGEIF(E14:$L14,">0")),"",AVERAGEIF(E14:$L14,">0")) -> 49.710431 | J25: =IF(ISERROR(AVERAGEIF(G14:$L14,">0")),"",AVERAGEIF(G14:$L14,">0")) -> 49.710431 | K25: =IF(ISERROR(AVERAGEIF(I14:$L14,">0")),"",AVERAGEIF(I14:$L14,">0")) -> 53.345914 | L25: =L14 -> 51.728197 | M25: =MAX(K25:L25) -> 53.345914 | N25: =MIN(H25:L25) -> 49.710431

Sheet Balance Sheet
A1: ='Profit & Loss'!A1 -> RAINBOW CHILDRENS MEDICARE LTD | J1: SCREENER.IN
A3: Narration | B3: 42825 | C3: 43190 | D3: 43555 | E3: 43921 | F3: 44286 | G3: 44651 | H3: 45016 | I3: 45382 | J3: 45747 | K3: 46112 | N3: 42064 | O3: 42430 | P3: 42795 | Q3: 43160 | R3: 43525 | S3: 43891 | T3: 44256 | U3: 44621 | V3: 44986 | W3: 45352 | X3: 45717 | Y3: 46082
A4: Equity Share Capital | B4: 9.28 | C4: 43.96 | D4: 43.96 | E4: 43.96 | F4: 43.96 | G4: 94.05 | H4: 101.5 | I4: 101.5 | J4: 101.55 | K4: 101.56 | M4: Equity Capital | N4: 9 | O4: 9 | P4: 9 | Q4: 44 | R4: 44 | S4: 44 | T4: 44 | U4: 94 | V4: 102 | W4: 102 | X4: 102 | Y4: 102
A5: Reserves | B5: 308.45 | C5: 306.96 | D5: 317.25 | E5: 350.5 | F5: 391.46 | G5: 497.81 | H5: 958.41 | I5: 1157.43 | J5: 1366.64 | K5: 1546.51 | M5: Reserves | N5: 166 | O5: 275 | P5: 308 | Q5: 307 | R5: 317 | S5: 350 | T5: 391 | U5: 498 | V5: 958 | W5: 1157 | X5: 1367 | Y5: 1547
A6: Borrowings | B6: 26.37 | C6: 24.08 | D6: 476.24 | E6: 501.16 | F6: 529.41 | G6: 591.85 | H6: 570.32 | I6: 765.31 | J6: 763.58 | K6: 890.98 | M6: Borrowings - | N6: 22 | O6: 24 | P6: 26 | Q6: 24 | R6: 476 | S6: 501 | T6: 529 | U6: 592 | V6: 570 | W6: 765 | X6: 764 | Y6: 891
A7: Other Liabilities | B7: 54.64 | C7: 72.6 | D7: 88.94 | E7: 123.26 | F7: 116.44 | G7: 112.03 | H7: 140.49 | I7: 146.16 | J7: 145.22 | K7: 235.79 | M7: Long term Borrowings | N7: 10 | O7: 8 | P7: 10 | Q7: 10 | R7: 50 | S7: 46 | T7: 41 | U7: 27 | V7: 0 | W7: 0 | X7: 0 | Y7: 0
A8: Total | B8: 398.74 | C8: 447.6 | D8: 926.39 | E8: 1018.88 | F8: 1081.27 | G8: 1295.74 | H8: 1770.72 | I8: 2170.4 | J8: 2376.99 | K8: 2774.84 | M8: Short term Borrowings | N8: 4 | O8: 2 | P8: 5 | Q8: 2 | R8: 3 | S8: 12 | T8: 7 | U8: 14 | V8: 0 | W8: 0 | X8: 0 | Y8: 0
M9: Lease Liabilities | N9: 0 | O9: 0 | P9: 0 | Q9: 0 | R9: 413 | S9: 433 | T9: 470 | U9: 539 | V9: 570 | W9: 765 | X9: 764 | Y9: 891
A10: Net Block | B10: 173.61 | C10: 295.74 | D10: 701.73 | E10: 701.53 | F10: 772.31 | G10: 858.44 | H10: 931.11 | I10: 1252.98 | J10: 1398.14 | K10: 1755.89 | M10: Preference Capital | N10: 6 | O10: 11 | P10: 11 | Q10: 11 | R10: 11 | S10: 11 | T10: 11 | U10: 11 | V10: 0 | W10: 0 | X10: 0 | Y10: 0
A11: Capital Work in Progress | B11: 7.34 | C11: 11.65 | D11: 22.63 | E11: 42.75 | F11: 28.77 | G11: 5.76 | H11: 22.79 | I11: 19.9 | J11: 28.46 | K11: 79.22 | M11: Other Borrowings | N11: 3 | O11: 3 | P11: 1 | Q11: 1 | R11: 0 | S11: 0 | T11: 0 | U11: 0 | V11: 0 | W11: 0 | X11: 0 | Y11: 0
A12: Investments | B12: 5.51 | C12: 0.14 | D12: 3.19 | E12: 9.9 | F12: 18.27 | G12: 22.1 | H12: 58.14 | I12: 307.5 | J12: 570.73 | K12: 404.5 | M12: Other Liabilities - | N12: 34 | O12: 41 | P12: 55 | Q12: 73 | R12: 89 | S12: 123 | T12: 116 | U12: 112 | V12: 140 | W12: 146 | X12: 145 | Y12: 236
A13: Other Assets | B13: 212.28 | C13: 140.07 | D13: 198.84 | E13: 264.7 | F13: 261.92 | G13: 409.44 | H13: 758.68 | I13: 590.02 | J13: 379.66 | K13: 535.23 | M13: Non controlling int | N13: 0 | O13: 0 | P13: 0 | Q13: 0 | R13: 0 | S13: 4 | T13: 2 | U13: 3 | V13: 5 | W13: 6 | X13: 7 | Y13: 16
A14: Total | B14: 398.74 | C14: 447.6 | D14: 926.39 | E14: 1018.88 | F14: 1081.27 | G14: 1295.74 | H14: 1770.72 | I14: 2170.4 | J14: 2376.99 | K14: 2774.84 | M14: Trade Payables | N14: 10 | O14: 12 | P14: 20 | Q14: 25 | R14: 43 | S14: 58 | T14: 54 | U14: 64 | V14: 79 | W14: 82 | X14: 91 | Y14: 101
M15: Advance from Customers | N15: 1 | O15: 2 | P15: 4 | Q15: 3 | R15: 0 | S15: 0 | T15: 0 | U15: 0 | V15: 0 | W15: 0 | X15: 0 | Y15: 0
A16: Working Capital | B16: =B13-B7 -> 157.64 | C16: =C13-C7 -> 67.47 | D16: =D13-D7 -> 109.9 | E16: =E13-E7 -> 141.44 | F16: =F13-F7 -> 145.48 | G16: =G13-G7 -> 297.41 | H16: =H13-H7 -> 618.19 | I16: =I13-I7 -> 443.86 | ... K16: =K13-K7 -> 299.44 | M16: Other liability items | N16: 23 | O16: 28 | P16: 31 | Q16: 45 | R16: 46 | S16: 61 | T16: 61 | U16: 44 | V16: 57 | W16: 59 | X16: 47 | Y16: 120
A17: Debtors | B17: 13.68 | C17: 15.39 | D17: 34.97 | E17: 43.96 | F17: 43.97 | G17: 40.41 | H17: 51.2 | I17: 70.44 | J17: 77.3 | K17: 103.18 | M17: Total Liabilities | N17: 231 | O17: 349 | P17: 399 | Q17: 448 | R17: 926 | S17: 1019 | T17: 1081 | U17: 1296 | V17: 1771 | W17: 2170 | X17: 2377 | Y17: 2775
A18: Inventory | B18: 6.74 | C18: 5.98 | D18: 7 | E18: 15.98 | F18: 10.1 | G18: 14.82 | H18: 18.76 | I18: 23.98 | J18: 27.57 | K18: 41.63 | M18: Fixed Assets - | N18: 78 | O18: 123 | P18: 174 | Q18: 296 | R18: 702 | S18: 702 | T18: 772 | U18: 858 | V18: 931 | W18: 1253 | X18: 1398 | Y18: 1756
M19: Land | N19: 10 | O19: 3 | P19: 3 | Q19: 3 | R19: 3 | S19: 3 | T19: 3 | U19: 3 | V19: 3 | W19: 4 | X19: 180 | Y19: 180
A20: Debtor Days | B20: =IF('Profit & Loss'!B4>0,'Balance Sheet'!B17/('Profit & Loss'!B4/365),0) -> 15.5411 | C20: =IF('Profit & Loss'!C4>0,'Balance Sheet'!C17/('Profit & Loss'!C4/365),0) -> 13.979419 | D20: =IF('Profit & Loss'!D4>0,'Balance Sheet'!D17/('Profit & Loss'!D4/365),0) -> 23.515632 | E20: =IF('Profit & Loss'!E4>0,'Balance Sheet'!E17/('Profit & Loss'!E4/365),0) -> 22.304174 | F20: =IF('Profit & Loss'!F4>0,'Balance Sheet'!F17/('Profit & Loss'!F4/365),0) -> 24.688947 | G20: =IF('Profit & Loss'!G4>0,'Balance Sheet'!G17/('Profit & Loss'!G4/365),0) -> 15.14711 | H20: =IF('Profit & Loss'!H4>0,'Balance Sheet'!H17/('Profit & Loss'!H4/365),0) -> 15.924061 | I20: =IF('Profit & Loss'!I4>0,'Balance Sheet'!I17/('Profit & Loss'!I4/365),0) -> 19.824659 | ... K20: =IF('Profit & Loss'!K4>0,'Balance Sheet'!K17/('Profit & Loss'!K4/365),0) -> 22.113289 | M20: Building | N20: 37 | O20: 66 | P20: 90 | Q20: 172 | R20: 592 | S20: 600 | T20: 699 | U20: 823 | V20: 921 | W20: 1238 | X20: 1283 | Y20: 1493
A21: Inventory Turnover | B21: =IF('Balance Sheet'!B18>0,'Profit & Loss'!B4/'Balance Sheet'!B18,0) -> 47.669139 | C21: =IF('Balance Sheet'!C18>0,'Profit & Loss'!C4/'Balance Sheet'!C18,0) -> 67.195652 | D21: =IF('Balance Sheet'!D18>0,'Profit & Loss'!D4/'Balance Sheet'!D18,0) -> 77.541429 | E21: =IF('Balance Sheet'!E18>0,'Profit & Loss'!E4/'Balance Sheet'!E18,0) -> 45.018148 | F21: =IF('Balance Sheet'!F18>0,'Profit & Loss'!F4/'Balance Sheet'!F18,0) -> 64.361386 | G21: =IF('Balance Sheet'!G18>0,'Profit & Loss'!G4/'Balance Sheet'!G18,0) -> 65.705803 | H21: =IF('Balance Sheet'!H18>0,'Profit & Loss'!H4/'Balance Sheet'!H18,0) -> 62.557036 | I21: =IF('Balance Sheet'!I18>0,'Profit & Loss'!I4/'Balance Sheet'!I18,0) -> 54.082569 | ... K21: =IF('Balance Sheet'!K18>0,'Profit & Loss'!K4/'Balance Sheet'!K18,0) -> 40.909921 | M21: Plant Machinery | N21: 46 | O21: 69 | P21: 24 | Q21: 40 | R21: 52 | S21: 55 | T21: 67 | U21: 76 | V21: 92 | W21: 123 | X21: 135 | Y21: 157
M22: Equipments | N22: 3 | O22: 5 | P22: 6 | Q22: 10 | R22: 105 | S22: 130 | T22: 155 | U22: 173 | V22: 208 | W22: 268 | X22: 298 | Y22: 363
A23: Return on Equity | B23: =IF(SUM('Balance Sheet'!B4:B5)>0,'Profit & Loss'!B12/SUM('Balance Sheet'!B4:B5),"") -> 0.098668681 | C23: =IF(SUM('Balance Sheet'!C4:C5)>0,'Profit & Loss'!C12/SUM('Balance Sheet'!C4:C5),"") -> 0.10335689 | D23: =IF(SUM('Balance Sheet'!D4:D5)>0,'Profit & Loss'!D12/SUM('Balance Sheet'!D4:D5),"") -> 0.12344619 | E23: =IF(SUM('Balance Sheet'!E4:E5)>0,'Profit & Loss'!E12/SUM('Balance Sheet'!E4:E5),"") -> 0.14128175 | F23: =IF(SUM('Balance Sheet'!F4:F5)>0,'Profit & Loss'!F12/SUM('Balance Sheet'!F4:F5),"") -> 0.091911258 | G23: =IF(SUM('Balance Sheet'!G4:G5)>0,'Profit & Loss'!G12/SUM('Balance Sheet'!G4:G5),"") -> 0.23361944 | H23: =IF(SUM('Balance Sheet'!H4:H5)>0,'Profit & Loss'!H12/SUM('Balance Sheet'!H4:H5),"") -> 0.19891312 | I23: =IF(SUM('Balance Sheet'!I4:I5)>0,'Profit & Loss'!I12/SUM('Balance Sheet'!I4:I5),"") -> 0.1723686 | ... K23: =IF(SUM('Balance Sheet'!K4:K5)>0,'Profit & Loss'!K12/SUM('Balance Sheet'!K4:K5),"") -> 0.16887632 | M23: Computers | N23: 4 | O23: 4 | P23: 3 | Q23: 5 | R23: 6 | S23: 7 | T23: 9 | U23: 11 | V23: 15 | W23: 23 | X23: 27 | Y23: 31
A24: Return on Capital Emp | C24: =IF((B4+B5+B6+C4+C5+C6)>0,('Profit & Loss'!C10+'Profit & Loss'!C9)*2/(B4+B5+B6+C4+C5+C6),"") -> 0.14164928 | D24: =IF((C4+C5+C6+D4+D5+D6)>0,('Profit & Loss'!D10+'Profit & Loss'!D9)*2/(C4+C5+C6+D4+D5+D6),"") -> 0.16409749 | E24: =IF((D4+D5+D6+E4+E5+E6)>0,('Profit & Loss'!E10+'Profit & Loss'!E9)*2/(D4+D5+D6+E4+E5+E6),"") -> 0.16343252 | F24: =IF((E4+E5+E6+F4+F5+F6)>0,('Profit & Loss'!F10+'Profit & Loss'!F9)*2/(E4+E5+E6+F4+F5+F6),"") -> 0.10971539 | G24: =IF((F4+F5+F6+G4+G5+G6)>0,('Profit & Loss'!G10+'Profit & Loss'!G9)*2/(F4+F5+F6+G4+G5+G6),"") -> 0.22668417 | H24: =IF((G4+G5+G6+H4+H5+H6)>0,('Profit & Loss'!H10+'Profit & Loss'!H9)*2/(G4+G5+G6+H4+H5+H6),"") -> 0.24177488 | I24: =IF((H4+H5+H6+I4+I5+I6)>0,('Profit & Loss'!I10+'Profit & Loss'!I9)*2/(H4+H5+H6+I4+I5+I6),"") -> 0.19556871 | J24: =IF((I4+I5+I6+J4+J5+J6)>0,('Profit & Loss'!J10+'Profit & Loss'!J9)*2/(I4+I5+I6+J4+J5+J6),"") -> 0.19116966 | K24: =IF((J4+J5+J6+K4+K5+K6)>0,('Profit & Loss'!K10+'Profit & Loss'!K9)*2/(J4+J5+J6+K4+K5+K6),"") -> 0.18450497 | M24: Furniture n fittings | N24: 12 | O24: 17 | P24: 15 | Q24: 27 | R24: 33 | S24: 35 | T24: 40 | U24: 44 | V24: 52 | W24: 67 | X24: 73 | Y24: 84
M25: Vehicles | N25: 3 | O25: 6 | P25: 4 | Q25: 4 | R25: 6 | S25: 10 | T25: 11 | U25: 15 | V25: 19 | W25: 21 | X25: 21 | Y25: 24
M26: Intangible Assets | N26: 0 | O26: 0 | P26: 0 | Q26: 0 | R26: 3 | S26: 3 | T26: 3 | U26: 3 | V26: 0 | W26: 0 | X26: 0 | Y26: 170
M27: Other fixed assets | N27: 1 | O27: 8 | P27: 49 | Q27: 81 | R27: 9 | S27: 9 | T27: 10 | U27: 10 | V27: 13 | W27: 15 | X27: 24 | Y27: 43
M28: Gross Block | N28: 116 | O28: 176 | P28: 195 | Q28: 343 | R28: 810 | S28: 854 | T28: 997 | U28: 1159 | V28: 1323 | W28: 1759 | X28: 2042 | Y28: 2546
M29: Accumulated Depreciation | N29: 38 | O29: 53 | P29: 22 | Q29: 48 | R29: 108 | S29: 152 | T29: 224 | U29: 300 | V29: 392 | W29: 506 | X29: 644 | Y29: 790
M30: CWIP | N30: 35 | O30: 31 | P30: 7 | Q30: 12 | R30: 23 | S30: 43 | T30: 29 | U30: 6 | V30: 23 | W30: 20 | X30: 28 | Y30: 79
M31: Investments | N31: 7 | O31: 2 | P31: 6 | Q31: 0 | R31: 3 | S31: 10 | T31: 18 | U31: 22 | V31: 58 | W31: 308 | X31: 571 | Y31: 404
M32: Other Assets - | N32: 111 | O32: 194 | P32: 212 | Q32: 140 | R32: 199 | S32: 265 | T32: 262 | U32: 409 | V32: 759 | W32: 590 | X32: 380 | Y32: 535
M33: Inventories | N33: 3 | O33: 4 | P33: 7 | Q33: 6 | R33: 7 | S33: 16 | T33: 10 | U33: 15 | V33: 19 | W33: 24 | X33: 28 | Y33: 42
M34: Trade receivables + | N34: 5 | O34: 6 | P34: 14 | Q34: 15 | R34: 35 | S34: 44 | T34: 44 | U34: 40 | V34: 51 | W34: 70 | X34: 77 | Y34: 103
M35: Cash Equivalents | N35: 71 | O35: 150 | P35: 88 | Q35: 36 | R35: 77 | S35: 97 | T35: 95 | U35: 185 | V35: 47 | W35: 10 | X35: 20 | Y35: 34
M36: Loans n Advances | N36: 1 | O36: 1 | P36: 0 | Q36: 5 | R36: 4 | S36: 11 | T36: 38 | U36: 10 | V36: 15 | W36: 14 | X36: 21 | Y36: 29
... M38: Total Assets | N38: 231 | O38: 349 | P38: 399 | Q38: 448 | R38: 926 | S38: 1019 | T38: 1081 | U38: 1296 | V38: 1771 | W38: 2170 | X38: 2377 | Y38: 2775

Sheet Cash Flow
A1: ='Balance Sheet'!A1 -> RAINBOW CHILDRENS MEDICARE LTD | J1: SCREENER.IN
AA2: business description
A3: Narration | B3: 42825 | C3: 43190 | D3: 43555 | E3: 43921 | F3: 44286 | G3: 44651 | H3: 45016 | I3: 45382 | J3: 45747 | K3: 46112 | N3: 42064 | O3: 42430 | P3: 42795 | Q3: 43160 | R3: 43525 | S3: 43891 | T3: 44256 | U3: 44621 | V3: 44986 | W3: 45352 | X3: 45717 | Y3: 46082 | AA3: Rainbow Children’s Medicare Ltd is India’s leading pure-play multi-specialty pediatric and perinatal hospital chain (founded 1999 by Dr. Ramesh Kancharla). It operates under three brands: Rainbow Children’s Hospital (pediatrics, NICU, PICU, quaternary care), BirthRight by Rainbow (maternity & fetal medicine) and Rainbow Fertility (IVF/ART). The company follows a full-time consultant-led, protocol-driven “One Rainbow” clinical model with a hub-and-spoke network. As of Mar 2026 it has 23+ hospitals + clinics across 6 states with ~2,375 capacity beds (~1/3 critical care).
A4: Cash from Operating Activity | B4: 35.53 | C4: 47.91 | D4: 127.24 | E4: 170.41 | F4: 142.71 | G4: 223.73 | H4: 328.78 | I4: 321.4 | J4: 395.66 | K4: 419.66 | M4: Cash from Operating Activity - | N4: 26 | O4: 17 | P4: 36 | Q4: 48 | R4: 127 | S4: 170 | T4: 143 | U4: 224 | V4: 329 | W4: 321 | X4: 396 | Y4: 420
A5: Cash from Investing Activity | B5: -33.34 | C5: -42.36 | D5: -116.89 | E5: -117.03 | F5: -82.88 | G5: -175.35 | H5: -465.2 | I5: -226.47 | J5: -267.8 | K5: -258.65 | M5: Profit from operations | N5: 50 | O5: 35 | P5: 53 | Q5: 68 | R5: 151 | S5: 203 | T5: 166 | U5: 308 | V5: 406 | W5: 435 | X5: 490 | Y5: 551 | AA5: revenue model
A6: Cash from Financing Activity | B6: -1.11 | C6: -7.48 | D6: -8.69 | E6: -51.81 | F6: -60.87 | G6: -44.06 | H6: 143.41 | I6: -101.78 | J6: -117.72 | K6: -147.37 | M6: Receivables | N6: -2 | O6: -2 | P6: -7 | Q6: -3 | R6: -18 | S6: -15 | T6: -3 | U6: 1 | V6: -16 | W6: -16 | X6: -8 | Y6: -31 | AA6: Primarily fee-for-service hospital revenues (IP + OP + diagnostics + pharmacy). High-acuity mix (NICU/PICU/transplants/complex surgeries) drives superior ARPOB. Maternity (~30%) and IVF add volume. Strong cash conversion; minimal government business.
A7: Net Cash Flow | B7: 1.08 | C7: -1.93 | D7: 1.66 | E7: 1.56 | F7: -1.04 | G7: 4.32 | H7: 6.99 | I7: -6.85 | J7: 10.14 | K7: 13.64 | M7: Inventory | N7: -2 | O7: -1 | P7: -3 | Q7: 1 | R7: -1 | S7: -9 | T7: 6 | U7: -5 | V7: -4 | W7: -5 | X7: -4 | Y7: -14
M8: Payables | N8: 0 | O8: 0 | P8: 8 | Q8: 5 | R8: 16 | S8: 15 | T8: -5 | U8: 15 | V8: 14 | W8: 3 | X8: 10 | Y8: 17 | AA8: industry overview
M9: Other WC items | N9: 2 | O9: 0 | P9: -8 | Q9: -9 | R9: -7 | S9: -4 | T9: 5 | U9: -33 | V9: 9 | W9: -6 | X9: -7 | Y9: -1 | AA9: Indian pediatric healthcare market expected to grow at 12–14% CAGR to ₹3,200–3,500 Bn by FY30. NICU segment 11.5–13.5% CAGR. Maternity market ~₹540 Bn growing at 9–10%. Drivers: rising incomes, insurance penetration, high-risk pregnancies, congenital disorders, medical tourism. India still severely under-penetrated in specialized pediatric beds.
M10: Working capital changes | N10: -1 | O10: -2 | P10: -10 | Q10: -7 | R10: -10 | S10: -12 | T10: 3 | U10: -22 | V10: 4 | W10: -25 | X10: -9 | Y10: -30
M11: Interest paid | N11: -8 | O11: -7 | P11: 0 | Q11: 0 | R11: 0 | S11: 0 | T11: 0 | U11: 0 | V11: 0 | W11: 0 | X11: 0 | Y11: 0 | AA11: positioning
M12: Direct taxes | N12: -14 | O12: -9 | P12: -8 | Q12: -13 | R12: -15 | S12: -20 | T12: -26 | U12: -63 | V12: -81 | W12: -89 | X12: -86 | Y12: -102 | AA12: Only listed pure-play children’s hospital group in Asia-Pacific. Differentiated by clinical outcomes (e.g. 94% liver transplant success, high survival of <1 kg babies), full-time doctors, standardized protocols, child-centric infrastructure and integrated mother-to-child care under one roof. Commands premium ARPOB vs multi-specialty peers.
M13: Other operating items | N13: -1 | O13: 0 | P13: 0 | Q13: 0 | R13: 0 | S13: 0 | T13: 0 | U13: 0 | V13: 0 | W13: 0 | X13: 0 | Y13: 0
M14: Cash from Investing Activity - | N14: -20 | O14: -107 | P14: -33 | Q14: -42 | R14: -117 | S14: -117 | T14: -83 | U14: -175 | V14: -465 | W14: -226 | X14: -268 | Y14: -259 | AA14: ARPOB
M15: Fixed assets purchased | N15: -61 | O15: -64 | P15: -56 | Q15: -151 | R15: -87 | S15: -75 | T15: -76 | U15: -62 | V15: -141 | W15: -354 | X15: -146 | Y15: -216
M16: Fixed assets sold | N16: 0 | O16: 0 | P16: 0 | Q16: 0 | R16: 2 | S16: 0 | T16: 0 | U16: 0 | V16: 0 | W16: 0 | X16: 0 | Y16: 1 | AA16: Year | AB16: Revenue | AC16: Change
M17: Investments purchased | N17: 0 | O17: 0 | P17: -4 | Q17: 0 | R17: -3 | S17: -7 | T17: -8 | U17: -3 | V17: -117 | W17: -869 | X17: -825 | Y17: -744 | AA17: FY 2021 | AB17: 48644
M18: Investments sold | N18: 0 | O18: 0 | P18: 0 | Q18: 5 | R18: 0 | S18: 0 | T18: 0 | U18: 0 | V18: 82 | W18: 633 | X18: 598 | Y18: 941 | AA18: FY 2022 | AB18: 51610 | AC18: =AB18/AB17-1 -> 0.060973604
M19: Interest received | N19: 7 | O19: 8 | P19: 12 | Q19: 10 | R19: 5 | S19: 8 | T19: 8 | U19: 5 | V19: 16 | W19: 23 | X19: 22 | Y19: 12 | AA19: FY2023 | AB19: 48932 | AC19: =AB19/AB18-1 -> -0.051889169
M20: Dividends received | N20: 1 | O20: 0 | P20: 0 | Q20: 0 | R20: 0 | S20: 0 | T20: 0 | U20: 1 | V20: 0 | W20: 0 | X20: 0 | Y20: 0 | AA20: FY 2024 | AB20: 55853 | AC20: =AB20/AB19-1 -> 0.14144118
M21: Acquisition of companies | N21: 0 | O21: 0 | P21: 0 | Q21: 0 | R21: -1 | S21: 0 | T21: 0 | U21: 0 | V21: 0 | W21: 0 | X21: 0 | Y21: -203 | AA21: FY 2025 | AB21: 53962 | AC21: =AB21/AB20-1 -> -0.033856731
M22: Inter corporate deposits | N22: 0 | O22: 0 | P22: 0 | Q22: 0 | R22: -1 | S22: -16 | T22: -2 | U22: 0 | V22: 0 | W22: 0 | X22: 0 | Y22: 0 | AA22: FY 2026 | AB22: 60141 | AC22: =AB22/AB21-1 -> 0.1145065
M23: Other investing items | N23: 32 | O23: -51 | P23: 15 | Q23: 94 | R23: -31 | S23: -28 | T23: -5 | U23: -116 | V23: -305 | W23: 340 | X23: 83 | Y23: -49
M24: Cash from Financing Activity - | N24: -7 | O24: 93 | P24: -1 | Q24: -7 | R24: -9 | S24: -52 | T24: -61 | U24: -44 | V24: 143 | W24: -102 | X24: -118 | Y24: -147 | AA24: capex plans
M25: Proceeds from shares | N25: 1 | O25: 100 | P25: 0 | Q25: 0 | R25: 0 | S25: 0 | T25: 0 | U25: 27 | V25: 280 | W25: 1 | X25: 0 | Y25: 0 | AA25: FY26: ~?2,170 Mn invested; net block +?792 Mn to ?8,924 Mn; CWIP ?758 Mn (Gurugram, Pune, Hennur). Strong cash (~?5,942 Mn in cash/FDs/MFs). 5-year ambition: Add >2,500 beds to ~5,000 total; invest ~?2,200 Cr (mostly internal accruals). Upcoming: Coimbatore (~130 beds, H2 FY28), Gurugram (Sector 44 hub ~325 + Sector 56 spoke ~125), Pune (~150), Seegehalli Bengaluru spoke (~80), more spokes. Asset-light leases preferred.
M26: Proceeds from borrowings | N26: 0 | O26: 0 | P26: 13 | Q26: 1 | R26: 37 | S26: 5 | T26: 0 | U26: 0 | V26: 0 | W26: 0 | X26: 0 | Y26: 0
M27: Repayment of borrowings | N27: -3 | O27: -3 | P27: -10 | Q27: -3 | R27: -2 | S27: -1 | T27: -9 | U27: -6 | V27: -40 | W27: 0 | X27: 0 | Y27: 0
M28: Interest paid fin | N28: -2 | O28: -2 | P28: -1 | Q28: -2 | R28: -1 | S28: -5 | T28: -5 | U28: -5 | V28: -3 | W28: 0 | X28: 0 | Y28: -78
M29: Dividends paid | N29: -2 | O29: -3 | P29: -3 | Q29: -3 | R29: -6 | S29: -17 | T29: 0 | U29: -9 | V29: -20 | W29: -31 | X29: -30 | Y29: -30
M30: Financial liabilities | N30: 0 | O30: 0 | P30: 0 | Q30: 0 | R30: -37 | S30: -39 | T30: -44 | U30: -52 | V30: -59 | W30: -72 | X30: -87 | Y30: -18
M31: Other financing items | N31: 0 | O31: 0 | P31: 0 | Q31: 0 | R31: 0 | S31: 4 | T31: -2 | U31: 0 | V31: -14 | W31: 0 | X31: 0 | Y31: -21
M32: Net Cash Flow | N32: -1 | O32: 3 | P32: 1 | Q32: -2 | R32: 2 | S32: 2 | T32: -1 | U32: 4 | V32: 7 | W32: -7 | X32: 10 | Y32: 14
M33: Free Cash Flow | N33: -35 | O33: -46 | P33: -21 | Q33: -103 | R33: 42 | S33: 96 | T33: 67 | U33: 162 | V33: 188 | W33: -32 | X33: 250 | Y33: 204
M34: CFO/OP | N34: 0.95 | O34: 0.88 | P34: 0.79 | Q34: 0.88 | R34: 0.94 | S34: 0.95 | T34: 1.02 | U34: 0.93 | V34: 1.03 | W34: 0.95 | X34: 0.97 | Y34: 0.95

Sheet Closing
A1: Price | B1: Close | C1: Volume | D1: Close | E1: Volume | P1: Date | Q1: Rainbow_Hospitals_Close | R1: Nifty_500_Close
A2: Ticker | B2: RAINBOW.NS | C2: RAINBOW.NS | D2: Nifty 500 | E2: Nifty 500 | P2: 44712 | Q2: 490.58237 | R2: 14119.581 | V2: rainb beta | W2: mkt beta | Y2: adjusted beta
A3: Date | M3: RAINBOW | N3: NIIFTY500 | P3: 44742 | Q3: 459.74826 | R3: 13387.532 | S3: =LN(Q3/Q2) -> -0.064914109 | T3: =LN(R3/R2) -> -0.053238718 | V3: =SLOPE(S3:S53,T3:T53) -> 0.7584218 | W3: 1 | Y3: =(V3*0.75)+(W3*0.25) -> 0.81881635
A4: 44691 | B4: 444.20789 | C4: 17359525 | D4: 16240.05 | E4: 283100 | J4: {=B4:B1063/B4} -> 1 | K4: {=E4:E1063/E4} -> 1 | M4: =B4/$B$4*100 -> 100 | N4: =D4/$D$4*100 -> 100 | P4: 44773 | Q4: 482.49149 | R4: 14665.631 | S4: =LN(Q4/Q3) -> 0.048284194 | T4: =LN(R4/R3) -> 0.091182877
A5: 44692 | B5: 476.86728 | C5: 5524324 | D5: 16167.1 | E5: 284300 | G5: =LN(B5/B4) -> 0.070945547 | H5: =LN(D5/D4) -> -0.0045021126 | J5: 1.0735228 | K5: 1.0042388 | M5: =B5/$B$4*100 -> 107.35228 | N5: =D5/$D$4*100 -> 99.550801 | P5: 44804 | Q5: 602.57172 | R5: 15325.029 | S5: =LN(Q5/Q4) -> 0.22224342 | T5: =LN(R5/R4) -> 0.043980674
A6: 44693 | B6: 455.99881 | C6: 1681626 | D6: 15808 | E6: 314900 | G6: =LN(B6/B5) -> -0.044748012 | H6: =LN(D6/D5) -> -0.022462148 | J6: 1.0265437 | K6: 1.1123278 | M6: =B6/$B$4*100 -> 102.65437 | N6: =D6/$D$4*100 -> 97.339603 | P6: 44834 | Q6: 624.55133 | R6: 14829.33 | S6: =LN(Q6/Q5) -> 0.035826831 | T6: =LN(R6/R5) -> -0.032880412
A7: 44694 | B7: 450.32532 | C7: 631619 | D7: 15782.15 | E7: 369100 | G7: =LN(B7/B6) -> -0.01251995 | H7: =LN(D7/D6) -> -0.0016365617 | J7: 1.0137716 | K7: 1.3037796 | M7: =B7/$B$4*100 -> 101.37716 | N7: =D7/$D$4*100 -> 97.180431 | P7: 44865 | Q7: 682.17029 | R7: 15423.979 | S7: =LN(Q7/Q6) -> 0.088245795 | T7: =LN(R7/R6) -> 0.039316427
A8: 44697 | B8: 430.73959 | C8: 725695 | D8: 15842.3 | E8: 217600 | G8: =LN(B8/B7) -> -0.044466533 | H8: =LN(D8/D7) -> 0.0038039862 | J8: 0.9696802 | K8: 0.76863299 | M8: =B8/$B$4*100 -> 96.96802 | N8: =D8/$D$4*100 -> 97.550808 | P8: 44895 | Q8: 738.10614 | R8: 15946.13 | S8: =LN(Q8/Q7) -> 0.07880832 | T8: =LN(R8/R7) -> 0.033292751
A9: 44698 | B9: 414.85388 | C9: 911509 | D9: 16259.3 | E9: 295700 | G9: =LN(B9/B8) -> -0.03757735 | H9: =LN(D9/D8) -> 0.025981475 | J9: 0.93391832 | K9: 1.0445072 | M9: =B9/$B$4*100 -> 93.391832 | N9: =D9/$D$4*100 -> 100.11853 | P9: 44926 | Q9: 731.81952 | R9: 15448.829 | S9: =LN(Q9/Q8) -> -0.0085537107 | T9: =LN(R9/R8) -> -0.031682945
A10: 44699 | B10: 435.5744 | C10: 2149029 | D10: 16240.3 | E10: 290400 | G10: =LN(B10/B9) -> 0.048739258 | H10: =LN(D10/D9) -> -0.0011692453 | J10: 0.98056432 | K10: 1.0257859 | M10: =B10/$B$4*100 -> 98.056432 | N10: =D10/$D$4*100 -> 100.00154 | P10: 44957 | Q10: 759.29254 | R10: 14935.5 | S10: =LN(Q10/Q9) -> 0.036853208 | T10: =LN(R10/R9) -> -0.033792285
A11: 44700 | B11: 445.49057 | C11: 924014 | D11: 15809.4 | E11: 313900 | G11: =LN(B11/B10) -> 0.022510456 | H11: =LN(D11/D10) -> -0.026891071 | J11: 1.0028876 | K11: 1.1087955 | M11: =B11/$B$4*100 -> 100.28876 | N11: =D11/$D$4*100 -> 97.348226 | P11: 44985 | Q11: 733.15607 | R11: 14518.75 | S11: =LN(Q11/Q10) -> -0.035028539 | T11: =LN(R11/R10) -> -0.028300012
A12: 44701 | B12: 471.34189 | C12: 847932 | D12: 16266.15 | E12: 252400 | G12: =LN(B12/B11) -> 0.056407629 | H12: =LN(D12/D11) -> 0.028481561 | J12: 1.061084 | K12: 0.89155775 | M12: =B12/$B$4*100 -> 106.1084 | N12: =D12/$D$4*100 -> 100.16072 | P12: 45016 | Q12: 723.20642 | R12: 14557.85 | S12: =LN(Q12/Q11) -> -0.013663907 | T12: =LN(R12/R11) -> 0.0026894227
A13: 44704 | B13: 457.67624 | C13: 253056 | D13: 16214.7 | E13: 293800 | G13: =LN(B13/B12) -> -0.029421676 | H13: =LN(D13/D12) -> -0.0031680352 | J13: 1.0303199 | K13: 1.0377958 | M13: =B13/$B$4*100 -> 103.03199 | N13: =D13/$D$4*100 -> 99.843907 | P13: 45046 | Q13: 783.44879 | R13: 15219.55 | S13: =LN(Q13/Q12) -> 0.080011014 | T13: =LN(R13/R12) -> 0.044450433
A14: 44705 | B14: 468.97385 | C14: 460881 | D14: 16125.15 | E14: 249800 | G14: =LN(B14/B13) -> 0.02438497 | H14: =LN(D14/D13) -> -0.0055380611 | J14: 1.0557531 | K14: 0.88237372 | M14: =B14/$B$4*100 -> 105.57531 | N14: =D14/$D$4*100 -> 99.292493 | P14: 45077 | Q14: 979.42242 | R14: 15766.4 | S14: =LN(Q14/Q13) -> 0.22325733 | T14: =LN(R14/R13) -> 0.035300345
A15: 44706 | B15: 470.00983 | C15: 474840 | D15: 16025.8 | E15: 243300 | G15: =LN(B15/B14) -> 0.0022065999 | H15: =LN(D15/D14) -> -0.0061802778 | J15: 1.0580853 | K15: 0.85941363 | M15: =B15/$B$4*100 -> 105.80853 | N15: =D15/$D$4*100 -> 98.680731 | P15: 45107 | Q15: 954.43396 | R15: 16430 | S15: =LN(Q15/Q14) -> -0.025844582 | T15: =LN(R15/R14) -> 0.041227814
A16: 44707 | B16: 483.28082 | C16: 545714 | D16: 16170.15 | E16: 314300 | G16: =LN(B16/B15) -> 0.027844296 | H16: =LN(D16/D15) -> 0.0089670628 | J16: 1.0879609 | K16: 1.1102084 | M16: =B16/$B$4*100 -> 108.79609 | N16: =D16/$D$4*100 -> 99.569586 | P16: 45138 | Q16: 1096.3428 | R16: 17059 | S16: =LN(Q16/Q15) -> 0.13861672 | T16: =LN(R16/R15) -> 0.037568992
... A53: 44760 | B53: 500.39987 | C53: 311768 | D53: 16278.5 | E53: 227700 | G53: =LN(B53/B52) -> 0.040439942 | H53: =LN(D53/D52) -> 0.014186202 | J53: 1.1264993 | K53: 0.80430943 | M53: =B53/$B$4*100 -> 112.64993 | N53: =D53/$D$4*100 -> 100.23676 | P53: 46265 | Q53: 1439.8 | R53: 23608.75 | S53: =LN(Q53/Q52) -> -0.057752438 | T53: =LN(R53/R52) -> 0.0062907585
A54: 44761 | B54: 491.17432 | C54: 106766 | D54: 16340.55 | E54: 222600 | G54: =LN(B54/B53) -> -0.018608434 | H54: =LN(D54/D53) -> 0.0038045179 | J54: 1.1057307 | K54: 0.7862946 | M54: =B54/$B$4*100 -> 110.57307 | N54: =D54/$D$4*100 -> 100.61884 | R54: - | S54: - | T54: - | U54: - | V54: -
A55: 44762 | B55: 481.01144 | C55: 91632 | D55: 16520.85 | E55: 284400 | G55: =LN(B55/B54) -> -0.020908026 | H55: =LN(D55/D54) -> 0.010973459 | J55: 1.0828521 | K55: 1.004592 | M55: =B55/$B$4*100 -> 108.28521 | N55: =D55/$D$4*100 -> 101.72906
A56: 44763 | B56: 486.7836 | C56: 123136 | D56: 16605.25 | E56: 243600 | G56: =LN(B56/B55) -> 0.011928609 | H56: =LN(D56/D55) -> 0.0050957145 | J56: 1.0958464 | K56: 0.86047333 | M56: =B56/$B$4*100 -> 109.58464 | N56: =D56/$D$4*100 -> 102.24876
A57: 44764 | B57: 481.70212 | C57: 50491 | D57: 16719.449 | E57: 190900 | G57: =LN(B57/B56) -> -0.01049376 | H57: =LN(D57/D56) -> 0.0068537552 | J57: 1.0844069 | K57: 0.67432003 | M57: =B57/$B$4*100 -> 108.44069 | N57: =D57/$D$4*100 -> 102.95196
A58: 44767 | B58: 486.68491 | C58: 80605 | D58: 16631 | E58: 211400 | G58: =LN(B58/B57) -> 0.010290993 | H58: =LN(D58/D57) -> -0.005304242 | J58: 1.0956242 | K58: 0.7467326 | M58: =B58/$B$4*100 -> 109.56242 | N58: =D58/$D$4*100 -> 102.40732
A59: 44768 | B59: 478.69269 | C59: 58026 | D59: 16483.85 | E59: 208200 | G59: =LN(B59/B58) -> -0.016558082 | H59: =LN(D59/D58) -> -0.0088873337 | J59: 1.0776321 | K59: 0.73542918 | M59: =B59/$B$4*100 -> 107.76321 | N59: =D59/$D$4*100 -> 101.50123
A60: 44769 | B60: 483.97153 | C60: 115421 | D60: 16641.801 | E60: 185200 | G60: =LN(B60/B59) -> 0.010967255 | H60: =LN(D60/D59) -> 0.0095365596 | J60: 1.0895158 | K60: 0.6541858 | M60: =B60/$B$4*100 -> 108.95158 | N60: =D60/$D$4*100 -> 102.47383
A61: 44770 | B61: 485.74753 | C61: 137299 | D61: 16929.6 | E61: 376300 | G61: =LN(B61/B60) -> 0.0036629227 | H61: =LN(D61/D60) -> 0.017145897 | J61: 1.093514 | K61: 1.3292123 | M61: =B61/$B$4*100 -> 109.3514 | N61: =D61/$D$4*100 -> 104.24598
A62: 44771 | B62: 482.49149 | C62: 168227 | D62: 17158.25 | E62: 436100 | G62: =LN(B62/B61) -> -0.0067257252 | H62: =LN(D62/D61) -> 0.013415561 | J62: 1.086184 | K62: 1.5404451 | M62: =B62/$B$4*100 -> 108.6184 | N62: =D62/$D$4*100 -> 105.65392
A63: 44774 | B63: 482.34344 | C63: 69281 | D63: 17340.051 | E63: 381500 | G63: =LN(B63/B62) -> -0.00030687275 | H63: =LN(D63/D62) -> 0.010539792 | J63: 1.0858507 | K63: 1.3475804 | M63: =B63/$B$4*100 -> 108.58507 | N63: =D63/$D$4*100 -> 106.77338
A64: 44775 | B64: 483.23148 | C64: 38372 | D64: 17345.449 | E64: 333600 | G64: =LN(B64/B63) -> 0.0018393834 | H64: =LN(D64/D63) -> 0.00031127921 | J64: 1.0878498 | K64: 1.1783822 | M64: =B64/$B$4*100 -> 108.78498 | N64: =D64/$D$4*100 -> 106.80663
A65: 44776 | B65: 469.71378 | C65: 62900 | D65: 17388.15 | E65: 285400 | G65: =LN(B65/B64) -> -0.028372264 | H65: =LN(D65/D64) -> 0.0024587831 | J65: 1.0574188 | K65: 1.0081243 | M65: =B65/$B$4*100 -> 105.74188 | N65: =D65/$D$4*100 -> 107.06956
A66: 44777 | B66: 455.45618 | C66: 105453 | D66: 17382 | E66: 325000 | G66: =LN(B66/B65) -> -0.030824018 | H66: =LN(D66/D65) -> -0.00035377418 | J66: 1.0253221 | K66: 1.1480042 | M66: =B66/$B$4*100 -> 102.53221 | N66: =D66/$D$4*100 -> 107.03169
... A1063: 46252 | B1063: 1458.7 | C1063: 52308 | D1063: 24252 | E1063: 259300 | G1063: =LN(B1063/B1062) -> -0.013482466 | H1063: =LN(D1063/D1062) -> 0.00083122079 | J1063: 3.2838227 | K1063: 0.91593077 | M1063: =B1063/$B$4*100 -> 328.38227 | N1063: =D1063/$D$4*100 -> 149.33452
A1064: 46253 | B1064: 1461.8 | C1064: 42464 | D1064: 24334.551 | G1064: =LN(B1064/B1063) -> 0.0021229918 | H1064: =LN(D1064/D1063) -> 0.0033980951 | M1064: =B1064/$B$4*100 -> 329.08017 | N1064: =D1064/$D$4*100 -> 149.84283
A1065: 46254 | C1065: 90078 | G1065: 0 | H1065: =LN(D1065/D1064) -> #NUM!
A1066: 46255 | C1066: 86438 | G1066: 0 | H1066: =LN(D1066/D1065) -> #DIV/0!
A1067: 46259 | B1067: =Profile!$C$43 -> 1439.8 | C1067: 31536 | G1067: 0 | H1067: =LN(D1067/D1066) -> #DIV/0!
B1068: - | C1068: - | D1068: - | E1068: - | F1068: - | G1068: - | H1068: - | I1068: - | J1068: - | K1068: - | L1068: - | M1068: - | N1068: - | O1068: - | P1068: -
